Workbook

Sheet customer_churn_dataset
A1: customer_id | B1: plan_type | C1: contract_type | D1: monthly_charge | E1: tenure_months | F1: signup_date | G1: payment_method | H1: autopay_enabled | I1: usage_score | J1: logins_per_month | K1: features_used | L1: support_tickets_6m | M1: complaint_unresolved | N1: total_revenue | O1: churned | P1: churn_date | Q1: last_active_date | R1: signup_year | S1: Tenure_budget | T1: Risk_score | U1: Missing_value_flag | V1: Risk_level
A2: CUST100500 | B2: Standard | C2: Month-to-month | D2: 21.31 | E2: 20 | F2: 43833 | G2: Credit card | H2: 1 | I2: 78.8 | J2: 8 | K2: 8 | L2: 2 | M2: 1 | N2: 426.2 | O2: 0 | Q2: 44441 | R2: =IF(ISBLANK(F2),"Missing",IFERROR(YEAR(F2),"Missing")) -> 2020 | S2: =IF(ISBLANK(E2),"Missing",IF(E2<6,"0-6mo",IF(E2<12,"6-12mo",IF(E2<24,"12-24mo","24mo+")))) -> 12-24mo | T2: =IF(ISBLANK(C2),0,IF(C2="Month-to-month",2,IF(C2="One year",1,0)))+IF(ISBLANK(I2),0,IF(I2<40,2,IF(I2<55,1,0)))+IF(ISBLANK(M2),0,IF(M2=1,3,0))+IF(ISBLANK(L2),0,IF(L2>=2,1,0))+IF(ISBLANK(E2),0,IF(E2<12,1,0)) -> 6 | U2: =IF((ISBLANK(B2)*1+ISBLANK(C2)*1+ISBLANK(D2)*1+ISBLANK(E2)*1+ISBLANK(F2)*1+ISBLANK(I2)*1+ISBLANK(J2)*1+ISBLANK(K2)*1+ISBLANK(L2)*1+ISBLANK(M2)*1+ISBLANK(N2)*1+ISBLANK(O2)*1)>0,"Missing Data","OK") -> OK | V2: =IF(T2>=6,"High Risk",IF(T2>=3,"Medium Risk","Low Risk")) -> High Risk
A3: CUST101041 | B3: Standard | C3: Month-to-month | D3: 19.8 | E3: 33 | F3: 43833 | G3: Manual/Invoice | H3: 1 | I3: 46.1 | J3: 20 | K3: 4 | L3: 0 | M3: 0 | N3: 653.4 | O3: 0 | Q3: 44837 | R3: =IF(ISBLANK(F3),"Missing",IFERROR(YEAR(F3),"Missing")) -> 2020 | S3: =IF(ISBLANK(E3),"Missing",IF(E3<6,"0-6mo",IF(E3<12,"6-12mo",IF(E3<24,"12-24mo","24mo+")))) -> 24mo+ | T3: =IF(ISBLANK(C3),0,IF(C3="Month-to-month",2,IF(C3="One year",1,0)))+IF(ISBLANK(I3),0,IF(I3<40,2,IF(I3<55,1,0)))+IF(ISBLANK(M3),0,IF(M3=1,3,0))+IF(ISBLANK(L3),0,IF(L3>=2,1,0))+IF(ISBLANK(E3),0,IF(E3<12,1,0)) -> 3 | U3: =IF((ISBLANK(B3)*1+ISBLANK(C3)*1+ISBLANK(D3)*1+ISBLANK(E3)*1+ISBLANK(F3)*1+ISBLANK(I3)*1+ISBLANK(J3)*1+ISBLANK(K3)*1+ISBLANK(L3)*1+ISBLANK(M3)*1+ISBLANK(N3)*1+ISBLANK(O3)*1)>0,"Missing Data","OK") -> OK | V3: =IF(T3>=6,"High Risk",IF(T3>=3,"Medium Risk","Low Risk")) -> Medium Risk
A4: CUST100305 | B4: Premium | C4: Month-to-month | D4: 40.58 | E4: 18 | F4: 43834 | G4: Bank transfer | H4: 1 | I4: 49.8 | J4: 17 | K4: 6 | L4: 3 | M4: 0 | N4: 730.44 | O4: 0 | Q4: 44381 | R4: =IF(ISBLANK(F4),"Missing",IFERROR(YEAR(F4),"Missing")) -> 2020 | S4: =IF(ISBLANK(E4),"Missing",IF(E4<6,"0-6mo",IF(E4<12,"6-12mo",IF(E4<24,"12-24mo","24mo+")))) -> 12-24mo | T4: =IF(ISBLANK(C4),0,IF(C4="Month-to-month",2,IF(C4="One year",1,0)))+IF(ISBLANK(I4),0,IF(I4<40,2,IF(I4<55,1,0)))+IF(ISBLANK(M4),0,IF(M4=1,3,0))+IF(ISBLANK(L4),0,IF(L4>=2,1,0))+IF(ISBLANK(E4),0,IF(E4<12,1,0)) -> 4 | U4: =IF((ISBLANK(B4)*1+ISBLANK(C4)*1+ISBLANK(D4)*1+ISBLANK(E4)*1+ISBLANK(F4)*1+ISBLANK(I4)*1+ISBLANK(J4)*1+ISBLANK(K4)*1+ISBLANK(L4)*1+ISBLANK(M4)*1+ISBLANK(N4)*1+ISBLANK(O4)*1)>0,"Missing Data","OK") -> OK | V4: =IF(T4>=6,"High Risk",IF(T4>=3,"Medium Risk","Low Risk")) -> Medium Risk
A5: CUST101045 | B5: Standard | C5: Month-to-month | D5: 20.46 | E5: 57 | F5: 43837 | G5: Credit card | H5: 0 | I5: 42.4 | J5: 10 | K5: 3 | L5: 1 | M5: 0 | N5: 1166.22 | O5: 0 | Q5: 45572 | R5: =IF(ISBLANK(F5),"Missing",IFERROR(YEAR(F5),"Missing")) -> 2020 | S5: =IF(ISBLANK(E5),"Missing",IF(E5<6,"0-6mo",IF(E5<12,"6-12mo",IF(E5<24,"12-24mo","24mo+")))) -> 24mo+ | T5: =IF(ISBLANK(C5),0,IF(C5="Month-to-month",2,IF(C5="One year",1,0)))+IF(ISBLANK(I5),0,IF(I5<40,2,IF(I5<55,1,0)))+IF(ISBLANK(M5),0,IF(M5=1,3,0))+IF(ISBLANK(L5),0,IF(L5>=2,1,0))+IF(ISBLANK(E5),0,IF(E5<12,1,0)) -> 3 | U5: =IF((ISBLANK(B5)*1+ISBLANK(C5)*1+ISBLANK(D5)*1+ISBLANK(E5)*1+ISBLANK(F5)*1+ISBLANK(I5)*1+ISBLANK(J5)*1+ISBLANK(K5)*1+ISBLANK(L5)*1+ISBLANK(M5)*1+ISBLANK(N5)*1+ISBLANK(O5)*1)>0,"Missing Data","OK") -> OK | V5: =IF(T5>=6,"High Risk",IF(T5>=3,"Medium Risk","Low Risk")) -> Medium Risk
A6: CUST101341 | B6: Standard | C6: Month-to-month | D6: 20.96 | E6: 9 | F6: 43837 | G6: Bank transfer | H6: 1 | I6: 54.2 | J6: 17 | K6: 6 | L6: 2 | M6: 1 | N6: 188.64 | O6: 0 | Q6: 44110 | R6: =IF(ISBLANK(F6),"Missing",IFERROR(YEAR(F6),"Missing")) -> 2020 | S6: =IF(ISBLANK(E6),"Missing",IF(E6<6,"0-6mo",IF(E6<12,"6-12mo",IF(E6<24,"12-24mo","24mo+")))) -> 6-12mo | T6: =IF(ISBLANK(C6),0,IF(C6="Month-to-month",2,IF(C6="One year",1,0)))+IF(ISBLANK(I6),0,IF(I6<40,2,IF(I6<55,1,0)))+IF(ISBLANK(M6),0,IF(M6=1,3,0))+IF(ISBLANK(L6),0,IF(L6>=2,1,0))+IF(ISBLANK(E6),0,IF(E6<12,1,0)) -> 8 | U6: =IF((ISBLANK(B6)*1+ISBLANK(C6)*1+ISBLANK(D6)*1+ISBLANK(E6)*1+ISBLANK(F6)*1+ISBLANK(I6)*1+ISBLANK(J6)*1+ISBLANK(K6)*1+ISBLANK(L6)*1+ISBLANK(M6)*1+ISBLANK(N6)*1+ISBLANK(O6)*1)>0,"Missing Data","OK") -> OK | V6: =IF(T6>=6,"High Risk",IF(T6>=3,"Medium Risk","Low Risk")) -> High Risk
A7: CUST101313 | B7: Premium | C7: One year | D7: 38.61 | E7: 8 | F7: 43839 | G7: Credit card | H7: 0 | I7: 45.7 | J7: 14 | K7: 2 | L7: 1 | M7: 1 | N7: 308.88 | O7: 1 | P7: 44082 | Q7: 44082 | R7: =IF(ISBLANK(F7),"Missing",IFERROR(YEAR(F7),"Missing")) -> 2020 | S7: =IF(ISBLANK(E7),"Missing",IF(E7<6,"0-6mo",IF(E7<12,"6-12mo",IF(E7<24,"12-24mo","24mo+")))) -> 6-12mo | T7: =IF(ISBLANK(C7),0,IF(C7="Month-to-month",2,IF(C7="One year",1,0)))+IF(ISBLANK(I7),0,IF(I7<40,2,IF(I7<55,1,0)))+IF(ISBLANK(M7),0,IF(M7=1,3,0))+IF(ISBLANK(L7),0,IF(L7>=2,1,0))+IF(ISBLANK(E7),0,IF(E7<12,1,0)) -> 6 | U7: =IF((ISBLANK(B7)*1+ISBLANK(C7)*1+ISBLANK(D7)*1+ISBLANK(E7)*1+ISBLANK(F7)*1+ISBLANK(I7)*1+ISBLANK(J7)*1+ISBLANK(K7)*1+ISBLANK(L7)*1+ISBLANK(M7)*1+ISBLANK(N7)*1+ISBLANK(O7)*1)>0,"Missing Data","OK") -> OK | V7: =IF(T7>=6,"High Risk",IF(T7>=3,"Medium Risk","Low Risk")) -> High Risk
A8: CUST100592 | B8: Basic | C8: Month-to-month | D8: 9.34 | E8: 72 | F8: 43842 | G8: Bank transfer | H8: 0 | I8: 72.8 | J8: 25 | K8: 8 | L8: 1 | M8: 0 | N8: 672.48 | O8: 0 | Q8: 46033 | R8: =IF(ISBLANK(F8),"Missing",IFERROR(YEAR(F8),"Missing")) -> 2020 | S8: =IF(ISBLANK(E8),"Missing",IF(E8<6,"0-6mo",IF(E8<12,"6-12mo",IF(E8<24,"12-24mo","24mo+")))) -> 24mo+ | T8: =IF(ISBLANK(C8),0,IF(C8="Month-to-month",2,IF(C8="One year",1,0)))+IF(ISBLANK(I8),0,IF(I8<40,2,IF(I8<55,1,0)))+IF(ISBLANK(M8),0,IF(M8=1,3,0))+IF(ISBLANK(L8),0,IF(L8>=2,1,0))+IF(ISBLANK(E8),0,IF(E8<12,1,0)) -> 2 | U8: =IF((ISBLANK(B8)*1+ISBLANK(C8)*1+ISBLANK(D8)*1+ISBLANK(E8)*1+ISBLANK(F8)*1+ISBLANK(I8)*1+ISBLANK(J8)*1+ISBLANK(K8)*1+ISBLANK(L8)*1+ISBLANK(M8)*1+ISBLANK(N8)*1+ISBLANK(O8)*1)>0,"Missing Data","OK") -> OK | V8: =IF(T8>=6,"High Risk",IF(T8>=3,"Medium Risk","Low Risk")) -> Low Risk
A9: CUST101076 | B9: Basic | C9: Month-to-month | D9: 10 | E9: 0 | F9: 43843 | G9: Credit card | H9: 0 | I9: 33.9 | J9: 9 | K9: 4 | L9: 1 | M9: 0 | N9: 0 | O9: 1 | P9: 43843 | Q9: 43843 | R9: =IF(ISBLANK(F9),"Missing",IFERROR(YEAR(F9),"Missing")) -> 2020 | S9: =IF(ISBLANK(E9),"Missing",IF(E9<6,"0-6mo",IF(E9<12,"6-12mo",IF(E9<24,"12-24mo","24mo+")))) -> 0-6mo | T9: =IF(ISBLANK(C9),0,IF(C9="Month-to-month",2,IF(C9="One year",1,0)))+IF(ISBLANK(I9),0,IF(I9<40,2,IF(I9<55,1,0)))+IF(ISBLANK(M9),0,IF(M9=1,3,0))+IF(ISBLANK(L9),0,IF(L9>=2,1,0))+IF(ISBLANK(E9),0,IF(E9<12,1,0)) -> 5 | U9: =IF((ISBLANK(B9)*1+ISBLANK(C9)*1+ISBLANK(D9)*1+ISBLANK(E9)*1+ISBLANK(F9)*1+ISBLANK(I9)*1+ISBLANK(J9)*1+ISBLANK(K9)*1+ISBLANK(L9)*1+ISBLANK(M9)*1+ISBLANK(N9)*1+ISBLANK(O9)*1)>0,"Missing Data","OK") -> OK | V9: =IF(T9>=6,"High Risk",IF(T9>=3,"Medium Risk","Low Risk")) -> Medium Risk
A10: CUST101481 | B10: Basic | C10: Month-to-month | D10: 9.77 | E10: 72 | F10: 43843 | G10: PayPal | H10: 0 | I10: 38.9 | J10: 10 | K10: 4 | L10: 1 | M10: 1 | N10: 703.44 | O10: 0 | Q10: 46034 | R10: =IF(ISBLANK(F10),"Missing",IFERROR(YEAR(F10),"Missing")) -> 2020 | S10: =IF(ISBLANK(E10),"Missing",IF(E10<6,"0-6mo",IF(E10<12,"6-12mo",IF(E10<24,"12-24mo","24mo+")))) -> 24mo+ | T10: =IF(ISBLANK(C10),0,IF(C10="Month-to-month",2,IF(C10="One year",1,0)))+IF(ISBLANK(I10),0,IF(I10<40,2,IF(I10<55,1,0)))+IF(ISBLANK(M10),0,IF(M10=1,3,0))+IF(ISBLANK(L10),0,IF(L10>=2,1,0))+IF(ISBLANK(E10),0,IF(E10<12,1,0)) -> 7 | U10: =IF((ISBLANK(B10)*1+ISBLANK(C10)*1+ISBLANK(D10)*1+ISBLANK(E10)*1+ISBLANK(F10)*1+ISBLANK(I10)*1+ISBLANK(J10)*1+ISBLANK(K10)*1+ISBLANK(L10)*1+ISBLANK(M10)*1+ISBLANK(N10)*1+ISBLANK(O10)*1)>0,"Missing Data","OK") -> OK | V10: =IF(T10>=6,"High Risk",IF(T10>=3,"Medium Risk","Low Risk")) -> High Risk
A11: CUST100688 | B11: Standard | C11: One year | D11: 20.96 | E11: 39 | F11: 43845 | G11: PayPal | H11: 1 | I11: 42.3 | J11: 10 | K11: 5 | L11: 1 | M11: 1 | N11: 817.44 | O11: 0 | Q11: 45032 | R11: =IF(ISBLANK(F11),"Missing",IFERROR(YEAR(F11),"Missing")) -> 2020 | S11: =IF(ISBLANK(E11),"Missing",IF(E11<6,"0-6mo",IF(E11<12,"6-12mo",IF(E11<24,"12-24mo","24mo+")))) -> 24mo+ | T11: =IF(ISBLANK(C11),0,IF(C11="Month-to-month",2,IF(C11="One year",1,0)))+IF(ISBLANK(I11),0,IF(I11<40,2,IF(I11<55,1,0)))+IF(ISBLANK(M11),0,IF(M11=1,3,0))+IF(ISBLANK(L11),0,IF(L11>=2,1,0))+IF(ISBLANK(E11),0,IF(E11<12,1,0)) -> 5 | U11: =IF((ISBLANK(B11)*1+ISBLANK(C11)*1+ISBLANK(D11)*1+ISBLANK(E11)*1+ISBLANK(F11)*1+ISBLANK(I11)*1+ISBLANK(J11)*1+ISBLANK(K11)*1+ISBLANK(L11)*1+ISBLANK(M11)*1+ISBLANK(N11)*1+ISBLANK(O11)*1)>0,"Missing Data","OK") -> OK | V11: =IF(T11>=6,"High Risk",IF(T11>=3,"Medium Risk","Low Risk")) -> Medium Risk
A12: CUST100968 | B12: Standard | C12: Month-to-month | D12: 20.71 | E12: 35 | F12: 43845 | G12: Credit card | H12: 0 | I12: 76.7 | J12: 25 | K12: 6 | L12: 0 | M12: 0 | N12: 724.85 | O12: 0 | Q12: 44910 | R12: =IF(ISBLANK(F12),"Missing",IFERROR(YEAR(F12),"Missing")) -> 2020 | S12: =IF(ISBLANK(E12),"Missing",IF(E12<6,"0-6mo",IF(E12<12,"6-12mo",IF(E12<24,"12-24mo","24mo+")))) -> 24mo+ | T12: =IF(ISBLANK(C12),0,IF(C12="Month-to-month",2,IF(C12="One year",1,0)))+IF(ISBLANK(I12),0,IF(I12<40,2,IF(I12<55,1,0)))+IF(ISBLANK(M12),0,IF(M12=1,3,0))+IF(ISBLANK(L12),0,IF(L12>=2,1,0))+IF(ISBLANK(E12),0,IF(E12<12,1,0)) -> 2 | U12: =IF((ISBLANK(B12)*1+ISBLANK(C12)*1+ISBLANK(D12)*1+ISBLANK(E12)*1+ISBLANK(F12)*1+ISBLANK(I12)*1+ISBLANK(J12)*1+ISBLANK(K12)*1+ISBLANK(L12)*1+ISBLANK(M12)*1+ISBLANK(N12)*1+ISBLANK(O12)*1)>0,"Missing Data","OK") -> OK | V12: =IF(T12>=6,"High Risk",IF(T12>=3,"Medium Risk","Low Risk")) -> Low Risk
A13: CUST101408 | B13: Standard | C13: Month-to-month | D13: 20.85 | E13: 19 | F13: 43845 | G13: Credit card | H13: 1 | I13: 47.5 | J13: 20 | K13: 6 | L13: 3 | M13: 0 | N13: 396.15 | O13: 0 | Q13: 44423 | R13: =IF(ISBLANK(F13),"Missing",IFERROR(YEAR(F13),"Missing")) -> 2020 | S13: =IF(ISBLANK(E13),"Missing",IF(E13<6,"0-6mo",IF(E13<12,"6-12mo",IF(E13<24,"12-24mo","24mo+")))) -> 12-24mo | T13: =IF(ISBLANK(C13),0,IF(C13="Month-to-month",2,IF(C13="One year",1,0)))+IF(ISBLANK(I13),0,IF(I13<40,2,IF(I13<55,1,0)))+IF(ISBLANK(M13),0,IF(M13=1,3,0))+IF(ISBLANK(L13),0,IF(L13>=2,1,0))+IF(ISBLANK(E13),0,IF(E13<12,1,0)) -> 4 | U13: =IF((ISBLANK(B13)*1+ISBLANK(C13)*1+ISBLANK(D13)*1+ISBLANK(E13)*1+ISBLANK(F13)*1+ISBLANK(I13)*1+ISBLANK(J13)*1+ISBLANK(K13)*1+ISBLANK(L13)*1+ISBLANK(M13)*1+ISBLANK(N13)*1+ISBLANK(O13)*1)>0,"Missing Data","OK") -> OK | V13: =IF(T13>=6,"High Risk",IF(T13>=3,"Medium Risk","Low Risk")) -> Medium Risk
A14: CUST101084 | B14: Premium | C14: Month-to-month | D14: 41.61 | E14: 3 | F14: 43847 | G14: PayPal | H14: 1 | I14: 80 | J14: 19 | K14: 8 | L14: 2 | M14: 1 | N14: 124.83 | O14: 1 | P14: 43938 | Q14: 43938 | R14: =IF(ISBLANK(F14),"Missing",IFERROR(YEAR(F14),"Missing")) -> 2020 | S14: =IF(ISBLANK(E14),"Missing",IF(E14<6,"0-6mo",IF(E14<12,"6-12mo",IF(E14<24,"12-24mo","24mo+")))) -> 0-6mo | T14: =IF(ISBLANK(C14),0,IF(C14="Month-to-month",2,IF(C14="One year",1,0)))+IF(ISBLANK(I14),0,IF(I14<40,2,IF(I14<55,1,0)))+IF(ISBLANK(M14),0,IF(M14=1,3,0))+IF(ISBLANK(L14),0,IF(L14>=2,1,0))+IF(ISBLANK(E14),0,IF(E14<12,1,0)) -> 7 | U14: =IF((ISBLANK(B14)*1+ISBLANK(C14)*1+ISBLANK(D14)*1+ISBLANK(E14)*1+ISBLANK(F14)*1+ISBLANK(I14)*1+ISBLANK(J14)*1+ISBLANK(K14)*1+ISBLANK(L14)*1+ISBLANK(M14)*1+ISBLANK(N14)*1+ISBLANK(O14)*1)>0,"Missing Data","OK") -> OK | V14: =IF(T14>=6,"High Risk",IF(T14>=3,"Medium Risk","Low Risk")) -> High Risk
A15: CUST101306 | B15: Standard | C15: One year | D15: 19.23 | E15: 1 | F15: 43850 | G15: Bank transfer | H15: 1 | I15: 59.1 | J15: 17 | K15: 5 | L15: 1 | M15: 0 | N15: 19.23 | O15: 0 | Q15: 43880 | R15: =IF(ISBLANK(F15),"Missing",IFERROR(YEAR(F15),"Missing")) -> 2020 | S15: =IF(ISBLANK(E15),"Missing",IF(E15<6,"0-6mo",IF(E15<12,"6-12mo",IF(E15<24,"12-24mo","24mo+")))) -> 0-6mo | T15: =IF(ISBLANK(C15),0,IF(C15="Month-to-month",2,IF(C15="One year",1,0)))+IF(ISBLANK(I15),0,IF(I15<40,2,IF(I15<55,1,0)))+IF(ISBLANK(M15),0,IF(M15=1,3,0))+IF(ISBLANK(L15),0,IF(L15>=2,1,0))+IF(ISBLANK(E15),0,IF(E15<12,1,0)) -> 2 | U15: =IF((ISBLANK(B15)*1+ISBLANK(C15)*1+ISBLANK(D15)*1+ISBLANK(E15)*1+ISBLANK(F15)*1+ISBLANK(I15)*1+ISBLANK(J15)*1+ISBLANK(K15)*1+ISBLANK(L15)*1+ISBLANK(M15)*1+ISBLANK(N15)*1+ISBLANK(O15)*1)>0,"Missing Data","OK") -> OK | V15: =IF(T15>=6,"High Risk",IF(T15>=3,"Medium Risk","Low Risk")) -> Low Risk
A16: CUST100916 | B16: Basic | C16: Month-to-month | D16: 10.61 | E16: 19 | F16: 43850 | G16: Credit card | H16: 1 | I16: 90.1 | J16: 21 | K16: 10 | L16: 0 | M16: 0 | N16: 201.59 | O16: 0 | Q16: 44428 | R16: =IF(ISBLANK(F16),"Missing",IFERROR(YEAR(F16),"Missing")) -> 2020 | S16: =IF(ISBLANK(E16),"Missing",IF(E16<6,"0-6mo",IF(E16<12,"6-12mo",IF(E16<24,"12-24mo","24mo+")))) -> 12-24mo | T16: =IF(ISBLANK(C16),0,IF(C16="Month-to-month",2,IF(C16="One year",1,0)))+IF(ISBLANK(I16),0,IF(I16<40,2,IF(I16<55,1,0)))+IF(ISBLANK(M16),0,IF(M16=1,3,0))+IF(ISBLANK(L16),0,IF(L16>=2,1,0))+IF(ISBLANK(E16),0,IF(E16<12,1,0)) -> 2 | U16: =IF((ISBLANK(B16)*1+ISBLANK(C16)*1+ISBLANK(D16)*1+ISBLANK(E16)*1+ISBLANK(F16)*1+ISBLANK(I16)*1+ISBLANK(J16)*1+ISBLANK(K16)*1+ISBLANK(L16)*1+ISBLANK(M16)*1+ISBLANK(N16)*1+ISBLANK(O16)*1)>0,"Missing Data","OK") -> OK | V16: =IF(T16>=6,"High Risk",IF(T16>=3,"Medium Risk","Low Risk")) -> Low Risk
A17: CUST100655 | B17: Basic | C17: Month-to-month | D17: 9.1 | E17: 18 | F17: 43850 | G17: Bank transfer | H17: 0 | I17: 88.9 | J17: 30 | K17: 10 | L17: 0 | M17: 0 | N17: 163.8 | O17: 1 | P17: 44397 | Q17: 44397 | R17: =IF(ISBLANK(F17),"Missing",IFERROR(YEAR(F17),"Missing")) -> 2020 | S17: =IF(ISBLANK(E17),"Missing",IF(E17<6,"0-6mo",IF(E17<12,"6-12mo",IF(E17<24,"12-24mo","24mo+")))) -> 12-24mo | T17: =IF(ISBLANK(C17),0,IF(C17="Month-to-month",2,IF(C17="One year",1,0)))+IF(ISBLANK(I17),0,IF(I17<40,2,IF(I17<55,1,0)))+IF(ISBLANK(M17),0,IF(M17=1,3,0))+IF(ISBLANK(L17),0,IF(L17>=2,1,0))+IF(ISBLANK(E17),0,IF(E17<12,1,0)) -> 2 | U17: =IF((ISBLANK(B17)*1+ISBLANK(C17)*1+ISBLANK(D17)*1+ISBLANK(E17)*1+ISBLANK(F17)*1+ISBLANK(I17)*1+ISBLANK(J17)*1+ISBLANK(K17)*1+ISBLANK(L17)*1+ISBLANK(M17)*1+ISBLANK(N17)*1+ISBLANK(O17)*1)>0,"Missing Data","OK") -> OK | V17: =IF(T17>=6,"High Risk",IF(T17>=3,"Medium Risk","Low Risk")) -> Low Risk
A18: CUST100826 | B18: Basic | C18: Month-to-month | D18: 10.72 | E18: 25 | F18: 43851 | G18: PayPal | H18: 1 | I18: 61.2 | J18: 17 | K18: 6 | L18: 0 | M18: 0 | N18: 268 | O18: 0 | Q18: 44612 | R18: =IF(ISBLANK(F18),"Missing",IFERROR(YEAR(F18),"Missing")) -> 2020 | S18: =IF(ISBLANK(E18),"Missing",IF(E18<6,"0-6mo",IF(E18<12,"6-12mo",IF(E18<24,"12-24mo","24mo+")))) -> 24mo+ | T18: =IF(ISBLANK(C18),0,IF(C18="Month-to-month",2,IF(C18="One year",1,0)))+IF(ISBLANK(I18),0,IF(I18<40,2,IF(I18<55,1,0)))+IF(ISBLANK(M18),0,IF(M18=1,3,0))+IF(ISBLANK(L18),0,IF(L18>=2,1,0))+IF(ISBLANK(E18),0,IF(E18<12,1,0)) -> 2 | U18: =IF((ISBLANK(B18)*1+ISBLANK(C18)*1+ISBLANK(D18)*1+ISBLANK(E18)*1+ISBLANK(F18)*1+ISBLANK(I18)*1+ISBLANK(J18)*1+ISBLANK(K18)*1+ISBLANK(L18)*1+ISBLANK(M18)*1+ISBLANK(N18)*1+ISBLANK(O18)*1)>0,"Missing Data","OK") -> OK | V18: =IF(T18>=6,"High Risk",IF(T18>=3,"Medium Risk","Low Risk")) -> Low Risk
A19: CUST100747 | B19: Standard | C19: Month-to-month | D19: 18.86 | E19: 6 | F19: 43853 | G19: Credit card | H19: 1 | I19: 73 | J19: 31 | K19: 6 | L19: 0 | M19: 0 | N19: 113.16 | O19: 0 | Q19: 44035 | R19: =IF(ISBLANK(F19),"Missing",IFERROR(YEAR(F19),"Missing")) -> 2020 | S19: =IF(ISBLANK(E19),"Missing",IF(E19<6,"0-6mo",IF(E19<12,"6-12mo",IF(E19<24,"12-24mo","24mo+")))) -> 6-12mo | T19: =IF(ISBLANK(C19),0,IF(C19="Month-to-month",2,IF(C19="One year",1,0)))+IF(ISBLANK(I19),0,IF(I19<40,2,IF(I19<55,1,0)))+IF(ISBLANK(M19),0,IF(M19=1,3,0))+IF(ISBLANK(L19),0,IF(L19>=2,1,0))+IF(ISBLANK(E19),0,IF(E19<12,1,0)) -> 3 | U19: =IF((ISBLANK(B19)*1+ISBLANK(C19)*1+ISBLANK(D19)*1+ISBLANK(E19)*1+ISBLANK(F19)*1+ISBLANK(I19)*1+ISBLANK(J19)*1+ISBLANK(K19)*1+ISBLANK(L19)*1+ISBLANK(M19)*1+ISBLANK(N19)*1+ISBLANK(O19)*1)>0,"Missing Data","OK") -> OK | V19: =IF(T19>=6,"High Risk",IF(T19>=3,"Medium Risk","Low Risk")) -> Medium Risk
A20: CUST101402 | B20: Basic | C20: One year | D20: 9.06 | E20: 7 | F20: 43853 | G20: Credit card | H20: 1 | I20: 64.7 | J20: 22 | K20: 5 | L20: 0 | M20: 0 | N20: 63.42 | O20: 0 | Q20: 44066 | R20: =IF(ISBLANK(F20),"Missing",IFERROR(YEAR(F20),"Missing")) -> 2020 | S20: =IF(ISBLANK(E20),"Missing",IF(E20<6,"0-6mo",IF(E20<12,"6-12mo",IF(E20<24,"12-24mo","24mo+")))) -> 6-12mo | T20: =IF(ISBLANK(C20),0,IF(C20="Month-to-month",2,IF(C20="One year",1,0)))+IF(ISBLANK(I20),0,IF(I20<40,2,IF(I20<55,1,0)))+IF(ISBLANK(M20),0,IF(M20=1,3,0))+IF(ISBLANK(L20),0,IF(L20>=2,1,0))+IF(ISBLANK(E20),0,IF(E20<12,1,0)) -> 2 | U20: =IF((ISBLANK(B20)*1+ISBLANK(C20)*1+ISBLANK(D20)*1+ISBLANK(E20)*1+ISBLANK(F20)*1+ISBLANK(I20)*1+ISBLANK(J20)*1+ISBLANK(K20)*1+ISBLANK(L20)*1+ISBLANK(M20)*1+ISBLANK(N20)*1+ISBLANK(O20)*1)>0,"Missing Data","OK") -> OK | V20: =IF(T20>=6,"High Risk",IF(T20>=3,"Medium Risk","Low Risk")) -> Low Risk
A21: CUST100575 | B21: Premium | C21: Two year | D21: 38.37 | E21: 5 | F21: 43861 | G21: Bank transfer | H21: 1 | I21: 71.4 | J21: 23 | K21: 10 | L21: 2 | M21: 0 | N21: 191.85 | O21: 0 | Q21: 44013 | R21: =IF(ISBLANK(F21),"Missing",IFERROR(YEAR(F21),"Missing")) -> 2020 | S21: =IF(ISBLANK(E21),"Missing",IF(E21<6,"0-6mo",IF(E21<12,"6-12mo",IF(E21<24,"12-24mo","24mo+")))) -> 0-6mo | T21: =IF(ISBLANK(C21),0,IF(C21="Month-to-month",2,IF(C21="One year",1,0)))+IF(ISBLANK(I21),0,IF(I21<40,2,IF(I21<55,1,0)))+IF(ISBLANK(M21),0,IF(M21=1,3,0))+IF(ISBLANK(L21),0,IF(L21>=2,1,0))+IF(ISBLANK(E21),0,IF(E21<12,1,0)) -> 2 | U21: =IF((ISBLANK(B21)*1+ISBLANK(C21)*1+ISBLANK(D21)*1+ISBLANK(E21)*1+ISBLANK(F21)*1+ISBLANK(I21)*1+ISBLANK(J21)*1+ISBLANK(K21)*1+ISBLANK(L21)*1+ISBLANK(M21)*1+ISBLANK(N21)*1+ISBLANK(O21)*1)>0,"Missing Data","OK") -> OK | V21: =IF(T21>=6,"High Risk",IF(T21>=3,"Medium Risk","Low Risk")) -> Low Risk
A22: CUST100057 | B22: Basic | C22: Month-to-month | D22: 10.27 | E22: 46 | F22: 43864 | G22: Credit card | H22: 1 | I22: 28.1 | J22: 18 | K22: 1 | L22: 3 | M22: 0 | N22: 472.42 | O22: 0 | Q22: 45264 | R22: =IF(ISBLANK(F22),"Missing",IFERROR(YEAR(F22),"Missing")) -> 2020 | S22: =IF(ISBLANK(E22),"Missing",IF(E22<6,"0-6mo",IF(E22<12,"6-12mo",IF(E22<24,"12-24mo","24mo+")))) -> 24mo+ | T22: =IF(ISBLANK(C22),0,IF(C22="Month-to-month",2,IF(C22="One year",1,0)))+IF(ISBLANK(I22),0,IF(I22<40,2,IF(I22<55,1,0)))+IF(ISBLANK(M22),0,IF(M22=1,3,0))+IF(ISBLANK(L22),0,IF(L22>=2,1,0))+IF(ISBLANK(E22),0,IF(E22<12,1,0)) -> 5 | U22: =IF((ISBLANK(B22)*1+ISBLANK(C22)*1+ISBLANK(D22)*1+ISBLANK(E22)*1+ISBLANK(F22)*1+ISBLANK(I22)*1+ISBLANK(J22)*1+ISBLANK(K22)*1+ISBLANK(L22)*1+ISBLANK(M22)*1+ISBLANK(N22)*1+ISBLANK(O22)*1)>0,"Missing Data","OK") -> OK | V22: =IF(T22>=6,"High Risk",IF(T22>=3,"Medium Risk","Low Risk")) -> Medium Risk
A23: CUST100209 | B23: Basic | C23: Month-to-month | D23: 9.11 | E23: 16 | F23: 43865 | G23: Bank transfer | H23: 1 | I23: 58.6 | J23: 21 | K23: 8 | L23: 2 | M23: 1 | N23: 145.76 | O23: 0 | Q23: 44352 | R23: =IF(ISBLANK(F23),"Missing",IFERROR(YEAR(F23),"Missing")) -> 2020 | S23: =IF(ISBLANK(E23),"Missing",IF(E23<6,"0-6mo",IF(E23<12,"6-12mo",IF(E23<24,"12-24mo","24mo+")))) -> 12-24mo | T23: =IF(ISBLANK(C23),0,IF(C23="Month-to-month",2,IF(C23="One year",1,0)))+IF(ISBLANK(I23),0,IF(I23<40,2,IF(I23<55,1,0)))+IF(ISBLANK(M23),0,IF(M23=1,3,0))+IF(ISBLANK(L23),0,IF(L23>=2,1,0))+IF(ISBLANK(E23),0,IF(E23<12,1,0)) -> 6 | U23: =IF((ISBLANK(B23)*1+ISBLANK(C23)*1+ISBLANK(D23)*1+ISBLANK(E23)*1+ISBLANK(F23)*1+ISBLANK(I23)*1+ISBLANK(J23)*1+ISBLANK(K23)*1+ISBLANK(L23)*1+ISBLANK(M23)*1+ISBLANK(N23)*1+ISBLANK(O23)*1)>0,"Missing Data","OK") -> OK | V23: =IF(T23>=6,"High Risk",IF(T23>=3,"Medium Risk","Low Risk")) -> High Risk
A24: CUST100912 | B24: Standard | C24: Month-to-month | D24: 20.08 | E24: 38 | F24: 43865 | G24: Bank transfer | H24: 1 | I24: 81.3 | J24: 25 | K24: 7 | L24: 1 | M24: 0 | N24: 763.04 | O24: 0 | Q24: 45021 | R24: =IF(ISBLANK(F24),"Missing",IFERROR(YEAR(F24),"Missing")) -> 2020 | S24: =IF(ISBLANK(E24),"Missing",IF(E24<6,"0-6mo",IF(E24<12,"6-12mo",IF(E24<24,"12-24mo","24mo+")))) -> 24mo+ | T24: =IF(ISBLANK(C24),0,IF(C24="Month-to-month",2,IF(C24="One year",1,0)))+IF(ISBLANK(I24),0,IF(I24<40,2,IF(I24<55,1,0)))+IF(ISBLANK(M24),0,IF(M24=1,3,0))+IF(ISBLANK(L24),0,IF(L24>=2,1,0))+IF(ISBLANK(E24),0,IF(E24<12,1,0)) -> 2 | U24: =IF((ISBLANK(B24)*1+ISBLANK(C24)*1+ISBLANK(D24)*1+ISBLANK(E24)*1+ISBLANK(F24)*1+ISBLANK(I24)*1+ISBLANK(J24)*1+ISBLANK(K24)*1+ISBLANK(L24)*1+ISBLANK(M24)*1+ISBLANK(N24)*1+ISBLANK(O24)*1)>0,"Missing Data","OK") -> OK | V24: =IF(T24>=6,"High Risk",IF(T24>=3,"Medium Risk","Low Risk")) -> Low Risk
A25: CUST101240 | B25: Premium | C25: One year | D25: 39.27 | E25: 14 | F25: 43866 | G25: Credit card | H25: 1 | I25: 90.3 | J25: 33 | K25: 9 | L25: 1 | M25: 0 | N25: 549.78 | O25: 0 | Q25: 44292 | R25: =IF(ISBLANK(F25),"Missing",IFERROR(YEAR(F25),"Missing")) -> 2020 | S25: =IF(ISBLANK(E25),"Missing",IF(E25<6,"0-6mo",IF(E25<12,"6-12mo",IF(E25<24,"12-24mo","24mo+")))) -> 12-24mo | T25: =IF(ISBLANK(C25),0,IF(C25="Month-to-month",2,IF(C25="One year",1,0)))+IF(ISBLANK(I25),0,IF(I25<40,2,IF(I25<55,1,0)))+IF(ISBLANK(M25),0,IF(M25=1,3,0))+IF(ISBLANK(L25),0,IF(L25>=2,1,0))+IF(ISBLANK(E25),0,IF(E25<12,1,0)) -> 1 | U25: =IF((ISBLANK(B25)*1+ISBLANK(C25)*1+ISBLANK(D25)*1+ISBLANK(E25)*1+ISBLANK(F25)*1+ISBLANK(I25)*1+ISBLANK(J25)*1+ISBLANK(K25)*1+ISBLANK(L25)*1+ISBLANK(M25)*1+ISBLANK(N25)*1+ISBLANK(O25)*1)>0,"Missing Data","OK") -> OK | V25: =IF(T25>=6,"High Risk",IF(T25>=3,"Medium Risk","Low Risk")) -> Low Risk
A26: CUST100324 | B26: Premium | C26: One year | D26: 40.21 | E26: 8 | F26: 43868 | G26: Bank transfer | H26: 0 | I26: 77.4 | J26: 11 | K26: 6 | L26: 0 | M26: 0 | N26: 321.68 | O26: 0 | Q26: 44111 | R26: =IF(ISBLANK(F26),"Missing",IFERROR(YEAR(F26),"Missing")) -> 2020 | S26: =IF(ISBLANK(E26),"Missing",IF(E26<6,"0-6mo",IF(E26<12,"6-12mo",IF(E26<24,"12-24mo","24mo+")))) -> 6-12mo | T26: =IF(ISBLANK(C26),0,IF(C26="Month-to-month",2,IF(C26="One year",1,0)))+IF(ISBLANK(I26),0,IF(I26<40,2,IF(I26<55,1,0)))+IF(ISBLANK(M26),0,IF(M26=1,3,0))+IF(ISBLANK(L26),0,IF(L26>=2,1,0))+IF(ISBLANK(E26),0,IF(E26<12,1,0)) -> 2 | U26: =IF((ISBLANK(B26)*1+ISBLANK(C26)*1+ISBLANK(D26)*1+ISBLANK(E26)*1+ISBLANK(F26)*1+ISBLANK(I26)*1+ISBLANK(J26)*1+ISBLANK(K26)*1+ISBLANK(L26)*1+ISBLANK(M26)*1+ISBLANK(N26)*1+ISBLANK(O26)*1)>0,"Missing Data","OK") -> OK | V26: =IF(T26>=6,"High Risk",IF(T26>=3,"Medium Risk","Low Risk")) -> Low Risk
A27: CUST100360 | B27: Basic | C27: Month-to-month | D27: 11.21 | E27: 19 | F27: 43871 | G27: Credit card | H27: 1 | I27: 48.9 | J27: 15 | K27: 4 | L27: 0 | M27: 0 | N27: 212.99 | O27: 0 | Q27: 44449 | R27: =IF(ISBLANK(F27),"Missing",IFERROR(YEAR(F27),"Missing")) -> 2020 | S27: =IF(ISBLANK(E27),"Missing",IF(E27<6,"0-6mo",IF(E27<12,"6-12mo",IF(E27<24,"12-24mo","24mo+")))) -> 12-24mo | T27: =IF(ISBLANK(C27),0,IF(C27="Month-to-month",2,IF(C27="One year",1,0)))+IF(ISBLANK(I27),0,IF(I27<40,2,IF(I27<55,1,0)))+IF(ISBLANK(M27),0,IF(M27=1,3,0))+IF(ISBLANK(L27),0,IF(L27>=2,1,0))+IF(ISBLANK(E27),0,IF(E27<12,1,0)) -> 3 | U27: =IF((ISBLANK(B27)*1+ISBLANK(C27)*1+ISBLANK(D27)*1+ISBLANK(E27)*1+ISBLANK(F27)*1+ISBLANK(I27)*1+ISBLANK(J27)*1+ISBLANK(K27)*1+ISBLANK(L27)*1+ISBLANK(M27)*1+ISBLANK(N27)*1+ISBLANK(O27)*1)>0,"Missing Data","OK") -> OK | V27: =IF(T27>=6,"High Risk",IF(T27>=3,"Medium Risk","Low Risk")) -> Medium Risk
A28: CUST100746 | B28: Basic | C28: Month-to-month | D28: 8.42 | E28: 37 | F28: 43872 | G28: Credit card | H28: 1 | I28: 18.2 | J28: 8 | K28: 0 | L28: 4 | M28: 1 | N28: 311.54 | O28: 1 | P28: 44998 | Q28: 44998 | R28: =IF(ISBLANK(F28),"Missing",IFERROR(YEAR(F28),"Missing")) -> 2020 | S28: =IF(ISBLANK(E28),"Missing",IF(E28<6,"0-6mo",IF(E28<12,"6-12mo",IF(E28<24,"12-24mo","24mo+")))) -> 24mo+ | T28: =IF(ISBLANK(C28),0,IF(C28="Month-to-month",2,IF(C28="One year",1,0)))+IF(ISBLANK(I28),0,IF(I28<40,2,IF(I28<55,1,0)))+IF(ISBLANK(M28),0,IF(M28=1,3,0))+IF(ISBLANK(L28),0,IF(L28>=2,1,0))+IF(ISBLANK(E28),0,IF(E28<12,1,0)) -> 8 | U28: =IF((ISBLANK(B28)*1+ISBLANK(C28)*1+ISBLANK(D28)*1+ISBLANK(E28)*1+ISBLANK(F28)*1+ISBLANK(I28)*1+ISBLANK(J28)*1+ISBLANK(K28)*1+ISBLANK(L28)*1+ISBLANK(M28)*1+ISBLANK(N28)*1+ISBLANK(O28)*1)>0,"Missing Data","OK") -> OK | V28: =IF(T28>=6,"High Risk",IF(T28>=3,"Medium Risk","Low Risk")) -> High Risk
A29: CUST100118 | B29: Premium | C29: One year | D29: 40.18 | E29: 17 | F29: 43872 | G29: Credit card | H29: 1 | I29: 74.1 | J29: 20 | K29: 7 | L29: 0 | M29: 0 | N29: 683.06 | O29: 0 | Q29: 44389 | R29: =IF(ISBLANK(F29),"Missing",IFERROR(YEAR(F29),"Missing")) -> 2020 | S29: =IF(ISBLANK(E29),"Missing",IF(E29<6,"0-6mo",IF(E29<12,"6-12mo",IF(E29<24,"12-24mo","24mo+")))) -> 12-24mo | T29: =IF(ISBLANK(C29),0,IF(C29="Month-to-month",2,IF(C29="One year",1,0)))+IF(ISBLANK(I29),0,IF(I29<40,2,IF(I29<55,1,0)))+IF(ISBLANK(M29),0,IF(M29=1,3,0))+IF(ISBLANK(L29),0,IF(L29>=2,1,0))+IF(ISBLANK(E29),0,IF(E29<12,1,0)) -> 1 | U29: =IF((ISBLANK(B29)*1+ISBLANK(C29)*1+ISBLANK(D29)*1+ISBLANK(E29)*1+ISBLANK(F29)*1+ISBLANK(I29)*1+ISBLANK(J29)*1+ISBLANK(K29)*1+ISBLANK(L29)*1+ISBLANK(M29)*1+ISBLANK(N29)*1+ISBLANK(O29)*1)>0,"Missing Data","OK") -> OK | V29: =IF(T29>=6,"High Risk",IF(T29>=3,"Medium Risk","Low Risk")) -> Low Risk
A30: CUST101121 | B30: Premium | C30: Month-to-month | D30: 39.31 | E30: 59 | F30: 43876 | G30: Manual/Invoice | H30: 1 | I30: 52.6 | J30: 21 | K30: 6 | L30: 2 | M30: 1 | N30: 2319.29 | O30: 0 | Q30: 45671 | R30: =IF(ISBLANK(F30),"Missing",IFERROR(YEAR(F30),"Missing")) -> 2020 | S30: =IF(ISBLANK(E30),"Missing",IF(E30<6,"0-6mo",IF(E30<12,"6-12mo",IF(E30<24,"12-24mo","24mo+")))) -> 24mo+ | T30: =IF(ISBLANK(C30),0,IF(C30="Month-to-month",2,IF(C30="One year",1,0)))+IF(ISBLANK(I30),0,IF(I30<40,2,IF(I30<55,1,0)))+IF(ISBLANK(M30),0,IF(M30=1,3,0))+IF(ISBLANK(L30),0,IF(L30>=2,1,0))+IF(ISBLANK(E30),0,IF(E30<12,1,0)) -> 7 | U30: =IF((ISBLANK(B30)*1+ISBLANK(C30)*1+ISBLANK(D30)*1+ISBLANK(E30)*1+ISBLANK(F30)*1+ISBLANK(I30)*1+ISBLANK(J30)*1+ISBLANK(K30)*1+ISBLANK(L30)*1+ISBLANK(M30)*1+ISBLANK(N30)*1+ISBLANK(O30)*1)>0,"Missing Data","OK") -> OK | V30: =IF(T30>=6,"High Risk",IF(T30>=3,"Medium Risk","Low Risk")) -> High Risk
A31: CUST101027 | B31: Premium | C31: Month-to-month | D31: 39.72 | E31: 4 | F31: 43879 | G31: PayPal | H31: 1 | I31: 54 | J31: 20 | K31: 6 | L31: 3 | M31: 0 | N31: 158.88 | O31: 1 | P31: 44000 | Q31: 44000 | R31: =IF(ISBLANK(F31),"Missing",IFERROR(YEAR(F31),"Missing")) -> 2020 | S31: =IF(ISBLANK(E31),"Missing",IF(E31<6,"0-6mo",IF(E31<12,"6-12mo",IF(E31<24,"12-24mo","24mo+")))) -> 0-6mo | T31: =IF(ISBLANK(C31),0,IF(C31="Month-to-month",2,IF(C31="One year",1,0)))+IF(ISBLANK(I31),0,IF(I31<40,2,IF(I31<55,1,0)))+IF(ISBLANK(M31),0,IF(M31=1,3,0))+IF(ISBLANK(L31),0,IF(L31>=2,1,0))+IF(ISBLANK(E31),0,IF(E31<12,1,0)) -> 5 | U31: =IF((ISBLANK(B31)*1+ISBLANK(C31)*1+ISBLANK(D31)*1+ISBLANK(E31)*1+ISBLANK(F31)*1+ISBLANK(I31)*1+ISBLANK(J31)*1+ISBLANK(K31)*1+ISBLANK(L31)*1+ISBLANK(M31)*1+ISBLANK(N31)*1+ISBLANK(O31)*1)>0,"Missing Data","OK") -> OK | V31: =IF(T31>=6,"High Risk",IF(T31>=3,"Medium Risk","Low Risk")) -> Medium Risk
A32: CUST100565 | B32: Standard | C32: Month-to-month | D32: 21.08 | E32: 2 | F32: 43879 | G32: Credit card | H32: 1 | I32: 63.3 | J32: 18 | K32: 6 | L32: 3 | M32: 1 | N32: 42.16 | O32: 1 | P32: 43939 | Q32: 43939 | R32: =IF(ISBLANK(F32),"Missing",IFERROR(YEAR(F32),"Missing")) -> 2020 | S32: =IF(ISBLANK(E32),"Missing",IF(E32<6,"0-6mo",IF(E32<12,"6-12mo",IF(E32<24,"12-24mo","24mo+")))) -> 0-6mo | T32: =IF(ISBLANK(C32),0,IF(C32="Month-to-month",2,IF(C32="One year",1,0)))+IF(ISBLANK(I32),0,IF(I32<40,2,IF(I32<55,1,0)))+IF(ISBLANK(M32),0,IF(M32=1,3,0))+IF(ISBLANK(L32),0,IF(L32>=2,1,0))+IF(ISBLANK(E32),0,IF(E32<12,1,0)) -> 7 | U32: =IF((ISBLANK(B32)*1+ISBLANK(C32)*1+ISBLANK(D32)*1+ISBLANK(E32)*1+ISBLANK(F32)*1+ISBLANK(I32)*1+ISBLANK(J32)*1+ISBLANK(K32)*1+ISBLANK(L32)*1+ISBLANK(M32)*1+ISBLANK(N32)*1+ISBLANK(O32)*1)>0,"Missing Data","OK") -> OK | V32: =IF(T32>=6,"High Risk",IF(T32>=3,"Medium Risk","Low Risk")) -> High Risk
A33: CUST100731 | B33: Premium | C33: Month-to-month | D33: 40 | E33: 25 | F33: 43879 | G33: Credit card | H33: 0 | I33: 72.1 | J33: 21 | K33: 6 | L33: 2 | M33: 0 | N33: 1000 | O33: 0 | Q33: 44640 | R33: =IF(ISBLANK(F33),"Missing",IFERROR(YEAR(F33),"Missing")) -> 2020 | S33: =IF(ISBLANK(E33),"Missing",IF(E33<6,"0-6mo",IF(E33<12,"6-12mo",IF(E33<24,"12-24mo","24mo+")))) -> 24mo+ | T33: =IF(ISBLANK(C33),0,IF(C33="Month-to-month",2,IF(C33="One year",1,0)))+IF(ISBLANK(I33),0,IF(I33<40,2,IF(I33<55,1,0)))+IF(ISBLANK(M33),0,IF(M33=1,3,0))+IF(ISBLANK(L33),0,IF(L33>=2,1,0))+IF(ISBLANK(E33),0,IF(E33<12,1,0)) -> 3 | U33: =IF((ISBLANK(B33)*1+ISBLANK(C33)*1+ISBLANK(D33)*1+ISBLANK(E33)*1+ISBLANK(F33)*1+ISBLANK(I33)*1+ISBLANK(J33)*1+ISBLANK(K33)*1+ISBLANK(L33)*1+ISBLANK(M33)*1+ISBLANK(N33)*1+ISBLANK(O33)*1)>0,"Missing Data","OK") -> OK | V33: =IF(T33>=6,"High Risk",IF(T33>=3,"Medium Risk","Low Risk")) -> Medium Risk
A34: CUST101393 | B34: Standard | C34: Two year | D34: 20.38 | E34: 5 | F34: 43879 | G34: Credit card | H34: 1 | I34: 53 | J34: 21 | K34: 7 | L34: 1 | M34: 0 | N34: 101.9 | O34: 0 | Q34: 44031 | R34: =IF(ISBLANK(F34),"Missing",IFERROR(YEAR(F34),"Missing")) -> 2020 | S34: =IF(ISBLANK(E34),"Missing",IF(E34<6,"0-6mo",IF(E34<12,"6-12mo",IF(E34<24,"12-24mo","24mo+")))) -> 0-6mo | T34: =IF(ISBLANK(C34),0,IF(C34="Month-to-month",2,IF(C34="One year",1,0)))+IF(ISBLANK(I34),0,IF(I34<40,2,IF(I34<55,1,0)))+IF(ISBLANK(M34),0,IF(M34=1,3,0))+IF(ISBLANK(L34),0,IF(L34>=2,1,0))+IF(ISBLANK(E34),0,IF(E34<12,1,0)) -> 2 | U34: =IF((ISBLANK(B34)*1+ISBLANK(C34)*1+ISBLANK(D34)*1+ISBLANK(E34)*1+ISBLANK(F34)*1+ISBLANK(I34)*1+ISBLANK(J34)*1+ISBLANK(K34)*1+ISBLANK(L34)*1+ISBLANK(M34)*1+ISBLANK(N34)*1+ISBLANK(O34)*1)>0,"Missing Data","OK") -> OK | V34: =IF(T34>=6,"High Risk",IF(T34>=3,"Medium Risk","Low Risk")) -> Low Risk
A35: CUST101366 | B35: Standard | C35: One year | D35: 20.41 | E35: 17 | F35: 43881 | G35: Credit card | H35: 1 | I35: 47.8 | J35: 11 | K35: 7 | L35: 2 | M35: 0 | N35: 346.97 | O35: 0 | Q35: 44398 | R35: =IF(ISBLANK(F35),"Missing",IFERROR(YEAR(F35),"Missing")) -> 2020 | S35: =IF(ISBLANK(E35),"Missing",IF(E35<6,"0-6mo",IF(E35<12,"6-12mo",IF(E35<24,"12-24mo","24mo+")))) -> 12-24mo | T35: =IF(ISBLANK(C35),0,IF(C35="Month-to-month",2,IF(C35="One year",1,0)))+IF(ISBLANK(I35),0,IF(I35<40,2,IF(I35<55,1,0)))+IF(ISBLANK(M35),0,IF(M35=1,3,0))+IF(ISBLANK(L35),0,IF(L35>=2,1,0))+IF(ISBLANK(E35),0,IF(E35<12,1,0)) -> 3 | U35: =IF((ISBLANK(B35)*1+ISBLANK(C35)*1+ISBLANK(D35)*1+ISBLANK(E35)*1+ISBLANK(F35)*1+ISBLANK(I35)*1+ISBLANK(J35)*1+ISBLANK(K35)*1+ISBLANK(L35)*1+ISBLANK(M35)*1+ISBLANK(N35)*1+ISBLANK(O35)*1)>0,"Missing Data","OK") -> OK | V35: =IF(T35>=6,"High Risk",IF(T35>=3,"Medium Risk","Low Risk")) -> Medium Risk
A36: CUST100426 | B36: Basic | C36: One year | D36: 10.17 | E36: 0 | F36: 43885 | G36: Credit card | H36: 0 | I36: 62.5 | J36: 22 | K36: 7 | L36: 0 | M36: 0 | N36: 0 | O36: 0 | Q36: 43885 | R36: =IF(ISBLANK(F36),"Missing",IFERROR(YEAR(F36),"Missing")) -> 2020 | S36: =IF(ISBLANK(E36),"Missing",IF(E36<6,"0-6mo",IF(E36<12,"6-12mo",IF(E36<24,"12-24mo","24mo+")))) -> 0-6mo | T36: =IF(ISBLANK(C36),0,IF(C36="Month-to-month",2,IF(C36="One year",1,0)))+IF(ISBLANK(I36),0,IF(I36<40,2,IF(I36<55,1,0)))+IF(ISBLANK(M36),0,IF(M36=1,3,0))+IF(ISBLANK(L36),0,IF(L36>=2,1,0))+IF(ISBLANK(E36),0,IF(E36<12,1,0)) -> 2 | U36: =IF((ISBLANK(B36)*1+ISBLANK(C36)*1+ISBLANK(D36)*1+ISBLANK(E36)*1+ISBLANK(F36)*1+ISBLANK(I36)*1+ISBLANK(J36)*1+ISBLANK(K36)*1+ISBLANK(L36)*1+ISBLANK(M36)*1+ISBLANK(N36)*1+ISBLANK(O36)*1)>0,"Missing Data","OK") -> OK | V36: =IF(T36>=6,"High Risk",IF(T36>=3,"Medium Risk","Low Risk")) -> Low Risk
A37: CUST101044 | B37: Premium | C37: Month-to-month | D37: 39.03 | E37: 11 | F37: 43885 | G37: Credit card | H37: 0 | I37: 69 | J37: 29 | K37: 9 | L37: 2 | M37: 1 | N37: 429.33 | O37: 1 | P37: 44219 | Q37: 44219 | R37: =IF(ISBLANK(F37),"Missing",IFERROR(YEAR(F37),"Missing")) -> 2020 | S37: =IF(ISBLANK(E37),"Missing",IF(E37<6,"0-6mo",IF(E37<12,"6-12mo",IF(E37<24,"12-24mo","24mo+")))) -> 6-12mo | T37: =IF(ISBLANK(C37),0,IF(C37="Month-to-month",2,IF(C37="One year",1,0)))+IF(ISBLANK(I37),0,IF(I37<40,2,IF(I37<55,1,0)))+IF(ISBLANK(M37),0,IF(M37=1,3,0))+IF(ISBLANK(L37),0,IF(L37>=2,1,0))+IF(ISBLANK(E37),0,IF(E37<12,1,0)) -> 7 | U37: =IF((ISBLANK(B37)*1+ISBLANK(C37)*1+ISBLANK(D37)*1+ISBLANK(E37)*1+ISBLANK(F37)*1+ISBLANK(I37)*1+ISBLANK(J37)*1+ISBLANK(K37)*1+ISBLANK(L37)*1+ISBLANK(M37)*1+ISBLANK(N37)*1+ISBLANK(O37)*1)>0,"Missing Data","OK") -> OK | V37: =IF(T37>=6,"High Risk",IF(T37>=3,"Medium Risk","Low Risk")) -> High Risk
A38: CUST100867 | B38: Basic | C38: Two year | D38: 11.23 | E38: 16 | F38: 43889 | G38: PayPal | H38: 1 | I38: 50.9 | J38: 17 | K38: 6 | L38: 3 | M38: 0 | N38: 179.68 | O38: 0 | Q38: 44376 | R38: =IF(ISBLANK(F38),"Missing",IFERROR(YEAR(F38),"Missing")) -> 2020 | S38: =IF(ISBLANK(E38),"Missing",IF(E38<6,"0-6mo",IF(E38<12,"6-12mo",IF(E38<24,"12-24mo","24mo+")))) -> 12-24mo | T38: =IF(ISBLANK(C38),0,IF(C38="Month-to-month",2,IF(C38="One year",1,0)))+IF(ISBLANK(I38),0,IF(I38<40,2,IF(I38<55,1,0)))+IF(ISBLANK(M38),0,IF(M38=1,3,0))+IF(ISBLANK(L38),0,IF(L38>=2,1,0))+IF(ISBLANK(E38),0,IF(E38<12,1,0)) -> 2 | U38: =IF((ISBLANK(B38)*1+ISBLANK(C38)*1+ISBLANK(D38)*1+ISBLANK(E38)*1+ISBLANK(F38)*1+ISBLANK(I38)*1+ISBLANK(J38)*1+ISBLANK(K38)*1+ISBLANK(L38)*1+ISBLANK(M38)*1+ISBLANK(N38)*1+ISBLANK(O38)*1)>0,"Missing Data","OK") -> OK | V38: =IF(T38>=6,"High Risk",IF(T38>=3,"Medium Risk","Low Risk")) -> Low Risk
A39: CUST100652 | B39: Standard | C39: Month-to-month | D39: 21.6 | E39: 2 | F39: 43890 | G39: Credit card | H39: 1 | I39: 55.6 | J39: 18 | K39: 7 | L39: 0 | M39: 0 | N39: 43.2 | O39: 0 | Q39: 43950 | R39: =IF(ISBLANK(F39),"Missing",IFERROR(YEAR(F39),"Missing")) -> 2020 | S39: =IF(ISBLANK(E39),"Missing",IF(E39<6,"0-6mo",IF(E39<12,"6-12mo",IF(E39<24,"12-24mo","24mo+")))) -> 0-6mo | T39: =IF(ISBLANK(C39),0,IF(C39="Month-to-month",2,IF(C39="One year",1,0)))+IF(ISBLANK(I39),0,IF(I39<40,2,IF(I39<55,1,0)))+IF(ISBLANK(M39),0,IF(M39=1,3,0))+IF(ISBLANK(L39),0,IF(L39>=2,1,0))+IF(ISBLANK(E39),0,IF(E39<12,1,0)) -> 3 | U39: =IF((ISBLANK(B39)*1+ISBLANK(C39)*1+ISBLANK(D39)*1+ISBLANK(E39)*1+ISBLANK(F39)*1+ISBLANK(I39)*1+ISBLANK(J39)*1+ISBLANK(K39)*1+ISBLANK(L39)*1+ISBLANK(M39)*1+ISBLANK(N39)*1+ISBLANK(O39)*1)>0,"Missing Data","OK") -> OK | V39: =IF(T39>=6,"High Risk",IF(T39>=3,"Medium Risk","Low Risk")) -> Medium Risk
A40: CUST100638 | B40: Basic | C40: Month-to-month | D40: 11.07 | E40: 8 | F40: 43892 | G40: Credit card | H40: 1 | I40: 43.4 | J40: 14 | K40: 3 | L40: 2 | M40: 0 | N40: 88.56 | O40: 1 | P40: 44135 | Q40: 44135 | R40: =IF(ISBLANK(F40),"Missing",IFERROR(YEAR(F40),"Missing")) -> 2020 | S40: =IF(ISBLANK(E40),"Missing",IF(E40<6,"0-6mo",IF(E40<12,"6-12mo",IF(E40<24,"12-24mo","24mo+")))) -> 6-12mo | T40: =IF(ISBLANK(C40),0,IF(C40="Month-to-month",2,IF(C40="One year",1,0)))+IF(ISBLANK(I40),0,IF(I40<40,2,IF(I40<55,1,0)))+IF(ISBLANK(M40),0,IF(M40=1,3,0))+IF(ISBLANK(L40),0,IF(L40>=2,1,0))+IF(ISBLANK(E40),0,IF(E40<12,1,0)) -> 5 | U40: =IF((ISBLANK(B40)*1+ISBLANK(C40)*1+ISBLANK(D40)*1+ISBLANK(E40)*1+ISBLANK(F40)*1+ISBLANK(I40)*1+ISBLANK(J40)*1+ISBLANK(K40)*1+ISBLANK(L40)*1+ISBLANK(M40)*1+ISBLANK(N40)*1+ISBLANK(O40)*1)>0,"Missing Data","OK") -> OK | V40: =IF(T40>=6,"High Risk",IF(T40>=3,"Medium Risk","Low Risk")) -> Medium Risk
A41: CUST101300 | B41: Basic | C41: Month-to-month | D41: 10.07 | E41: 11 | F41: 43894 | G41: PayPal | H41: 1 | I41: 89.5 | J41: 30 | K41: 10 | L41: 2 | M41: 1 | N41: 110.77 | O41: 0 | Q41: 44228 | R41: =IF(ISBLANK(F41),"Missing",IFERROR(YEAR(F41),"Missing")) -> 2020 | S41: =IF(ISBLANK(E41),"Missing",IF(E41<6,"0-6mo",IF(E41<12,"6-12mo",IF(E41<24,"12-24mo","24mo+")))) -> 6-12mo | T41: =IF(ISBLANK(C41),0,IF(C41="Month-to-month",2,IF(C41="One year",1,0)))+IF(ISBLANK(I41),0,IF(I41<40,2,IF(I41<55,1,0)))+IF(ISBLANK(M41),0,IF(M41=1,3,0))+IF(ISBLANK(L41),0,IF(L41>=2,1,0))+IF(ISBLANK(E41),0,IF(E41<12,1,0)) -> 7 | U41: =IF((ISBLANK(B41)*1+ISBLANK(C41)*1+ISBLANK(D41)*1+ISBLANK(E41)*1+ISBLANK(F41)*1+ISBLANK(I41)*1+ISBLANK(J41)*1+ISBLANK(K41)*1+ISBLANK(L41)*1+ISBLANK(M41)*1+ISBLANK(N41)*1+ISBLANK(O41)*1)>0,"Missing Data","OK") -> OK | V41: =IF(T41>=6,"High Risk",IF(T41>=3,"Medium Risk","Low Risk")) -> High Risk
A42: CUST101462 | B42: Basic | C42: Month-to-month | D42: 10.07 | E42: 13 | F42: 43897 | G42: PayPal | H42: 1 | I42: 41.5 | J42: 15 | K42: 6 | L42: 3 | M42: 0 | N42: 130.91 | O42: 0 | Q42: 44292 | R42: =IF(ISBLANK(F42),"Missing",IFERROR(YEAR(F42),"Missing")) -> 2020 | S42: =IF(ISBLANK(E42),"Missing",IF(E42<6,"0-6mo",IF(E42<12,"6-12mo",IF(E42<24,"12-24mo","24mo+")))) -> 12-24mo | T42: =IF(ISBLANK(C42),0,IF(C42="Month-to-month",2,IF(C42="One year",1,0)))+IF(ISBLANK(I42),0,IF(I42<40,2,IF(I42<55,1,0)))+IF(ISBLANK(M42),0,IF(M42=1,3,0))+IF(ISBLANK(L42),0,IF(L42>=2,1,0))+IF(ISBLANK(E42),0,IF(E42<12,1,0)) -> 4 | U42: =IF((ISBLANK(B42)*1+ISBLANK(C42)*1+ISBLANK(D42)*1+ISBLANK(E42)*1+ISBLANK(F42)*1+ISBLANK(I42)*1+ISBLANK(J42)*1+ISBLANK(K42)*1+ISBLANK(L42)*1+ISBLANK(M42)*1+ISBLANK(N42)*1+ISBLANK(O42)*1)>0,"Missing Data","OK") -> OK | V42: =IF(T42>=6,"High Risk",IF(T42>=3,"Medium Risk","Low Risk")) -> Medium Risk
A43: CUST100814 | B43: Premium | C43: Month-to-month | D43: 39.97 | E43: 5 | F43: 43898 | G43: Credit card | H43: 1 | I43: 48.8 | J43: 13 | K43: 6 | L43: 1 | M43: 0 | N43: 199.85 | O43: 0 | Q43: 44050 | R43: =IF(ISBLANK(F43),"Missing",IFERROR(YEAR(F43),"Missing")) -> 2020 | S43: =IF(ISBLANK(E43),"Missing",IF(E43<6,"0-6mo",IF(E43<12,"6-12mo",IF(E43<24,"12-24mo","24mo+")))) -> 0-6mo | T43: =IF(ISBLANK(C43),0,IF(C43="Month-to-month",2,IF(C43="One year",1,0)))+IF(ISBLANK(I43),0,IF(I43<40,2,IF(I43<55,1,0)))+IF(ISBLANK(M43),0,IF(M43=1,3,0))+IF(ISBLANK(L43),0,IF(L43>=2,1,0))+IF(ISBLANK(E43),0,IF(E43<12,1,0)) -> 4 | U43: =IF((ISBLANK(B43)*1+ISBLANK(C43)*1+ISBLANK(D43)*1+ISBLANK(E43)*1+ISBLANK(F43)*1+ISBLANK(I43)*1+ISBLANK(J43)*1+ISBLANK(K43)*1+ISBLANK(L43)*1+ISBLANK(M43)*1+ISBLANK(N43)*1+ISBLANK(O43)*1)>0,"Missing Data","OK") -> OK | V43: =IF(T43>=6,"High Risk",IF(T43>=3,"Medium Risk","Low Risk")) -> Medium Risk
A44: CUST100021 | B44: Basic | C44: One year | D44: 11.38 | E44: 25 | F44: 43899 | G44: Bank transfer | H44: 1 | I44: 54.4 | J44: 22 | K44: 5 | L44: 1 | M44: 0 | N44: 284.5 | O44: 0 | Q44: 44660 | R44: =IF(ISBLANK(F44),"Missing",IFERROR(YEAR(F44),"Missing")) -> 2020 | S44: =IF(ISBLANK(E44),"Missing",IF(E44<6,"0-6mo",IF(E44<12,"6-12mo",IF(E44<24,"12-24mo","24mo+")))) -> 24mo+ | T44: =IF(ISBLANK(C44),0,IF(C44="Month-to-month",2,IF(C44="One year",1,0)))+IF(ISBLANK(I44),0,IF(I44<40,2,IF(I44<55,1,0)))+IF(ISBLANK(M44),0,IF(M44=1,3,0))+IF(ISBLANK(L44),0,IF(L44>=2,1,0))+IF(ISBLANK(E44),0,IF(E44<12,1,0)) -> 2 | U44: =IF((ISBLANK(B44)*1+ISBLANK(C44)*1+ISBLANK(D44)*1+ISBLANK(E44)*1+ISBLANK(F44)*1+ISBLANK(I44)*1+ISBLANK(J44)*1+ISBLANK(K44)*1+ISBLANK(L44)*1+ISBLANK(M44)*1+ISBLANK(N44)*1+ISBLANK(O44)*1)>0,"Missing Data","OK") -> OK | V44: =IF(T44>=6,"High Risk",IF(T44>=3,"Medium Risk","Low Risk")) -> Low Risk
A45: CUST101096 | B45: Basic | C45: Two year | D45: 10.88 | E45: 11 | F45: 43899 | G45: Manual/Invoice | H45: 0 | I45: 38.5 | J45: 9 | K45: 0 | L45: 1 | M45: 0 | N45: 119.68 | O45: 0 | Q45: 44233 | R45: =IF(ISBLANK(F45),"Missing",IFERROR(YEAR(F45),"Missing")) -> 2020 | S45: =IF(ISBLANK(E45),"Missing",IF(E45<6,"0-6mo",IF(E45<12,"6-12mo",IF(E45<24,"12-24mo","24mo+")))) -> 6-12mo | T45: =IF(ISBLANK(C45),0,IF(C45="Month-to-month",2,IF(C45="One year",1,0)))+IF(ISBLANK(I45),0,IF(I45<40,2,IF(I45<55,1,0)))+IF(ISBLANK(M45),0,IF(M45=1,3,0))+IF(ISBLANK(L45),0,IF(L45>=2,1,0))+IF(ISBLANK(E45),0,IF(E45<12,1,0)) -> 3 | U45: =IF((ISBLANK(B45)*1+ISBLANK(C45)*1+ISBLANK(D45)*1+ISBLANK(E45)*1+ISBLANK(F45)*1+ISBLANK(I45)*1+ISBLANK(J45)*1+ISBLANK(K45)*1+ISBLANK(L45)*1+ISBLANK(M45)*1+ISBLANK(N45)*1+ISBLANK(O45)*1)>0,"Missing Data","OK") -> OK | V45: =IF(T45>=6,"High Risk",IF(T45>=3,"Medium Risk","Low Risk")) -> Medium Risk
A46: CUST100689 | B46: Basic | C46: Month-to-month | D46: 10.42 | E46: 27 | F46: 43899 | G46: Credit card | H46: 0 | I46: 53.1 | J46: 11 | K46: 4 | L46: 1 | M46: 1 | N46: 281.34 | O46: 1 | P46: 44720 | Q46: 44720 | R46: =IF(ISBLANK(F46),"Missing",IFERROR(YEAR(F46),"Missing")) -> 2020 | S46: =IF(ISBLANK(E46),"Missing",IF(E46<6,"0-6mo",IF(E46<12,"6-12mo",IF(E46<24,"12-24mo","24mo+")))) -> 24mo+ | T46: =IF(ISBLANK(C46),0,IF(C46="Month-to-month",2,IF(C46="One year",1,0)))+IF(ISBLANK(I46),0,IF(I46<40,2,IF(I46<55,1,0)))+IF(ISBLANK(M46),0,IF(M46=1,3,0))+IF(ISBLANK(L46),0,IF(L46>=2,1,0))+IF(ISBLANK(E46),0,IF(E46<12,1,0)) -> 6 | U46: =IF((ISBLANK(B46)*1+ISBLANK(C46)*1+ISBLANK(D46)*1+ISBLANK(E46)*1+ISBLANK(F46)*1+ISBLANK(I46)*1+ISBLANK(J46)*1+ISBLANK(K46)*1+ISBLANK(L46)*1+ISBLANK(M46)*1+ISBLANK(N46)*1+ISBLANK(O46)*1)>0,"Missing Data","OK") -> OK | V46: =IF(T46>=6,"High Risk",IF(T46>=3,"Medium Risk","Low Risk")) -> High Risk
A47: CUST100279 | B47: Standard | C47: Month-to-month | D47: 20.72 | E47: 46 | F47: 43901 | G47: Credit card | H47: 0 | I47: 60.9 | J47: 11 | K47: 8 | L47: 0 | M47: 0 | N47: 953.12 | O47: 0 | Q47: 45301 | R47: =IF(ISBLANK(F47),"Missing",IFERROR(YEAR(F47),"Missing")) -> 2020 | S47: =IF(ISBLANK(E47),"Missing",IF(E47<6,"0-6mo",IF(E47<12,"6-12mo",IF(E47<24,"12-24mo","24mo+")))) -> 24mo+ | T47: =IF(ISBLANK(C47),0,IF(C47="Month-to-month",2,IF(C47="One year",1,0)))+IF(ISBLANK(I47),0,IF(I47<40,2,IF(I47<55,1,0)))+IF(ISBLANK(M47),0,IF(M47=1,3,0))+IF(ISBLANK(L47),0,IF(L47>=2,1,0))+IF(ISBLANK(E47),0,IF(E47<12,1,0)) -> 2 | U47: =IF((ISBLANK(B47)*1+ISBLANK(C47)*1+ISBLANK(D47)*1+ISBLANK(E47)*1+ISBLANK(F47)*1+ISBLANK(I47)*1+ISBLANK(J47)*1+ISBLANK(K47)*1+ISBLANK(L47)*1+ISBLANK(M47)*1+ISBLANK(N47)*1+ISBLANK(O47)*1)>0,"Missing Data","OK") -> OK | V47: =IF(T47>=6,"High Risk",IF(T47>=3,"Medium Risk","Low Risk")) -> Low Risk
A48: CUST100141 | B48: Basic | C48: Month-to-month | D48: 10.98 | E48: 41 | F48: 43904 | G48: Manual/Invoice | H48: 1 | I48: 52.7 | J48: 14 | K48: 5 | L48: 0 | M48: 0 | N48: 450.18 | O48: 0 | Q48: 45152 | R48: =IF(ISBLANK(F48),"Missing",IFERROR(YEAR(F48),"Missing")) -> 2020 | S48: =IF(ISBLANK(E48),"Missing",IF(E48<6,"0-6mo",IF(E48<12,"6-12mo",IF(E48<24,"12-24mo","24mo+")))) -> 24mo+ | T48: =IF(ISBLANK(C48),0,IF(C48="Month-to-month",2,IF(C48="One year",1,0)))+IF(ISBLANK(I48),0,IF(I48<40,2,IF(I48<55,1,0)))+IF(ISBLANK(M48),0,IF(M48=1,3,0))+IF(ISBLANK(L48),0,IF(L48>=2,1,0))+IF(ISBLANK(E48),0,IF(E48<12,1,0)) -> 3 | U48: =IF((ISBLANK(B48)*1+ISBLANK(C48)*1+ISBLANK(D48)*1+ISBLANK(E48)*1+ISBLANK(F48)*1+ISBLANK(I48)*1+ISBLANK(J48)*1+ISBLANK(K48)*1+ISBLANK(L48)*1+ISBLANK(M48)*1+ISBLANK(N48)*1+ISBLANK(O48)*1)>0,"Missing Data","OK") -> OK | V48: =IF(T48>=6,"High Risk",IF(T48>=3,"Medium Risk","Low Risk")) -> Medium Risk
A49: CUST101346 | B49: Basic | C49: Month-to-month | D49: 12.94 | E49: 11 | F49: 43904 | G49: Credit card | H49: 0 | I49: 55.2 | J49: 22 | K49: 6 | L49: 1 | M49: 0 | N49: 142.34 | O49: 0 | Q49: 44238 | R49: =IF(ISBLANK(F49),"Missing",IFERROR(YEAR(F49),"Missing")) -> 2020 | S49: =IF(ISBLANK(E49),"Missing",IF(E49<6,"0-6mo",IF(E49<12,"6-12mo",IF(E49<24,"12-24mo","24mo+")))) -> 6-12mo | T49: =IF(ISBLANK(C49),0,IF(C49="Month-to-month",2,IF(C49="One year",1,0)))+IF(ISBLANK(I49),0,IF(I49<40,2,IF(I49<55,1,0)))+IF(ISBLANK(M49),0,IF(M49=1,3,0))+IF(ISBLANK(L49),0,IF(L49>=2,1,0))+IF(ISBLANK(E49),0,IF(E49<12,1,0)) -> 3 | U49: =IF((ISBLANK(B49)*1+ISBLANK(C49)*1+ISBLANK(D49)*1+ISBLANK(E49)*1+ISBLANK(F49)*1+ISBLANK(I49)*1+ISBLANK(J49)*1+ISBLANK(K49)*1+ISBLANK(L49)*1+ISBLANK(M49)*1+ISBLANK(N49)*1+ISBLANK(O49)*1)>0,"Missing Data","OK") -> OK | V49: =IF(T49>=6,"High Risk",IF(T49>=3,"Medium Risk","Low Risk")) -> Medium Risk
A50: CUST101487 | B50: Standard | C50: Month-to-month | D50: 18.58 | E50: 18 | F50: 43905 | G50: Credit card | H50: 0 | I50: 65.9 | J50: 21 | K50: 6 | L50: 3 | M50: 0 | N50: 334.44 | O50: 0 | Q50: 44452 | R50: =IF(ISBLANK(F50),"Missing",IFERROR(YEAR(F50),"Missing")) -> 2020 | S50: =IF(ISBLANK(E50),"Missing",IF(E50<6,"0-6mo",IF(E50<12,"6-12mo",IF(E50<24,"12-24mo","24mo+")))) -> 12-24mo | T50: =IF(ISBLANK(C50),0,IF(C50="Month-to-month",2,IF(C50="One year",1,0)))+IF(ISBLANK(I50),0,IF(I50<40,2,IF(I50<55,1,0)))+IF(ISBLANK(M50),0,IF(M50=1,3,0))+IF(ISBLANK(L50),0,IF(L50>=2,1,0))+IF(ISBLANK(E50),0,IF(E50<12,1,0)) -> 3 | U50: =IF((ISBLANK(B50)*1+ISBLANK(C50)*1+ISBLANK(D50)*1+ISBLANK(E50)*1+ISBLANK(F50)*1+ISBLANK(I50)*1+ISBLANK(J50)*1+ISBLANK(K50)*1+ISBLANK(L50)*1+ISBLANK(M50)*1+ISBLANK(N50)*1+ISBLANK(O50)*1)>0,"Missing Data","OK") -> OK | V50: =IF(T50>=6,"High Risk",IF(T50>=3,"Medium Risk","Low Risk")) -> Medium Risk
A51: CUST101143 | B51: Standard | C51: Two year | D51: 20.24 | E51: 6 | F51: 43907 | G51: Manual/Invoice | H51: 1 | I51: 36.8 | J51: 10 | K51: 2 | L51: 0 | M51: 0 | N51: 121.44 | O51: 0 | Q51: 44089 | R51: =IF(ISBLANK(F51),"Missing",IFERROR(YEAR(F51),"Missing")) -> 2020 | S51: =IF(ISBLANK(E51),"Missing",IF(E51<6,"0-6mo",IF(E51<12,"6-12mo",IF(E51<24,"12-24mo","24mo+")))) -> 6-12mo | T51: =IF(ISBLANK(C51),0,IF(C51="Month-to-month",2,IF(C51="One year",1,0)))+IF(ISBLANK(I51),0,IF(I51<40,2,IF(I51<55,1,0)))+IF(ISBLANK(M51),0,IF(M51=1,3,0))+IF(ISBLANK(L51),0,IF(L51>=2,1,0))+IF(ISBLANK(E51),0,IF(E51<12,1,0)) -> 3 | U51: =IF((ISBLANK(B51)*1+ISBLANK(C51)*1+ISBLANK(D51)*1+ISBLANK(E51)*1+ISBLANK(F51)*1+ISBLANK(I51)*1+ISBLANK(J51)*1+ISBLANK(K51)*1+ISBLANK(L51)*1+ISBLANK(M51)*1+ISBLANK(N51)*1+ISBLANK(O51)*1)>0,"Missing Data","OK") -> OK | V51: =IF(T51>=6,"High Risk",IF(T51>=3,"Medium Risk","Low Risk")) -> Medium Risk
A52: CUST100140 | B52: Premium | C52: Two year | D52: 39.32 | E52: 32 | F52: 43909 | G52: Bank transfer | H52: 1 | I52: 36.5 | J52: 11 | K52: 2 | L52: 0 | M52: 0 | N52: 1258.24 | O52: 0 | Q52: 44883 | R52: =IF(ISBLANK(F52),"Missing",IFERROR(YEAR(F52),"Missing")) -> 2020 | S52: =IF(ISBLANK(E52),"Missing",IF(E52<6,"0-6mo",IF(E52<12,"6-12mo",IF(E52<24,"12-24mo","24mo+")))) -> 24mo+ | T52: =IF(ISBLANK(C52),0,IF(C52="Month-to-month",2,IF(C52="One year",1,0)))+IF(ISBLANK(I52),0,IF(I52<40,2,IF(I52<55,1,0)))+IF(ISBLANK(M52),0,IF(M52=1,3,0))+IF(ISBLANK(L52),0,IF(L52>=2,1,0))+IF(ISBLANK(E52),0,IF(E52<12,1,0)) -> 2 | U52: =IF((ISBLANK(B52)*1+ISBLANK(C52)*1+ISBLANK(D52)*1+ISBLANK(E52)*1+ISBLANK(F52)*1+ISBLANK(I52)*1+ISBLANK(J52)*1+ISBLANK(K52)*1+ISBLANK(L52)*1+ISBLANK(M52)*1+ISBLANK(N52)*1+ISBLANK(O52)*1)>0,"Missing Data","OK") -> OK | V52: =IF(T52>=6,"High Risk",IF(T52>=3,"Medium Risk","Low Risk")) -> Low Risk
A53: CUST100131 | B53: Basic | C53: Two year | D53: 12.48 | E53: 8 | F53: 43909 | G53: Credit card | H53: 0 | I53: 27.8 | J53: 11 | K53: 2 | L53: 3 | M53: 0 | N53: 99.84 | O53: 0 | Q53: 44152 | R53: =IF(ISBLANK(F53),"Missing",IFERROR(YEAR(F53),"Missing")) -> 2020 | S53: =IF(ISBLANK(E53),"Missing",IF(E53<6,"0-6mo",IF(E53<12,"6-12mo",IF(E53<24,"12-24mo","24mo+")))) -> 6-12mo | T53: =IF(ISBLANK(C53),0,IF(C53="Month-to-month",2,IF(C53="One year",1,0)))+IF(ISBLANK(I53),0,IF(I53<40,2,IF(I53<55,1,0)))+IF(ISBLANK(M53),0,IF(M53=1,3,0))+IF(ISBLANK(L53),0,IF(L53>=2,1,0))+IF(ISBLANK(E53),0,IF(E53<12,1,0)) -> 4 | U53: =IF((ISBLANK(B53)*1+ISBLANK(C53)*1+ISBLANK(D53)*1+ISBLANK(E53)*1+ISBLANK(F53)*1+ISBLANK(I53)*1+ISBLANK(J53)*1+ISBLANK(K53)*1+ISBLANK(L53)*1+ISBLANK(M53)*1+ISBLANK(N53)*1+ISBLANK(O53)*1)>0,"Missing Data","OK") -> OK | V53: =IF(T53>=6,"High Risk",IF(T53>=3,"Medium Risk","Low Risk")) -> Medium Risk
A54: CUST100724 | B54: Standard | C54: One year | D54: 19.96 | E54: 8 | F54: 43910 | G54: Credit card | H54: 1 | I54: 14.4 | J54: 7 | K54: 2 | L54: 1 | M54: 1 | N54: 159.68 | O54: 0 | Q54: 44153 | R54: =IF(ISBLANK(F54),"Missing",IFERROR(YEAR(F54),"Missing")) -> 2020 | S54: =IF(ISBLANK(E54),"Missing",IF(E54<6,"0-6mo",IF(E54<12,"6-12mo",IF(E54<24,"12-24mo","24mo+")))) -> 6-12mo | T54: =IF(ISBLANK(C54),0,IF(C54="Month-to-month",2,IF(C54="One year",1,0)))+IF(ISBLANK(I54),0,IF(I54<40,2,IF(I54<55,1,0)))+IF(ISBLANK(M54),0,IF(M54=1,3,0))+IF(ISBLANK(L54),0,IF(L54>=2,1,0))+IF(ISBLANK(E54),0,IF(E54<12,1,0)) -> 7 | U54: =IF((ISBLANK(B54)*1+ISBLANK(C54)*1+ISBLANK(D54)*1+ISBLANK(E54)*1+ISBLANK(F54)*1+ISBLANK(I54)*1+ISBLANK(J54)*1+ISBLANK(K54)*1+ISBLANK(L54)*1+ISBLANK(M54)*1+ISBLANK(N54)*1+ISBLANK(O54)*1)>0,"Missing Data","OK") -> OK | V54: =IF(T54>=6,"High Risk",IF(T54>=3,"Medium Risk","Low Risk")) -> High Risk
A55: CUST100562 | B55: Basic | C55: One year | D55: 10.73 | E55: 25 | F55: 43911 | G55: PayPal | H55: 1 | I55: 60.9 | J55: 18 | K55: 6 | L55: 3 | M55: 0 | N55: 268.25 | O55: 0 | Q55: 44672 | R55: =IF(ISBLANK(F55),"Missing",IFERROR(YEAR(F55),"Missing")) -> 2020 | S55: =IF(ISBLANK(E55),"Missing",IF(E55<6,"0-6mo",IF(E55<12,"6-12mo",IF(E55<24,"12-24mo","24mo+")))) -> 24mo+ | T55: =IF(ISBLANK(C55),0,IF(C55="Month-to-month",2,IF(C55="One year",1,0)))+IF(ISBLANK(I55),0,IF(I55<40,2,IF(I55<55,1,0)))+IF(ISBLANK(M55),0,IF(M55=1,3,0))+IF(ISBLANK(L55),0,IF(L55>=2,1,0))+IF(ISBLANK(E55),0,IF(E55<12,1,0)) -> 2 | U55: =IF((ISBLANK(B55)*1+ISBLANK(C55)*1+ISBLANK(D55)*1+ISBLANK(E55)*1+ISBLANK(F55)*1+ISBLANK(I55)*1+ISBLANK(J55)*1+ISBLANK(K55)*1+ISBLANK(L55)*1+ISBLANK(M55)*1+ISBLANK(N55)*1+ISBLANK(O55)*1)>0,"Missing Data","OK") -> OK | V55: =IF(T55>=6,"High Risk",IF(T55>=3,"Medium Risk","Low Risk")) -> Low Risk
A56: CUST100943 | B56: Premium | C56: One year | D56: 41.12 | E56: 11 | F56: 43912 | G56: Credit card | H56: 0 | I56: 21.4 | J56: 7 | K56: 1 | L56: 1 | M56: 0 | N56: 452.32 | O56: 0 | Q56: 44246 | R56: =IF(ISBLANK(F56),"Missing",IFERROR(YEAR(F56),"Missing")) -> 2020 | S56: =IF(ISBLANK(E56),"Missing",IF(E56<6,"0-6mo",IF(E56<12,"6-12mo",IF(E56<24,"12-24mo","24mo+")))) -> 6-12mo | T56: =IF(ISBLANK(C56),0,IF(C56="Month-to-month",2,IF(C56="One year",1,0)))+IF(ISBLANK(I56),0,IF(I56<40,2,IF(I56<55,1,0)))+IF(ISBLANK(M56),0,IF(M56=1,3,0))+IF(ISBLANK(L56),0,IF(L56>=2,1,0))+IF(ISBLANK(E56),0,IF(E56<12,1,0)) -> 4 | U56: =IF((ISBLANK(B56)*1+ISBLANK(C56)*1+ISBLANK(D56)*1+ISBLANK(E56)*1+ISBLANK(F56)*1+ISBLANK(I56)*1+ISBLANK(J56)*1+ISBLANK(K56)*1+ISBLANK(L56)*1+ISBLANK(M56)*1+ISBLANK(N56)*1+ISBLANK(O56)*1)>0,"Missing Data","OK") -> OK | V56: =IF(T56>=6,"High Risk",IF(T56>=3,"Medium Risk","Low Risk")) -> Medium Risk
A57: CUST100922 | B57: Premium | C57: Month-to-month | D57: 38.55 | E57: 72 | F57: 43913 | G57: Manual/Invoice | H57: 1 | I57: 45.4 | J57: 12 | K57: 6 | L57: 0 | M57: 0 | N57: 2775.6 | O57: 0 | Q57: 46104 | R57: =IF(ISBLANK(F57),"Missing",IFERROR(YEAR(F57),"Missing")) -> 2020 | S57: =IF(ISBLANK(E57),"Missing",IF(E57<6,"0-6mo",IF(E57<12,"6-12mo",IF(E57<24,"12-24mo","24mo+")))) -> 24mo+ | T57: =IF(ISBLANK(C57),0,IF(C57="Month-to-month",2,IF(C57="One year",1,0)))+IF(ISBLANK(I57),0,IF(I57<40,2,IF(I57<55,1,0)))+IF(ISBLANK(M57),0,IF(M57=1,3,0))+IF(ISBLANK(L57),0,IF(L57>=2,1,0))+IF(ISBLANK(E57),0,IF(E57<12,1,0)) -> 3 | U57: =IF((ISBLANK(B57)*1+ISBLANK(C57)*1+ISBLANK(D57)*1+ISBLANK(E57)*1+ISBLANK(F57)*1+ISBLANK(I57)*1+ISBLANK(J57)*1+ISBLANK(K57)*1+ISBLANK(L57)*1+ISBLANK(M57)*1+ISBLANK(N57)*1+ISBLANK(O57)*1)>0,"Missing Data","OK") -> OK | V57: =IF(T57>=6,"High Risk",IF(T57>=3,"Medium Risk","Low Risk")) -> Medium Risk
A58: CUST100164 | B58: Basic | C58: Month-to-month | D58: 10.05 | E58: 7 | F58: 43913 | G58: PayPal | H58: 1 | I58: 82.8 | J58: 23 | K58: 10 | L58: 3 | M58: 0 | N58: 70.35 | O58: 0 | Q58: 44126 | R58: =IF(ISBLANK(F58),"Missing",IFERROR(YEAR(F58),"Missing")) -> 2020 | S58: =IF(ISBLANK(E58),"Missing",IF(E58<6,"0-6mo",IF(E58<12,"6-12mo",IF(E58<24,"12-24mo","24mo+")))) -> 6-12mo | T58: =IF(ISBLANK(C58),0,IF(C58="Month-to-month",2,IF(C58="One year",1,0)))+IF(ISBLANK(I58),0,IF(I58<40,2,IF(I58<55,1,0)))+IF(ISBLANK(M58),0,IF(M58=1,3,0))+IF(ISBLANK(L58),0,IF(L58>=2,1,0))+IF(ISBLANK(E58),0,IF(E58<12,1,0)) -> 4 | U58: =IF((ISBLANK(B58)*1+ISBLANK(C58)*1+ISBLANK(D58)*1+ISBLANK(E58)*1+ISBLANK(F58)*1+ISBLANK(I58)*1+ISBLANK(J58)*1+ISBLANK(K58)*1+ISBLANK(L58)*1+ISBLANK(M58)*1+ISBLANK(N58)*1+ISBLANK(O58)*1)>0,"Missing Data","OK") -> OK | V58: =IF(T58>=6,"High Risk",IF(T58>=3,"Medium Risk","Low Risk")) -> Medium Risk
A59: CUST100752 | B59: Standard | C59: Month-to-month | D59: 20.63 | E59: 17 | F59: 43914 | G59: PayPal | H59: 1 | I59: 25.7 | J59: 4 | K59: 1 | L59: 2 | M59: 0 | N59: 350.71 | O59: 1 | P59: 44431 | Q59: 44431 | R59: =IF(ISBLANK(F59),"Missing",IFERROR(YEAR(F59),"Missing")) -> 2020 | S59: =IF(ISBLANK(E59),"Missing",IF(E59<6,"0-6mo",IF(E59<12,"6-12mo",IF(E59<24,"12-24mo","24mo+")))) -> 12-24mo | T59: =IF(ISBLANK(C59),0,IF(C59="Month-to-month",2,IF(C59="One year",1,0)))+IF(ISBLANK(I59),0,IF(I59<40,2,IF(I59<55,1,0)))+IF(ISBLANK(M59),0,IF(M59=1,3,0))+IF(ISBLANK(L59),0,IF(L59>=2,1,0))+IF(ISBLANK(E59),0,IF(E59<12,1,0)) -> 5 | U59: =IF((ISBLANK(B59)*1+ISBLANK(C59)*1+ISBLANK(D59)*1+ISBLANK(E59)*1+ISBLANK(F59)*1+ISBLANK(I59)*1+ISBLANK(J59)*1+ISBLANK(K59)*1+ISBLANK(L59)*1+ISBLANK(M59)*1+ISBLANK(N59)*1+ISBLANK(O59)*1)>0,"Missing Data","OK") -> OK | V59: =IF(T59>=6,"High Risk",IF(T59>=3,"Medium Risk","Low Risk")) -> Medium Risk
A60: CUST100776 | B60: Basic | C60: Month-to-month | D60: 10.24 | E60: 8 | F60: 43914 | G60: Bank transfer | H60: 1 | I60: 61.4 | J60: 19 | K60: 9 | L60: 1 | M60: 0 | N60: 81.92 | O60: 0 | Q60: 44157 | R60: =IF(ISBLANK(F60),"Missing",IFERROR(YEAR(F60),"Missing")) -> 2020 | S60: =IF(ISBLANK(E60),"Missing",IF(E60<6,"0-6mo",IF(E60<12,"6-12mo",IF(E60<24,"12-24mo","24mo+")))) -> 6-12mo | T60: =IF(ISBLANK(C60),0,IF(C60="Month-to-month",2,IF(C60="One year",1,0)))+IF(ISBLANK(I60),0,IF(I60<40,2,IF(I60<55,1,0)))+IF(ISBLANK(M60),0,IF(M60=1,3,0))+IF(ISBLANK(L60),0,IF(L60>=2,1,0))+IF(ISBLANK(E60),0,IF(E60<12,1,0)) -> 3 | U60: =IF((ISBLANK(B60)*1+ISBLANK(C60)*1+ISBLANK(D60)*1+ISBLANK(E60)*1+ISBLANK(F60)*1+ISBLANK(I60)*1+ISBLANK(J60)*1+ISBLANK(K60)*1+ISBLANK(L60)*1+ISBLANK(M60)*1+ISBLANK(N60)*1+ISBLANK(O60)*1)>0,"Missing Data","OK") -> OK | V60: =IF(T60>=6,"High Risk",IF(T60>=3,"Medium Risk","Low Risk")) -> Medium Risk
A61: CUST100344 | B61: Basic | C61: Month-to-month | D61: 9.82 | E61: 64 | F61: 43916 | G61: Credit card | H61: 0 | I61: 56.6 | J61: 21 | K61: 8 | L61: 0 | M61: 0 | N61: 628.48 | O61: 0 | Q61: 45864 | R61: =IF(ISBLANK(F61),"Missing",IFERROR(YEAR(F61),"Missing")) -> 2020 | S61: =IF(ISBLANK(E61),"Missing",IF(E61<6,"0-6mo",IF(E61<12,"6-12mo",IF(E61<24,"12-24mo","24mo+")))) -> 24mo+ | T61: =IF(ISBLANK(C61),0,IF(C61="Month-to-month",2,IF(C61="One year",1,0)))+IF(ISBLANK(I61),0,IF(I61<40,2,IF(I61<55,1,0)))+IF(ISBLANK(M61),0,IF(M61=1,3,0))+IF(ISBLANK(L61),0,IF(L61>=2,1,0))+IF(ISBLANK(E61),0,IF(E61<12,1,0)) -> 2 | U61: =IF((ISBLANK(B61)*1+ISBLANK(C61)*1+ISBLANK(D61)*1+ISBLANK(E61)*1+ISBLANK(F61)*1+ISBLANK(I61)*1+ISBLANK(J61)*1+ISBLANK(K61)*1+ISBLANK(L61)*1+ISBLANK(M61)*1+ISBLANK(N61)*1+ISBLANK(O61)*1)>0,"Missing Data","OK") -> OK | V61: =IF(T61>=6,"High Risk",IF(T61>=3,"Medium Risk","Low Risk")) -> Low Risk
A62: CUST101206 | B62: Standard | C62: Month-to-month | D62: 19.45 | E62: 4 | F62: 43918 | G62: Credit card | H62: 1 | I62: 47.5 | J62: 17 | K62: 5 | L62: 1 | M62: 1 | N62: 77.8 | O62: 0 | Q62: 44039 | R62: =IF(ISBLANK(F62),"Missing",IFERROR(YEAR(F62),"Missing")) -> 2020 | S62: =IF(ISBLANK(E62),"Missing",IF(E62<6,"0-6mo",IF(E62<12,"6-12mo",IF(E62<24,"12-24mo","24mo+")))) -> 0-6mo | T62: =IF(ISBLANK(C62),0,IF(C62="Month-to-month",2,IF(C62="One year",1,0)))+IF(ISBLANK(I62),0,IF(I62<40,2,IF(I62<55,1,0)))+IF(ISBLANK(M62),0,IF(M62=1,3,0))+IF(ISBLANK(L62),0,IF(L62>=2,1,0))+IF(ISBLANK(E62),0,IF(E62<12,1,0)) -> 7 | U62: =IF((ISBLANK(B62)*1+ISBLANK(C62)*1+ISBLANK(D62)*1+ISBLANK(E62)*1+ISBLANK(F62)*1+ISBLANK(I62)*1+ISBLANK(J62)*1+ISBLANK(K62)*1+ISBLANK(L62)*1+ISBLANK(M62)*1+ISBLANK(N62)*1+ISBLANK(O62)*1)>0,"Missing Data","OK") -> OK | V62: =IF(T62>=6,"High Risk",IF(T62>=3,"Medium Risk","Low Risk")) -> High Risk
A63: CUST100928 | B63: Standard | C63: Month-to-month | D63: 19.54 | E63: 15 | F63: 43918 | G63: Credit card | H63: 0 | I63: 58.9 | J63: 20 | K63: 6 | L63: 3 | M63: 1 | N63: 293.1 | O63: 0 | Q63: 44374 | R63: =IF(ISBLANK(F63),"Missing",IFERROR(YEAR(F63),"Missing")) -> 2020 | S63: =IF(ISBLANK(E63),"Missing",IF(E63<6,"0-6mo",IF(E63<12,"6-12mo",IF(E63<24,"12-24mo","24mo+")))) -> 12-24mo | T63: =IF(ISBLANK(C63),0,IF(C63="Month-to-month",2,IF(C63="One year",1,0)))+IF(ISBLANK(I63),0,IF(I63<40,2,IF(I63<55,1,0)))+IF(ISBLANK(M63),0,IF(M63=1,3,0))+IF(ISBLANK(L63),0,IF(L63>=2,1,0))+IF(ISBLANK(E63),0,IF(E63<12,1,0)) -> 6 | U63: =IF((ISBLANK(B63)*1+ISBLANK(C63)*1+ISBLANK(D63)*1+ISBLANK(E63)*1+ISBLANK(F63)*1+ISBLANK(I63)*1+ISBLANK(J63)*1+ISBLANK(K63)*1+ISBLANK(L63)*1+ISBLANK(M63)*1+ISBLANK(N63)*1+ISBLANK(O63)*1)>0,"Missing Data","OK") -> OK | V63: =IF(T63>=6,"High Risk",IF(T63>=3,"Medium Risk","Low Risk")) -> High Risk
A64: CUST100971 | B64: Premium | C64: Two year | D64: 40.01 | E64: 11 | F64: 43919 | G64: Credit card | H64: 0 | I64: 50.1 | J64: 21 | K64: 6 | L64: 2 | M64: 0 | N64: 440.11 | O64: 0 | Q64: 44253 | R64: =IF(ISBLANK(F64),"Missing",IFERROR(YEAR(F64),"Missing")) -> 2020 | S64: =IF(ISBLANK(E64),"Missing",IF(E64<6,"0-6mo",IF(E64<12,"6-12mo",IF(E64<24,"12-24mo","24mo+")))) -> 6-12mo | T64: =IF(ISBLANK(C64),0,IF(C64="Month-to-month",2,IF(C64="One year",1,0)))+IF(ISBLANK(I64),0,IF(I64<40,2,IF(I64<55,1,0)))+IF(ISBLANK(M64),0,IF(M64=1,3,0))+IF(ISBLANK(L64),0,IF(L64>=2,1,0))+IF(ISBLANK(E64),0,IF(E64<12,1,0)) -> 3 | U64: =IF((ISBLANK(B64)*1+ISBLANK(C64)*1+ISBLANK(D64)*1+ISBLANK(E64)*1+ISBLANK(F64)*1+ISBLANK(I64)*1+ISBLANK(J64)*1+ISBLANK(K64)*1+ISBLANK(L64)*1+ISBLANK(M64)*1+ISBLANK(N64)*1+ISBLANK(O64)*1)>0,"Missing Data","OK") -> OK | V64: =IF(T64>=6,"High Risk",IF(T64>=3,"Medium Risk","Low Risk")) -> Medium Risk
A65: CUST100784 | B65: Basic | C65: Month-to-month | D65: 10.61 | E65: 29 | F65: 43920 | G65: Bank transfer | H65: 1 | I65: 29.9 | J65: 17 | K65: 1 | L65: 3 | M65: 0 | N65: 307.69 | O65: 0 | Q65: 44802 | R65: =IF(ISBLANK(F65),"Missing",IFERROR(YEAR(F65),"Missing")) -> 2020 | S65: =IF(ISBLANK(E65),"Missing",IF(E65<6,"0-6mo",IF(E65<12,"6-12mo",IF(E65<24,"12-24mo","24mo+")))) -> 24mo+ | T65: =IF(ISBLANK(C65),0,IF(C65="Month-to-month",2,IF(C65="One year",1,0)))+IF(ISBLANK(I65),0,IF(I65<40,2,IF(I65<55,1,0)))+IF(ISBLANK(M65),0,IF(M65=1,3,0))+IF(ISBLANK(L65),0,IF(L65>=2,1,0))+IF(ISBLANK(E65),0,IF(E65<12,1,0)) -> 5 | U65: =IF((ISBLANK(B65)*1+ISBLANK(C65)*1+ISBLANK(D65)*1+ISBLANK(E65)*1+ISBLANK(F65)*1+ISBLANK(I65)*1+ISBLANK(J65)*1+ISBLANK(K65)*1+ISBLANK(L65)*1+ISBLANK(M65)*1+ISBLANK(N65)*1+ISBLANK(O65)*1)>0,"Missing Data","OK") -> OK | V65: =IF(T65>=6,"High Risk",IF(T65>=3,"Medium Risk","Low Risk")) -> Medium Risk
A66: CUST100569 | B66: Basic | C66: Month-to-month | D66: 11.83 | E66: 29 | F66: 43920 | G66: PayPal | H66: 1 | I66: 42.4 | J66: 16 | K66: 2 | L66: 1 | M66: 0 | N66: 343.07 | O66: 0 | Q66: 44802 | R66: =IF(ISBLANK(F66),"Missing",IFERROR(YEAR(F66),"Missing")) -> 2020 | S66: =IF(ISBLANK(E66),"Missing",IF(E66<6,"0-6mo",IF(E66<12,"6-12mo",IF(E66<24,"12-24mo","24mo+")))) -> 24mo+ | T66: =IF(ISBLANK(C66),0,IF(C66="Month-to-month",2,IF(C66="One year",1,0)))+IF(ISBLANK(I66),0,IF(I66<40,2,IF(I66<55,1,0)))+IF(ISBLANK(M66),0,IF(M66=1,3,0))+IF(ISBLANK(L66),0,IF(L66>=2,1,0))+IF(ISBLANK(E66),0,IF(E66<12,1,0)) -> 3 | U66: =IF((ISBLANK(B66)*1+ISBLANK(C66)*1+ISBLANK(D66)*1+ISBLANK(E66)*1+ISBLANK(F66)*1+ISBLANK(I66)*1+ISBLANK(J66)*1+ISBLANK(K66)*1+ISBLANK(L66)*1+ISBLANK(M66)*1+ISBLANK(N66)*1+ISBLANK(O66)*1)>0,"Missing Data","OK") -> OK | V66: =IF(T66>=6,"High Risk",IF(T66>=3,"Medium Risk","Low Risk")) -> Medium Risk
A67: CUST100129 | B67: Standard | C67: Month-to-month | D67: 17.84 | E67: 50 | F67: 43922 | G67: Credit card | H67: 0 | I67: 57.2 | J67: 13 | K67: 7 | L67: 1 | M67: 0 | N67: 892 | O67: 0 | Q67: 45444 | R67: =IF(ISBLANK(F67),"Missing",IFERROR(YEAR(F67),"Missing")) -> 2020 | S67: =IF(ISBLANK(E67),"Missing",IF(E67<6,"0-6mo",IF(E67<12,"6-12mo",IF(E67<24,"12-24mo","24mo+")))) -> 24mo+ | T67: =IF(ISBLANK(C67),0,IF(C67="Month-to-month",2,IF(C67="One year",1,0)))+IF(ISBLANK(I67),0,IF(I67<40,2,IF(I67<55,1,0)))+IF(ISBLANK(M67),0,IF(M67=1,3,0))+IF(ISBLANK(L67),0,IF(L67>=2,1,0))+IF(ISBLANK(E67),0,IF(E67<12,1,0)) -> 2 | U67: =IF((ISBLANK(B67)*1+ISBLANK(C67)*1+ISBLANK(D67)*1+ISBLANK(E67)*1+ISBLANK(F67)*1+ISBLANK(I67)*1+ISBLANK(J67)*1+ISBLANK(K67)*1+ISBLANK(L67)*1+ISBLANK(M67)*1+ISBLANK(N67)*1+ISBLANK(O67)*1)>0,"Missing Data","OK") -> OK | V67: =IF(T67>=6,"High Risk",IF(T67>=3,"Medium Risk","Low Risk")) -> Low Risk
A68: CUST100030 | B68: Standard | C68: One year | D68: 20.1 | E68: 3 | F68: 43923 | G68: PayPal | H68: 1 | I68: 60.8 | J68: 24 | K68: 6 | L68: 0 | M68: 0 | N68: 60.3 | O68: 0 | Q68: 44014 | R68: =IF(ISBLANK(F68),"Missing",IFERROR(YEAR(F68),"Missing")) -> 2020 | S68: =IF(ISBLANK(E68),"Missing",IF(E68<6,"0-6mo",IF(E68<12,"6-12mo",IF(E68<24,"12-24mo","24mo+")))) -> 0-6mo | T68: =IF(ISBLANK(C68),0,IF(C68="Month-to-month",2,IF(C68="One year",1,0)))+IF(ISBLANK(I68),0,IF(I68<40,2,IF(I68<55,1,0)))+IF(ISBLANK(M68),0,IF(M68=1,3,0))+IF(ISBLANK(L68),0,IF(L68>=2,1,0))+IF(ISBLANK(E68),0,IF(E68<12,1,0)) -> 2 | U68: =IF((ISBLANK(B68)*1+ISBLANK(C68)*1+ISBLANK(D68)*1+ISBLANK(E68)*1+ISBLANK(F68)*1+ISBLANK(I68)*1+ISBLANK(J68)*1+ISBLANK(K68)*1+ISBLANK(L68)*1+ISBLANK(M68)*1+ISBLANK(N68)*1+ISBLANK(O68)*1)>0,"Missing Data","OK") -> OK | V68: =IF(T68>=6,"High Risk",IF(T68>=3,"Medium Risk","Low Risk")) -> Low Risk
A69: CUST100299 | B69: Basic | C69: Month-to-month | D69: 10.66 | E69: 72 | F69: 43924 | G69: Bank transfer | H69: 0 | I69: 47.8 | J69: 23 | K69: 7 | L69: 0 | M69: 0 | N69: 767.52 | O69: 0 | Q69: 46115 | R69: =IF(ISBLANK(F69),"Missing",IFERROR(YEAR(F69),"Missing")) -> 2020 | S69: =IF(ISBLANK(E69),"Missing",IF(E69<6,"0-6mo",IF(E69<12,"6-12mo",IF(E69<24,"12-24mo","24mo+")))) -> 24mo+ | T69: =IF(ISBLANK(C69),0,IF(C69="Month-to-month",2,IF(C69="One year",1,0)))+IF(ISBLANK(I69),0,IF(I69<40,2,IF(I69<55,1,0)))+IF(ISBLANK(M69),0,IF(M69=1,3,0))+IF(ISBLANK(L69),0,IF(L69>=2,1,0))+IF(ISBLANK(E69),0,IF(E69<12,1,0)) -> 3 | U69: =IF((ISBLANK(B69)*1+ISBLANK(C69)*1+ISBLANK(D69)*1+ISBLANK(E69)*1+ISBLANK(F69)*1+ISBLANK(I69)*1+ISBLANK(J69)*1+ISBLANK(K69)*1+ISBLANK(L69)*1+ISBLANK(M69)*1+ISBLANK(N69)*1+ISBLANK(O69)*1)>0,"Missing Data","OK") -> OK | V69: =IF(T69>=6,"High Risk",IF(T69>=3,"Medium Risk","Low Risk")) -> Medium Risk
A70: CUST100635 | B70: Basic | C70: One year | D70: 9.24 | E70: 1 | F70: 43924 | G70: Credit card | H70: 0 | I70: 31.5 | J70: 11 | K70: 5 | L70: 1 | M70: 0 | N70: 9.24 | O70: 0 | Q70: 43954 | R70: =IF(ISBLANK(F70),"Missing",IFERROR(YEAR(F70),"Missing")) -> 2020 | S70: =IF(ISBLANK(E70),"Missing",IF(E70<6,"0-6mo",IF(E70<12,"6-12mo",IF(E70<24,"12-24mo","24mo+")))) -> 0-6mo | T70: =IF(ISBLANK(C70),0,IF(C70="Month-to-month",2,IF(C70="One year",1,0)))+IF(ISBLANK(I70),0,IF(I70<40,2,IF(I70<55,1,0)))+IF(ISBLANK(M70),0,IF(M70=1,3,0))+IF(ISBLANK(L70),0,IF(L70>=2,1,0))+IF(ISBLANK(E70),0,IF(E70<12,1,0)) -> 4 | U70: =IF((ISBLANK(B70)*1+ISBLANK(C70)*1+ISBLANK(D70)*1+ISBLANK(E70)*1+ISBLANK(F70)*1+ISBLANK(I70)*1+ISBLANK(J70)*1+ISBLANK(K70)*1+ISBLANK(L70)*1+ISBLANK(M70)*1+ISBLANK(N70)*1+ISBLANK(O70)*1)>0,"Missing Data","OK") -> OK | V70: =IF(T70>=6,"High Risk",IF(T70>=3,"Medium Risk","Low Risk")) -> Medium Risk
A71: CUST101369 | B71: Basic | C71: Month-to-month | D71: 8.86 | E71: 40 | F71: 43927 | G71: PayPal | H71: 1 | I71: 43.3 | J71: 16 | K71: 7 | L71: 0 | M71: 0 | N71: 354.4 | O71: 1 | P71: 45144 | Q71: 45144 | R71: =IF(ISBLANK(F71),"Missing",IFERROR(YEAR(F71),"Missing")) -> 2020 | S71: =IF(ISBLANK(E71),"Missing",IF(E71<6,"0-6mo",IF(E71<12,"6-12mo",IF(E71<24,"12-24mo","24mo+")))) -> 24mo+ | T71: =IF(ISBLANK(C71),0,IF(C71="Month-to-month",2,IF(C71="One year",1,0)))+IF(ISBLANK(I71),0,IF(I71<40,2,IF(I71<55,1,0)))+IF(ISBLANK(M71),0,IF(M71=1,3,0))+IF(ISBLANK(L71),0,IF(L71>=2,1,0))+IF(ISBLANK(E71),0,IF(E71<12,1,0)) -> 3 | U71: =IF((ISBLANK(B71)*1+ISBLANK(C71)*1+ISBLANK(D71)*1+ISBLANK(E71)*1+ISBLANK(F71)*1+ISBLANK(I71)*1+ISBLANK(J71)*1+ISBLANK(K71)*1+ISBLANK(L71)*1+ISBLANK(M71)*1+ISBLANK(N71)*1+ISBLANK(O71)*1)>0,"Missing Data","OK") -> OK | V71: =IF(T71>=6,"High Risk",IF(T71>=3,"Medium Risk","Low Risk")) -> Medium Risk
A72: CUST101191 | B72: Standard | C72: One year | D72: 20.61 | E72: 14 | F72: 43927 | G72: PayPal | H72: 1 | I72: 56.6 | J72: 19 | K72: 7 | L72: 0 | M72: 0 | N72: 288.54 | O72: 0 | Q72: 44353 | R72: =IF(ISBLANK(F72),"Missing",IFERROR(YEAR(F72),"Missing")) -> 2020 | S72: =IF(ISBLANK(E72),"Missing",IF(E72<6,"0-6mo",IF(E72<12,"6-12mo",IF(E72<24,"12-24mo","24mo+")))) -> 12-24mo | T72: =IF(ISBLANK(C72),0,IF(C72="Month-to-month",2,IF(C72="One year",1,0)))+IF(ISBLANK(I72),0,IF(I72<40,2,IF(I72<55,1,0)))+IF(ISBLANK(M72),0,IF(M72=1,3,0))+IF(ISBLANK(L72),0,IF(L72>=2,1,0))+IF(ISBLANK(E72),0,IF(E72<12,1,0)) -> 1 | U72: =IF((ISBLANK(B72)*1+ISBLANK(C72)*1+ISBLANK(D72)*1+ISBLANK(E72)*1+ISBLANK(F72)*1+ISBLANK(I72)*1+ISBLANK(J72)*1+ISBLANK(K72)*1+ISBLANK(L72)*1+ISBLANK(M72)*1+ISBLANK(N72)*1+ISBLANK(O72)*1)>0,"Missing Data","OK") -> OK | V72: =IF(T72>=6,"High Risk",IF(T72>=3,"Medium Risk","Low Risk")) -> Low Risk
A73: CUST100383 | B73: Premium | C73: Two year | D73: 39.53 | E73: 14 | F73: 43928 | G73: Credit card | H73: 1 | I73: 24.1 | J73: 10 | K73: 3 | L73: 5 | M73: 0 | N73: 553.42 | O73: 0 | Q73: 44354 | R73: =IF(ISBLANK(F73),"Missing",IFERROR(YEAR(F73),"Missing")) -> 2020 | S73: =IF(ISBLANK(E73),"Missing",IF(E73<6,"0-6mo",IF(E73<12,"6-12mo",IF(E73<24,"12-24mo","24mo+")))) -> 12-24mo | T73: =IF(ISBLANK(C73),0,IF(C73="Month-to-month",2,IF(C73="One year",1,0)))+IF(ISBLANK(I73),0,IF(I73<40,2,IF(I73<55,1,0)))+IF(ISBLANK(M73),0,IF(M73=1,3,0))+IF(ISBLANK(L73),0,IF(L73>=2,1,0))+IF(ISBLANK(E73),0,IF(E73<12,1,0)) -> 3 | U73: =IF((ISBLANK(B73)*1+ISBLANK(C73)*1+ISBLANK(D73)*1+ISBLANK(E73)*1+ISBLANK(F73)*1+ISBLANK(I73)*1+ISBLANK(J73)*1+ISBLANK(K73)*1+ISBLANK(L73)*1+ISBLANK(M73)*1+ISBLANK(N73)*1+ISBLANK(O73)*1)>0,"Missing Data","OK") -> OK | V73: =IF(T73>=6,"High Risk",IF(T73>=3,"Medium Risk","Low Risk")) -> Medium Risk
A74: CUST100837 | B74: Basic | C74: Two year | D74: 9.11 | E74: 6 | F74: 43929 | G74: Credit card | H74: 0 | I74: 36.4 | J74: 18 | K74: 3 | L74: 1 | M74: 1 | N74: 54.66 | O74: 0 | Q74: 44111 | R74: =IF(ISBLANK(F74),"Missing",IFERROR(YEAR(F74),"Missing")) -> 2020 | S74: =IF(ISBLANK(E74),"Missing",IF(E74<6,"0-6mo",IF(E74<12,"6-12mo",IF(E74<24,"12-24mo","24mo+")))) -> 6-12mo | T74: =IF(ISBLANK(C74),0,IF(C74="Month-to-month",2,IF(C74="One year",1,0)))+IF(ISBLANK(I74),0,IF(I74<40,2,IF(I74<55,1,0)))+IF(ISBLANK(M74),0,IF(M74=1,3,0))+IF(ISBLANK(L74),0,IF(L74>=2,1,0))+IF(ISBLANK(E74),0,IF(E74<12,1,0)) -> 6 | U74: =IF((ISBLANK(B74)*1+ISBLANK(C74)*1+ISBLANK(D74)*1+ISBLANK(E74)*1+ISBLANK(F74)*1+ISBLANK(I74)*1+ISBLANK(J74)*1+ISBLANK(K74)*1+ISBLANK(L74)*1+ISBLANK(M74)*1+ISBLANK(N74)*1+ISBLANK(O74)*1)>0,"Missing Data","OK") -> OK | V74: =IF(T74>=6,"High Risk",IF(T74>=3,"Medium Risk","Low Risk")) -> High Risk
A75: CUST101455 | B75: Premium | C75: Month-to-month | D75: 40.66 | E75: 15 | F75: 43929 | G75: Credit card | H75: 0 | I75: 48.3 | J75: 13 | K75: 7 | L75: 3 | M75: 0 | N75: 609.9 | O75: 0 | Q75: 44385 | R75: =IF(ISBLANK(F75),"Missing",IFERROR(YEAR(F75),"Missing")) -> 2020 | S75: =IF(ISBLANK(E75),"Missing",IF(E75<6,"0-6mo",IF(E75<12,"6-12mo",IF(E75<24,"12-24mo","24mo+")))) -> 12-24mo | T75: =IF(ISBLANK(C75),0,IF(C75="Month-to-month",2,IF(C75="One year",1,0)))+IF(ISBLANK(I75),0,IF(I75<40,2,IF(I75<55,1,0)))+IF(ISBLANK(M75),0,IF(M75=1,3,0))+IF(ISBLANK(L75),0,IF(L75>=2,1,0))+IF(ISBLANK(E75),0,IF(E75<12,1,0)) -> 4 | U75: =IF((ISBLANK(B75)*1+ISBLANK(C75)*1+ISBLANK(D75)*1+ISBLANK(E75)*1+ISBLANK(F75)*1+ISBLANK(I75)*1+ISBLANK(J75)*1+ISBLANK(K75)*1+ISBLANK(L75)*1+ISBLANK(M75)*1+ISBLANK(N75)*1+ISBLANK(O75)*1)>0,"Missing Data","OK") -> OK | V75: =IF(T75>=6,"High Risk",IF(T75>=3,"Medium Risk","Low Risk")) -> Medium Risk
A76: CUST101168 | B76: Basic | C76: One year | D76: 10.69 | E76: 22 | F76: 43930 | G76: Bank transfer | H76: 1 | I76: 29.3 | J76: 9 | K76: 1 | L76: 3 | M76: 0 | N76: 235.18 | O76: 0 | Q76: 44599 | R76: =IF(ISBLANK(F76),"Missing",IFERROR(YEAR(F76),"Missing")) -> 2020 | S76: =IF(ISBLANK(E76),"Missing",IF(E76<6,"0-6mo",IF(E76<12,"6-12mo",IF(E76<24,"12-24mo","24mo+")))) -> 12-24mo | T76: =IF(ISBLANK(C76),0,IF(C76="Month-to-month",2,IF(C76="One year",1,0)))+IF(ISBLANK(I76),0,IF(I76<40,2,IF(I76<55,1,0)))+IF(ISBLANK(M76),0,IF(M76=1,3,0))+IF(ISBLANK(L76),0,IF(L76>=2,1,0))+IF(ISBLANK(E76),0,IF(E76<12,1,0)) -> 4 | U76: =IF((ISBLANK(B76)*1+ISBLANK(C76)*1+ISBLANK(D76)*1+ISBLANK(E76)*1+ISBLANK(F76)*1+ISBLANK(I76)*1+ISBLANK(J76)*1+ISBLANK(K76)*1+ISBLANK(L76)*1+ISBLANK(M76)*1+ISBLANK(N76)*1+ISBLANK(O76)*1)>0,"Missing Data","OK") -> OK | V76: =IF(T76>=6,"High Risk",IF(T76>=3,"Medium Risk","Low Risk")) -> Medium Risk
A77: CUST100231 | B77: Standard | C77: One year | D77: 19.31 | E77: 6 | F77: 43930 | G77: Credit card | H77: 1 | I77: 2.6 | J77: 6 | K77: 0 | L77: 2 | M77: 0 | N77: 115.86 | O77: 0 | Q77: 44112 | R77: =IF(ISBLANK(F77),"Missing",IFERROR(YEAR(F77),"Missing")) -> 2020 | S77: =IF(ISBLANK(E77),"Missing",IF(E77<6,"0-6mo",IF(E77<12,"6-12mo",IF(E77<24,"12-24mo","24mo+")))) -> 6-12mo | T77: =IF(ISBLANK(C77),0,IF(C77="Month-to-month",2,IF(C77="One year",1,0)))+IF(ISBLANK(I77),0,IF(I77<40,2,IF(I77<55,1,0)))+IF(ISBLANK(M77),0,IF(M77=1,3,0))+IF(ISBLANK(L77),0,IF(L77>=2,1,0))+IF(ISBLANK(E77),0,IF(E77<12,1,0)) -> 5 | U77: =IF((ISBLANK(B77)*1+ISBLANK(C77)*1+ISBLANK(D77)*1+ISBLANK(E77)*1+ISBLANK(F77)*1+ISBLANK(I77)*1+ISBLANK(J77)*1+ISBLANK(K77)*1+ISBLANK(L77)*1+ISBLANK(M77)*1+ISBLANK(N77)*1+ISBLANK(O77)*1)>0,"Missing Data","OK") -> OK | V77: =IF(T77>=6,"High Risk",IF(T77>=3,"Medium Risk","Low Risk")) -> Medium Risk
A78: CUST100468 | B78: Basic | C78: Month-to-month | D78: 10.06 | E78: 72 | F78: 43931 | G78: Manual/Invoice | H78: 1 | I78: 62.7 | J78: 16 | K78: 5 | L78: 2 | M78: 0 | N78: 724.32 | O78: 0 | Q78: 46122 | R78: =IF(ISBLANK(F78),"Missing",IFERROR(YEAR(F78),"Missing")) -> 2020 | S78: =IF(ISBLANK(E78),"Missing",IF(E78<6,"0-6mo",IF(E78<12,"6-12mo",IF(E78<24,"12-24mo","24mo+")))) -> 24mo+ | T78: =IF(ISBLANK(C78),0,IF(C78="Month-to-month",2,IF(C78="One year",1,0)))+IF(ISBLANK(I78),0,IF(I78<40,2,IF(I78<55,1,0)))+IF(ISBLANK(M78),0,IF(M78=1,3,0))+IF(ISBLANK(L78),0,IF(L78>=2,1,0))+IF(ISBLANK(E78),0,IF(E78<12,1,0)) -> 3 | U78: =IF((ISBLANK(B78)*1+ISBLANK(C78)*1+ISBLANK(D78)*1+ISBLANK(E78)*1+ISBLANK(F78)*1+ISBLANK(I78)*1+ISBLANK(J78)*1+ISBLANK(K78)*1+ISBLANK(L78)*1+ISBLANK(M78)*1+ISBLANK(N78)*1+ISBLANK(O78)*1)>0,"Missing Data","OK") -> OK | V78: =IF(T78>=6,"High Risk",IF(T78>=3,"Medium Risk","Low Risk")) -> Medium Risk
A79: CUST101202 | B79: Basic | C79: Month-to-month | D79: 8.47 | E79: 2 | F79: 43934 | G79: Bank transfer | H79: 0 | I79: 52.8 | J79: 12 | K79: 7 | L79: 0 | M79: 0 | N79: 16.94 | O79: 0 | Q79: 43994 | R79: =IF(ISBLANK(F79),"Missing",IFERROR(YEAR(F79),"Missing")) -> 2020 | S79: =IF(ISBLANK(E79),"Missing",IF(E79<6,"0-6mo",IF(E79<12,"6-12mo",IF(E79<24,"12-24mo","24mo+")))) -> 0-6mo | T79: =IF(ISBLANK(C79),0,IF(C79="Month-to-month",2,IF(C79="One year",1,0)))+IF(ISBLANK(I79),0,IF(I79<40,2,IF(I79<55,1,0)))+IF(ISBLANK(M79),0,IF(M79=1,3,0))+IF(ISBLANK(L79),0,IF(L79>=2,1,0))+IF(ISBLANK(E79),0,IF(E79<12,1,0)) -> 4 | U79: =IF((ISBLANK(B79)*1+ISBLANK(C79)*1+ISBLANK(D79)*1+ISBLANK(E79)*1+ISBLANK(F79)*1+ISBLANK(I79)*1+ISBLANK(J79)*1+ISBLANK(K79)*1+ISBLANK(L79)*1+ISBLANK(M79)*1+ISBLANK(N79)*1+ISBLANK(O79)*1)>0,"Missing Data","OK") -> OK | V79: =IF(T79>=6,"High Risk",IF(T79>=3,"Medium Risk","Low Risk")) -> Medium Risk
A80: CUST101024 | B80: Premium | C80: Month-to-month | D80: 37.78 | E80: 27 | F80: 43935 | G80: PayPal | H80: 1 | I80: 54.8 | J80: 16 | K80: 7 | L80: 3 | M80: 1 | N80: 1020.06 | O80: 1 | P80: 44756 | Q80: 44756 | R80: =IF(ISBLANK(F80),"Missing",IFERROR(YEAR(F80),"Missing")) -> 2020 | S80: =IF(ISBLANK(E80),"Missing",IF(E80<6,"0-6mo",IF(E80<12,"6-12mo",IF(E80<24,"12-24mo","24mo+")))) -> 24mo+ | T80: =IF(ISBLANK(C80),0,IF(C80="Month-to-month",2,IF(C80="One year",1,0)))+IF(ISBLANK(I80),0,IF(I80<40,2,IF(I80<55,1,0)))+IF(ISBLANK(M80),0,IF(M80=1,3,0))+IF(ISBLANK(L80),0,IF(L80>=2,1,0))+IF(ISBLANK(E80),0,IF(E80<12,1,0)) -> 7 | U80: =IF((ISBLANK(B80)*1+ISBLANK(C80)*1+ISBLANK(D80)*1+ISBLANK(E80)*1+ISBLANK(F80)*1+ISBLANK(I80)*1+ISBLANK(J80)*1+ISBLANK(K80)*1+ISBLANK(L80)*1+ISBLANK(M80)*1+ISBLANK(N80)*1+ISBLANK(O80)*1)>0,"Missing Data","OK") -> OK | V80: =IF(T80>=6,"High Risk",IF(T80>=3,"Medium Risk","Low Risk")) -> High Risk
A81: CUST101311 | B81: Premium | C81: Two year | D81: 42.35 | E81: 4 | F81: 43936 | G81: Manual/Invoice | H81: 1 | I81: 100 | J81: 25 | K81: 10 | L81: 3 | M81: 1 | N81: 169.4 | O81: 1 | P81: 44057 | Q81: 44057 | R81: =IF(ISBLANK(F81),"Missing",IFERROR(YEAR(F81),"Missing")) -> 2020 | S81: =IF(ISBLANK(E81),"Missing",IF(E81<6,"0-6mo",IF(E81<12,"6-12mo",IF(E81<24,"12-24mo","24mo+")))) -> 0-6mo | T81: =IF(ISBLANK(C81),0,IF(C81="Month-to-month",2,IF(C81="One year",1,0)))+IF(ISBLANK(I81),0,IF(I81<40,2,IF(I81<55,1,0)))+IF(ISBLANK(M81),0,IF(M81=1,3,0))+IF(ISBLANK(L81),0,IF(L81>=2,1,0))+IF(ISBLANK(E81),0,IF(E81<12,1,0)) -> 5 | U81: =IF((ISBLANK(B81)*1+ISBLANK(C81)*1+ISBLANK(D81)*1+ISBLANK(E81)*1+ISBLANK(F81)*1+ISBLANK(I81)*1+ISBLANK(J81)*1+ISBLANK(K81)*1+ISBLANK(L81)*1+ISBLANK(M81)*1+ISBLANK(N81)*1+ISBLANK(O81)*1)>0,"Missing Data","OK") -> OK | V81: =IF(T81>=6,"High Risk",IF(T81>=3,"Medium Risk","Low Risk")) -> Medium Risk
A82: CUST101211 | B82: Standard | C82: Month-to-month | D82: 19.44 | E82: 17 | F82: 43939 | G82: Bank transfer | H82: 0 | I82: 56.9 | J82: 14 | K82: 6 | L82: 2 | M82: 0 | N82: 330.48 | O82: 1 | P82: 44456 | Q82: 44456 | R82: =IF(ISBLANK(F82),"Missing",IFERROR(YEAR(F82),"Missing")) -> 2020 | S82: =IF(ISBLANK(E82),"Missing",IF(E82<6,"0-6mo",IF(E82<12,"6-12mo",IF(E82<24,"12-24mo","24mo+")))) -> 12-24mo | T82: =IF(ISBLANK(C82),0,IF(C82="Month-to-month",2,IF(C82="One year",1,0)))+IF(ISBLANK(I82),0,IF(I82<40,2,IF(I82<55,1,0)))+IF(ISBLANK(M82),0,IF(M82=1,3,0))+IF(ISBLANK(L82),0,IF(L82>=2,1,0))+IF(ISBLANK(E82),0,IF(E82<12,1,0)) -> 3 | U82: =IF((ISBLANK(B82)*1+ISBLANK(C82)*1+ISBLANK(D82)*1+ISBLANK(E82)*1+ISBLANK(F82)*1+ISBLANK(I82)*1+ISBLANK(J82)*1+ISBLANK(K82)*1+ISBLANK(L82)*1+ISBLANK(M82)*1+ISBLANK(N82)*1+ISBLANK(O82)*1)>0,"Missing Data","OK") -> OK | V82: =IF(T82>=6,"High Risk",IF(T82>=3,"Medium Risk","Low Risk")) -> Medium Risk
A83: CUST101243 | B83: Premium | C83: Month-to-month | D83: 39.72 | E83: 63 | F83: 43940 | G83: Credit card | H83: 1 | I83: 70.8 | J83: 23 | K83: 6 | L83: 0 | M83: 0 | N83: 2502.36 | O83: 0 | Q83: 45857 | R83: =IF(ISBLANK(F83),"Missing",IFERROR(YEAR(F83),"Missing")) -> 2020 | S83: =IF(ISBLANK(E83),"Missing",IF(E83<6,"0-6mo",IF(E83<12,"6-12mo",IF(E83<24,"12-24mo","24mo+")))) -> 24mo+ | T83: =IF(ISBLANK(C83),0,IF(C83="Month-to-month",2,IF(C83="One year",1,0)))+IF(ISBLANK(I83),0,IF(I83<40,2,IF(I83<55,1,0)))+IF(ISBLANK(M83),0,IF(M83=1,3,0))+IF(ISBLANK(L83),0,IF(L83>=2,1,0))+IF(ISBLANK(E83),0,IF(E83<12,1,0)) -> 2 | U83: =IF((ISBLANK(B83)*1+ISBLANK(C83)*1+ISBLANK(D83)*1+ISBLANK(E83)*1+ISBLANK(F83)*1+ISBLANK(I83)*1+ISBLANK(J83)*1+ISBLANK(K83)*1+ISBLANK(L83)*1+ISBLANK(M83)*1+ISBLANK(N83)*1+ISBLANK(O83)*1)>0,"Missing Data","OK") -> OK | V83: =IF(T83>=6,"High Risk",IF(T83>=3,"Medium Risk","Low Risk")) -> Low Risk
A84: CUST100395 | B84: Premium | C84: One year | D84: 40.36 | E84: 38 | F84: 43940 | G84: Credit card | H84: 1 | I84: 81.6 | J84: 35 | K84: 7 | L84: 1 | M84: 1 | N84: 1533.68 | O84: 0 | Q84: 45096 | R84: =IF(ISBLANK(F84),"Missing",IFERROR(YEAR(F84),"Missing")) -> 2020 | S84: =IF(ISBLANK(E84),"Missing",IF(E84<6,"0-6mo",IF(E84<12,"6-12mo",IF(E84<24,"12-24mo","24mo+")))) -> 24mo+ | T84: =IF(ISBLANK(C84),0,IF(C84="Month-to-month",2,IF(C84="One year",1,0)))+IF(ISBLANK(I84),0,IF(I84<40,2,IF(I84<55,1,0)))+IF(ISBLANK(M84),0,IF(M84=1,3,0))+IF(ISBLANK(L84),0,IF(L84>=2,1,0))+IF(ISBLANK(E84),0,IF(E84<12,1,0)) -> 4 | U84: =IF((ISBLANK(B84)*1+ISBLANK(C84)*1+ISBLANK(D84)*1+ISBLANK(E84)*1+ISBLANK(F84)*1+ISBLANK(I84)*1+ISBLANK(J84)*1+ISBLANK(K84)*1+ISBLANK(L84)*1+ISBLANK(M84)*1+ISBLANK(N84)*1+ISBLANK(O84)*1)>0,"Missing Data","OK") -> OK | V84: =IF(T84>=6,"High Risk",IF(T84>=3,"Medium Risk","Low Risk")) -> Medium Risk
A85: CUST100199 | B85: Standard | C85: One year | D85: 20.17 | E85: 0 | F85: 43942 | G85: Credit card | H85: 0 | I85: 26.3 | J85: 6 | K85: 4 | L85: 4 | M85: 1 | N85: 0 | O85: 0 | Q85: 43942 | R85: =IF(ISBLANK(F85),"Missing",IFERROR(YEAR(F85),"Missing")) -> 2020 | S85: =IF(ISBLANK(E85),"Missing",IF(E85<6,"0-6mo",IF(E85<12,"6-12mo",IF(E85<24,"12-24mo","24mo+")))) -> 0-6mo | T85: =IF(ISBLANK(C85),0,IF(C85="Month-to-month",2,IF(C85="One year",1,0)))+IF(ISBLANK(I85),0,IF(I85<40,2,IF(I85<55,1,0)))+IF(ISBLANK(M85),0,IF(M85=1,3,0))+IF(ISBLANK(L85),0,IF(L85>=2,1,0))+IF(ISBLANK(E85),0,IF(E85<12,1,0)) -> 8 | U85: =IF((ISBLANK(B85)*1+ISBLANK(C85)*1+ISBLANK(D85)*1+ISBLANK(E85)*1+ISBLANK(F85)*1+ISBLANK(I85)*1+ISBLANK(J85)*1+ISBLANK(K85)*1+ISBLANK(L85)*1+ISBLANK(M85)*1+ISBLANK(N85)*1+ISBLANK(O85)*1)>0,"Missing Data","OK") -> OK | V85: =IF(T85>=6,"High Risk",IF(T85>=3,"Medium Risk","Low Risk")) -> High Risk
A86: CUST101007 | B86: Premium | C86: Month-to-month | D86: 38.73 | E86: 38 | F86: 43942 | G86: PayPal | H86: 0 | I86: 84.8 | J86: 27 | K86: 6 | L86: 1 | M86: 0 | N86: 1471.74 | O86: 0 | Q86: 45098 | R86: =IF(ISBLANK(F86),"Missing",IFERROR(YEAR(F86),"Missing")) -> 2020 | S86: =IF(ISBLANK(E86),"Missing",IF(E86<6,"0-6mo",IF(E86<12,"6-12mo",IF(E86<24,"12-24mo","24mo+")))) -> 24mo+ | T86: =IF(ISBLANK(C86),0,IF(C86="Month-to-month",2,IF(C86="One year",1,0)))+IF(ISBLANK(I86),0,IF(I86<40,2,IF(I86<55,1,0)))+IF(ISBLANK(M86),0,IF(M86=1,3,0))+IF(ISBLANK(L86),0,IF(L86>=2,1,0))+IF(ISBLANK(E86),0,IF(E86<12,1,0)) -> 2 | U86: =IF((ISBLANK(B86)*1+ISBLANK(C86)*1+ISBLANK(D86)*1+ISBLANK(E86)*1+ISBLANK(F86)*1+ISBLANK(I86)*1+ISBLANK(J86)*1+ISBLANK(K86)*1+ISBLANK(L86)*1+ISBLANK(M86)*1+ISBLANK(N86)*1+ISBLANK(O86)*1)>0,"Missing Data","OK") -> OK | V86: =IF(T86>=6,"High Risk",IF(T86>=3,"Medium Risk","Low Risk")) -> Low Risk
A87: CUST101147 | B87: Standard | C87: One year | D87: 19.81 | E87: 15 | F87: 43943 | G87: Credit card | H87: 0 | I87: 29.2 | J87: 9 | K87: 5 | L87: 0 | M87: 0 | N87: 297.15 | O87: 0 | Q87: 44399 | R87: =IF(ISBLANK(F87),"Missing",IFERROR(YEAR(F87),"Missing")) -> 2020 | S87: =IF(ISBLANK(E87),"Missing",IF(E87<6,"0-6mo",IF(E87<12,"6-12mo",IF(E87<24,"12-24mo","24mo+")))) -> 12-24mo | T87: =IF(ISBLANK(C87),0,IF(C87="Month-to-month",2,IF(C87="One year",1,0)))+IF(ISBLANK(I87),0,IF(I87<40,2,IF(I87<55,1,0)))+IF(ISBLANK(M87),0,IF(M87=1,3,0))+IF(ISBLANK(L87),0,IF(L87>=2,1,0))+IF(ISBLANK(E87),0,IF(E87<12,1,0)) -> 3 | U87: =IF((ISBLANK(B87)*1+ISBLANK(C87)*1+ISBLANK(D87)*1+ISBLANK(E87)*1+ISBLANK(F87)*1+ISBLANK(I87)*1+ISBLANK(J87)*1+ISBLANK(K87)*1+ISBLANK(L87)*1+ISBLANK(M87)*1+ISBLANK(N87)*1+ISBLANK(O87)*1)>0,"Missing Data","OK") -> OK | V87: =IF(T87>=6,"High Risk",IF(T87>=3,"Medium Risk","Low Risk")) -> Medium Risk
A88: CUST100822 | B88: Basic | C88: One year | D88: 9.36 | E88: 3 | F88: 43944 | G88: PayPal | H88: 1 | I88: 43.9 | J88: 11 | K88: 6 | L88: 1 | M88: 0 | N88: 28.08 | O88: 0 | Q88: 44035 | R88: =IF(ISBLANK(F88),"Missing",IFERROR(YEAR(F88),"Missing")) -> 2020 | S88: =IF(ISBLANK(E88),"Missing",IF(E88<6,"0-6mo",IF(E88<12,"6-12mo",IF(E88<24,"12-24mo","24mo+")))) -> 0-6mo | T88: =IF(ISBLANK(C88),0,IF(C88="Month-to-month",2,IF(C88="One year",1,0)))+IF(ISBLANK(I88),0,IF(I88<40,2,IF(I88<55,1,0)))+IF(ISBLANK(M88),0,IF(M88=1,3,0))+IF(ISBLANK(L88),0,IF(L88>=2,1,0))+IF(ISBLANK(E88),0,IF(E88<12,1,0)) -> 3 | U88: =IF((ISBLANK(B88)*1+ISBLANK(C88)*1+ISBLANK(D88)*1+ISBLANK(E88)*1+ISBLANK(F88)*1+ISBLANK(I88)*1+ISBLANK(J88)*1+ISBLANK(K88)*1+ISBLANK(L88)*1+ISBLANK(M88)*1+ISBLANK(N88)*1+ISBLANK(O88)*1)>0,"Missing Data","OK") -> OK | V88: =IF(T88>=6,"High Risk",IF(T88>=3,"Medium Risk","Low Risk")) -> Medium Risk
A89: CUST101071 | B89: Basic | C89: One year | D89: 10.78 | E89: 5 | F89: 43946 | G89: Credit card | H89: 0 | I89: 59.7 | J89: 24 | K89: 5 | L89: 0 | M89: 0 | N89: 53.9 | O89: 0 | Q89: 44098 | R89: =IF(ISBLANK(F89),"Missing",IFERROR(YEAR(F89),"Missing")) -> 2020 | S89: =IF(ISBLANK(E89),"Missing",IF(E89<6,"0-6mo",IF(E89<12,"6-12mo",IF(E89<24,"12-24mo","24mo+")))) -> 0-6mo | T89: =IF(ISBLANK(C89),0,IF(C89="Month-to-month",2,IF(C89="One year",1,0)))+IF(ISBLANK(I89),0,IF(I89<40,2,IF(I89<55,1,0)))+IF(ISBLANK(M89),0,IF(M89=1,3,0))+IF(ISBLANK(L89),0,IF(L89>=2,1,0))+IF(ISBLANK(E89),0,IF(E89<12,1,0)) -> 2 | U89: =IF((ISBLANK(B89)*1+ISBLANK(C89)*1+ISBLANK(D89)*1+ISBLANK(E89)*1+ISBLANK(F89)*1+ISBLANK(I89)*1+ISBLANK(J89)*1+ISBLANK(K89)*1+ISBLANK(L89)*1+ISBLANK(M89)*1+ISBLANK(N89)*1+ISBLANK(O89)*1)>0,"Missing Data","OK") -> OK | V89: =IF(T89>=6,"High Risk",IF(T89>=3,"Medium Risk","Low Risk")) -> Low Risk
A90: CUST100250 | B90: Basic | C90: One year | D90: 11.32 | E90: 13 | F90: 43947 | G90: Credit card | H90: 1 | I90: 49.5 | J90: 9 | K90: 5 | L90: 0 | M90: 0 | N90: 147.16 | O90: 0 | Q90: 44342 | R90: =IF(ISBLANK(F90),"Missing",IFERROR(YEAR(F90),"Missing")) -> 2020 | S90: =IF(ISBLANK(E90),"Missing",IF(E90<6,"0-6mo",IF(E90<12,"6-12mo",IF(E90<24,"12-24mo","24mo+")))) -> 12-24mo | T90: =IF(ISBLANK(C90),0,IF(C90="Month-to-month",2,IF(C90="One year",1,0)))+IF(ISBLANK(I90),0,IF(I90<40,2,IF(I90<55,1,0)))+IF(ISBLANK(M90),0,IF(M90=1,3,0))+IF(ISBLANK(L90),0,IF(L90>=2,1,0))+IF(ISBLANK(E90),0,IF(E90<12,1,0)) -> 2 | U90: =IF((ISBLANK(B90)*1+ISBLANK(C90)*1+ISBLANK(D90)*1+ISBLANK(E90)*1+ISBLANK(F90)*1+ISBLANK(I90)*1+ISBLANK(J90)*1+ISBLANK(K90)*1+ISBLANK(L90)*1+ISBLANK(M90)*1+ISBLANK(N90)*1+ISBLANK(O90)*1)>0,"Missing Data","OK") -> OK | V90: =IF(T90>=6,"High Risk",IF(T90>=3,"Medium Risk","Low Risk")) -> Low Risk
A91: CUST100234 | B91: Basic | C91: Month-to-month | D91: 9.62 | E91: 13 | F91: 43947 | G91: PayPal | H91: 1 | I91: 57.7 | J91: 17 | K91: 8 | L91: 0 | M91: 0 | N91: 125.06 | O91: 1 | P91: 44342 | Q91: 44342 | R91: =IF(ISBLANK(F91),"Missing",IFERROR(YEAR(F91),"Missing")) -> 2020 | S91: =IF(ISBLANK(E91),"Missing",IF(E91<6,"0-6mo",IF(E91<12,"6-12mo",IF(E91<24,"12-24mo","24mo+")))) -> 12-24mo | T91: =IF(ISBLANK(C91),0,IF(C91="Month-to-month",2,IF(C91="One year",1,0)))+IF(ISBLANK(I91),0,IF(I91<40,2,IF(I91<55,1,0)))+IF(ISBLANK(M91),0,IF(M91=1,3,0))+IF(ISBLANK(L91),0,IF(L91>=2,1,0))+IF(ISBLANK(E91),0,IF(E91<12,1,0)) -> 2 | U91: =IF((ISBLANK(B91)*1+ISBLANK(C91)*1+ISBLANK(D91)*1+ISBLANK(E91)*1+ISBLANK(F91)*1+ISBLANK(I91)*1+ISBLANK(J91)*1+ISBLANK(K91)*1+ISBLANK(L91)*1+ISBLANK(M91)*1+ISBLANK(N91)*1+ISBLANK(O91)*1)>0,"Missing Data","OK") -> OK | V91: =IF(T91>=6,"High Risk",IF(T91>=3,"Medium Risk","Low Risk")) -> Low Risk
A92: CUST100524 | B92: Premium | C92: One year | D92: 38.81 | E92: 3 | F92: 43950 | G92: PayPal | H92: 1 | I92: 45 | J92: 17 | K92: 3 | L92: 0 | M92: 0 | N92: 116.43 | O92: 0 | Q92: 44041 | R92: =IF(ISBLANK(F92),"Missing",IFERROR(YEAR(F92),"Missing")) -> 2020 | S92: =IF(ISBLANK(E92),"Missing",IF(E92<6,"0-6mo",IF(E92<12,"6-12mo",IF(E92<24,"12-24mo","24mo+")))) -> 0-6mo | T92: =IF(ISBLANK(C92),0,IF(C92="Month-to-month",2,IF(C92="One year",1,0)))+IF(ISBLANK(I92),0,IF(I92<40,2,IF(I92<55,1,0)))+IF(ISBLANK(M92),0,IF(M92=1,3,0))+IF(ISBLANK(L92),0,IF(L92>=2,1,0))+IF(ISBLANK(E92),0,IF(E92<12,1,0)) -> 3 | U92: =IF((ISBLANK(B92)*1+ISBLANK(C92)*1+ISBLANK(D92)*1+ISBLANK(E92)*1+ISBLANK(F92)*1+ISBLANK(I92)*1+ISBLANK(J92)*1+ISBLANK(K92)*1+ISBLANK(L92)*1+ISBLANK(M92)*1+ISBLANK(N92)*1+ISBLANK(O92)*1)>0,"Missing Data","OK") -> OK | V92: =IF(T92>=6,"High Risk",IF(T92>=3,"Medium Risk","Low Risk")) -> Medium Risk
A93: CUST100778 | B93: Standard | C93: Two year | D93: 21.08 | E93: 19 | F93: 43950 | G93: Manual/Invoice | H93: 1 | I93: 86.2 | J93: 35 | K93: 7 | L93: 0 | M93: 0 | N93: 400.52 | O93: 0 | Q93: 44528 | R93: =IF(ISBLANK(F93),"Missing",IFERROR(YEAR(F93),"Missing")) -> 2020 | S93: =IF(ISBLANK(E93),"Missing",IF(E93<6,"0-6mo",IF(E93<12,"6-12mo",IF(E93<24,"12-24mo","24mo+")))) -> 12-24mo | T93: =IF(ISBLANK(C93),0,IF(C93="Month-to-month",2,IF(C93="One year",1,0)))+IF(ISBLANK(I93),0,IF(I93<40,2,IF(I93<55,1,0)))+IF(ISBLANK(M93),0,IF(M93=1,3,0))+IF(ISBLANK(L93),0,IF(L93>=2,1,0))+IF(ISBLANK(E93),0,IF(E93<12,1,0)) -> 0 | U93: =IF((ISBLANK(B93)*1+ISBLANK(C93)*1+ISBLANK(D93)*1+ISBLANK(E93)*1+ISBLANK(F93)*1+ISBLANK(I93)*1+ISBLANK(J93)*1+ISBLANK(K93)*1+ISBLANK(L93)*1+ISBLANK(M93)*1+ISBLANK(N93)*1+ISBLANK(O93)*1)>0,"Missing Data","OK") -> OK | V93: =IF(T93>=6,"High Risk",IF(T93>=3,"Medium Risk","Low Risk")) -> Low Risk
A94: CUST101198 | B94: Standard | C94: Month-to-month | D94: 18.21 | E94: 5 | F94: 43952 | G94: PayPal | H94: 1 | I94: 62.6 | J94: 15 | K94: 6 | L94: 1 | M94: 0 | N94: 91.05 | O94: 1 | P94: 44104 | Q94: 44104 | R94: =IF(ISBLANK(F94),"Missing",IFERROR(YEAR(F94),"Missing")) -> 2020 | S94: =IF(ISBLANK(E94),"Missing",IF(E94<6,"0-6mo",IF(E94<12,"6-12mo",IF(E94<24,"12-24mo","24mo+")))) -> 0-6mo | T94: =IF(ISBLANK(C94),0,IF(C94="Month-to-month",2,IF(C94="One year",1,0)))+IF(ISBLANK(I94),0,IF(I94<40,2,IF(I94<55,1,0)))+IF(ISBLANK(M94),0,IF(M94=1,3,0))+IF(ISBLANK(L94),0,IF(L94>=2,1,0))+IF(ISBLANK(E94),0,IF(E94<12,1,0)) -> 3 | U94: =IF((ISBLANK(B94)*1+ISBLANK(C94)*1+ISBLANK(D94)*1+ISBLANK(E94)*1+ISBLANK(F94)*1+ISBLANK(I94)*1+ISBLANK(J94)*1+ISBLANK(K94)*1+ISBLANK(L94)*1+ISBLANK(M94)*1+ISBLANK(N94)*1+ISBLANK(O94)*1)>0,"Missing Data","OK") -> OK | V94: =IF(T94>=6,"High Risk",IF(T94>=3,"Medium Risk","Low Risk")) -> Medium Risk
A95: CUST100100 | B95: Basic | C95: Month-to-month | D95: 10.55 | E95: 72 | F95: 43953 | G95: PayPal | H95: 0 | I95: 50.6 | J95: 12 | K95: 6 | L95: 1 | M95: 1 | N95: 759.6 | O95: 0 | Q95: 46144 | R95: =IF(ISBLANK(F95),"Missing",IFERROR(YEAR(F95),"Missing")) -> 2020 | S95: =IF(ISBLANK(E95),"Missing",IF(E95<6,"0-6mo",IF(E95<12,"6-12mo",IF(E95<24,"12-24mo","24mo+")))) -> 24mo+ | T95: =IF(ISBLANK(C95),0,IF(C95="Month-to-month",2,IF(C95="One year",1,0)))+IF(ISBLANK(I95),0,IF(I95<40,2,IF(I95<55,1,0)))+IF(ISBLANK(M95),0,IF(M95=1,3,0))+IF(ISBLANK(L95),0,IF(L95>=2,1,0))+IF(ISBLANK(E95),0,IF(E95<12,1,0)) -> 6 | U95: =IF((ISBLANK(B95)*1+ISBLANK(C95)*1+ISBLANK(D95)*1+ISBLANK(E95)*1+ISBLANK(F95)*1+ISBLANK(I95)*1+ISBLANK(J95)*1+ISBLANK(K95)*1+ISBLANK(L95)*1+ISBLANK(M95)*1+ISBLANK(N95)*1+ISBLANK(O95)*1)>0,"Missing Data","OK") -> OK | V95: =IF(T95>=6,"High Risk",IF(T95>=3,"Medium Risk","Low Risk")) -> High Risk
A96: CUST100817 | B96: Basic | C96: Month-to-month | D96: 10.94 | E96: 5 | F96: 43954 | G96: Bank transfer | H96: 1 | I96: 37.9 | J96: 17 | K96: 4 | L96: 2 | M96: 0 | N96: 54.7 | O96: 1 | P96: 44106 | Q96: 44106 | R96: =IF(ISBLANK(F96),"Missing",IFERROR(YEAR(F96),"Missing")) -> 2020 | S96: =IF(ISBLANK(E96),"Missing",IF(E96<6,"0-6mo",IF(E96<12,"6-12mo",IF(E96<24,"12-24mo","24mo+")))) -> 0-6mo | T96: =IF(ISBLANK(C96),0,IF(C96="Month-to-month",2,IF(C96="One year",1,0)))+IF(ISBLANK(I96),0,IF(I96<40,2,IF(I96<55,1,0)))+IF(ISBLANK(M96),0,IF(M96=1,3,0))+IF(ISBLANK(L96),0,IF(L96>=2,1,0))+IF(ISBLANK(E96),0,IF(E96<12,1,0)) -> 6 | U96: =IF((ISBLANK(B96)*1+ISBLANK(C96)*1+ISBLANK(D96)*1+ISBLANK(E96)*1+ISBLANK(F96)*1+ISBLANK(I96)*1+ISBLANK(J96)*1+ISBLANK(K96)*1+ISBLANK(L96)*1+ISBLANK(M96)*1+ISBLANK(N96)*1+ISBLANK(O96)*1)>0,"Missing Data","OK") -> OK | V96: =IF(T96>=6,"High Risk",IF(T96>=3,"Medium Risk","Low Risk")) -> High Risk
A97: CUST100256 | B97: Premium | C97: Month-to-month | D97: 40.05 | E97: 1 | F97: 43954 | G97: PayPal | H97: 1 | I97: 31.4 | J97: 9 | K97: 4 | L97: 0 | M97: 0 | N97: 40.05 | O97: 1 | P97: 43984 | Q97: 43984 | R97: =IF(ISBLANK(F97),"Missing",IFERROR(YEAR(F97),"Missing")) -> 2020 | S97: =IF(ISBLANK(E97),"Missing",IF(E97<6,"0-6mo",IF(E97<12,"6-12mo",IF(E97<24,"12-24mo","24mo+")))) -> 0-6mo | T97: =IF(ISBLANK(C97),0,IF(C97="Month-to-month",2,IF(C97="One year",1,0)))+IF(ISBLANK(I97),0,IF(I97<40,2,IF(I97<55,1,0)))+IF(ISBLANK(M97),0,IF(M97=1,3,0))+IF(ISBLANK(L97),0,IF(L97>=2,1,0))+IF(ISBLANK(E97),0,IF(E97<12,1,0)) -> 5 | U97: =IF((ISBLANK(B97)*1+ISBLANK(C97)*1+ISBLANK(D97)*1+ISBLANK(E97)*1+ISBLANK(F97)*1+ISBLANK(I97)*1+ISBLANK(J97)*1+ISBLANK(K97)*1+ISBLANK(L97)*1+ISBLANK(M97)*1+ISBLANK(N97)*1+ISBLANK(O97)*1)>0,"Missing Data","OK") -> OK | V97: =IF(T97>=6,"High Risk",IF(T97>=3,"Medium Risk","Low Risk")) -> Medium Risk
A98: CUST100270 | B98: Premium | C98: Two year | D98: 40.3 | E98: 20 | F98: 43955 | G98: Manual/Invoice | H98: 1 | I98: 55.8 | J98: 23 | K98: 6 | L98: 2 | M98: 0 | N98: 806 | O98: 0 | Q98: 44563 | R98: =IF(ISBLANK(F98),"Missing",IFERROR(YEAR(F98),"Missing")) -> 2020 | S98: =IF(ISBLANK(E98),"Missing",IF(E98<6,"0-6mo",IF(E98<12,"6-12mo",IF(E98<24,"12-24mo","24mo+")))) -> 12-24mo | T98: =IF(ISBLANK(C98),0,IF(C98="Month-to-month",2,IF(C98="One year",1,0)))+IF(ISBLANK(I98),0,IF(I98<40,2,IF(I98<55,1,0)))+IF(ISBLANK(M98),0,IF(M98=1,3,0))+IF(ISBLANK(L98),0,IF(L98>=2,1,0))+IF(ISBLANK(E98),0,IF(E98<12,1,0)) -> 1 | U98: =IF((ISBLANK(B98)*1+ISBLANK(C98)*1+ISBLANK(D98)*1+ISBLANK(E98)*1+ISBLANK(F98)*1+ISBLANK(I98)*1+ISBLANK(J98)*1+ISBLANK(K98)*1+ISBLANK(L98)*1+ISBLANK(M98)*1+ISBLANK(N98)*1+ISBLANK(O98)*1)>0,"Missing Data","OK") -> OK | V98: =IF(T98>=6,"High Risk",IF(T98>=3,"Medium Risk","Low Risk")) -> Low Risk
A99: CUST100480 | B99: Standard | C99: Two year | D99: 20.01 | E99: 0 | F99: 43955 | G99: Credit card | H99: 0 | I99: 48.7 | J99: 2 | K99: 4 | L99: 0 | M99: 0 | N99: 0 | O99: 0 | Q99: 43955 | R99: =IF(ISBLANK(F99),"Missing",IFERROR(YEAR(F99),"Missing")) -> 2020 | S99: =IF(ISBLANK(E99),"Missing",IF(E99<6,"0-6mo",IF(E99<12,"6-12mo",IF(E99<24,"12-24mo","24mo+")))) -> 0-6mo | T99: =IF(ISBLANK(C99),0,IF(C99="Month-to-month",2,IF(C99="One year",1,0)))+IF(ISBLANK(I99),0,IF(I99<40,2,IF(I99<55,1,0)))+IF(ISBLANK(M99),0,IF(M99=1,3,0))+IF(ISBLANK(L99),0,IF(L99>=2,1,0))+IF(ISBLANK(E99),0,IF(E99<12,1,0)) -> 2 | U99: =IF((ISBLANK(B99)*1+ISBLANK(C99)*1+ISBLANK(D99)*1+ISBLANK(E99)*1+ISBLANK(F99)*1+ISBLANK(I99)*1+ISBLANK(J99)*1+ISBLANK(K99)*1+ISBLANK(L99)*1+ISBLANK(M99)*1+ISBLANK(N99)*1+ISBLANK(O99)*1)>0,"Missing Data","OK") -> OK | V99: =IF(T99>=6,"High Risk",IF(T99>=3,"Medium Risk","Low Risk")) -> Low Risk
A100: CUST100254 | B100: Basic | C100: One year | D100: 9.35 | E100: 8 | F100: 43957 | G100: Credit card | H100: 1 | I100: 24.9 | J100: 13 | K100: 4 | L100: 3 | M100: 0 | N100: 74.8 | O100: 0 | Q100: 44200 | R100: =IF(ISBLANK(F100),"Missing",IFERROR(YEAR(F100),"Missing")) -> 2020 | S100: =IF(ISBLANK(E100),"Missing",IF(E100<6,"0-6mo",IF(E100<12,"6-12mo",IF(E100<24,"12-24mo","24mo+")))) -> 6-12mo | T100: =IF(ISBLANK(C100),0,IF(C100="Month-to-month",2,IF(C100="One year",1,0)))+IF(ISBLANK(I100),0,IF(I100<40,2,IF(I100<55,1,0)))+IF(ISBLANK(M100),0,IF(M100=1,3,0))+IF(ISBLANK(L100),0,IF(L100>=2,1,0))+IF(ISBLANK(E100),0,IF(E100<12,1,0)) -> 5 | U100: =IF((ISBLANK(B100)*1+ISBLANK(C100)*1+ISBLANK(D100)*1+ISBLANK(E100)*1+ISBLANK(F100)*1+ISBLANK(I100)*1+ISBLANK(J100)*1+ISBLANK(K100)*1+ISBLANK(L100)*1+ISBLANK(M100)*1+ISBLANK(N100)*1+ISBLANK(O100)*1)>0,"Missing Data","OK") -> OK | V100: =IF(T100>=6,"High Risk",IF(T100>=3,"Medium Risk","Low Risk")) -> Medium Risk
...

Sheet cleaned_data
A1: Customer_id | B1: Plan Type | C1: Contract Type | D1: Monthly Charge | E1: Tenure | F1: Signup date | G1: Payment_method | H1: Autopay | I1: usage_score | J1: login_per_month | K1: Feature_used | L1: Support_tickets | M1: complaint_unresolved | N1: Total Revenue | O1: Churned | P1: Duplicate_flag | Q1: Cleaning_notes
A2: =TRIM(customer_churn_dataset!A2) -> CUST100500 | B2: =PROPER(TRIM(customer_churn_dataset!B2)) -> Standard | C2: =PROPER(TRIM(customer_churn_dataset!C2)) -> Month-To-Month | D2: =IF(ISBLANK(customer_churn_dataset!D2),ROUND(MEDIAN(customer_churn_dataset!D$2:D$1501),2),IF(customer_churn_dataset!D2<0,ABS(customer_churn_dataset!D2),customer_churn_dataset!D2)) -> 21.31 | E2: =IF(ISBLANK(customer_churn_dataset!E2),0,MAX(0,customer_churn_dataset!E2)) -> 20 | F2: =IF(ISBLANK(customer_churn_dataset!F2),"",customer_churn_dataset!F2) -> 43833 | G2: =PROPER(TRIM(customer_churn_dataset!G2)) -> Credit Card | H2: =IF(ISBLANK(customer_churn_dataset!H2),0,customer_churn_dataset!H2) -> 1 | I2: =IF(ISBLANK(customer_churn_dataset!I2),ROUND(MEDIAN(customer_churn_dataset!I$2:I$1501),1),MIN(100,MAX(0,customer_churn_dataset!I2))) -> 78.8 | J2: =IF(ISBLANK(customer_churn_dataset!J2),0,MAX(0,customer_churn_dataset!J2)) -> 8 | K2: =IF(ISBLANK(customer_churn_dataset!K2),0,MIN(10,MAX(0,customer_churn_dataset!K2))) -> 8 | L2: =IF(ISBLANK(customer_churn_dataset!L2),0,MAX(0,customer_churn_dataset!L2)) -> 2 | M2: =IF(ISBLANK(customer_churn_dataset!M2),0,customer_churn_dataset!M2) -> 1 | N2: =IF(ISBLANK(customer_churn_dataset!N2),0,MAX(0,customer_churn_dataset!N2)) -> 426.2 | O2: =IF(ISBLANK(customer_churn_dataset!O2),0,customer_churn_dataset!O2) -> 0 | P2: =IF(COUNTIF(customer_churn_dataset!$A$2:$A$1501,customer_churn_dataset!A2)>1,"Duplicate","Unique") -> Unique
A3: =TRIM(customer_churn_dataset!A3) -> CUST101041 | B3: =PROPER(TRIM(customer_churn_dataset!B3)) -> Standard | C3: =PROPER(TRIM(customer_churn_dataset!C3)) -> Month-To-Month | D3: =IF(ISBLANK(customer_churn_dataset!D3),ROUND(MEDIAN(customer_churn_dataset!D$2:D$1501),2),IF(customer_churn_dataset!D3<0,ABS(customer_churn_dataset!D3),customer_churn_dataset!D3)) -> 19.8 | E3: =IF(ISBLANK(customer_churn_dataset!E3),0,MAX(0,customer_churn_dataset!E3)) -> 33 | F3: =IF(ISBLANK(customer_churn_dataset!F3),"",customer_churn_dataset!F3) -> 43833 | G3: =PROPER(TRIM(customer_churn_dataset!G3)) -> Manual/Invoice | H3: =IF(ISBLANK(customer_churn_dataset!H3),0,customer_churn_dataset!H3) -> 1 | I3: =IF(ISBLANK(customer_churn_dataset!I3),ROUND(MEDIAN(customer_churn_dataset!I$2:I$1501),1),MIN(100,MAX(0,customer_churn_dataset!I3))) -> 46.1 | J3: =IF(ISBLANK(customer_churn_dataset!J3),0,MAX(0,customer_churn_dataset!J3)) -> 20 | K3: =IF(ISBLANK(customer_churn_dataset!K3),0,MIN(10,MAX(0,customer_churn_dataset!K3))) -> 4 | L3: =IF(ISBLANK(customer_churn_dataset!L3),0,MAX(0,customer_churn_dataset!L3)) -> 0 | M3: =IF(ISBLANK(customer_churn_dataset!M3),0,customer_churn_dataset!M3) -> 0 | N3: =IF(ISBLANK(customer_churn_dataset!N3),0,MAX(0,customer_churn_dataset!N3)) -> 653.4 | O3: =IF(ISBLANK(customer_churn_dataset!O3),0,customer_churn_dataset!O3) -> 0 | P3: =IF(COUNTIF(customer_churn_dataset!$A$2:$A$1501,customer_churn_dataset!A3)>1,"Duplicate","Unique") -> Unique
A4: =TRIM(customer_churn_dataset!A4) -> CUST100305 | B4: =PROPER(TRIM(customer_churn_dataset!B4)) -> Premium | C4: =PROPER(TRIM(customer_churn_dataset!C4)) -> Month-To-Month | D4: =IF(ISBLANK(customer_churn_dataset!D4),ROUND(MEDIAN(customer_churn_dataset!D$2:D$1501),2),IF(customer_churn_dataset!D4<0,ABS(customer_churn_dataset!D4),customer_churn_dataset!D4)) -> 40.58 | E4: =IF(ISBLANK(customer_churn_dataset!E4),0,MAX(0,customer_churn_dataset!E4)) -> 18 | F4: =IF(ISBLANK(customer_churn_dataset!F4),"",customer_churn_dataset!F4) -> 43834 | G4: =PROPER(TRIM(customer_churn_dataset!G4)) -> Bank Transfer | H4: =IF(ISBLANK(customer_churn_dataset!H4),0,customer_churn_dataset!H4) -> 1 | I4: =IF(ISBLANK(customer_churn_dataset!I4),ROUND(MEDIAN(customer_churn_dataset!I$2:I$1501),1),MIN(100,MAX(0,customer_churn_dataset!I4))) -> 49.8 | J4: =IF(ISBLANK(customer_churn_dataset!J4),0,MAX(0,customer_churn_dataset!J4)) -> 17 | K4: =IF(ISBLANK(customer_churn_dataset!K4),0,MIN(10,MAX(0,customer_churn_dataset!K4))) -> 6 | L4: =IF(ISBLANK(customer_churn_dataset!L4),0,MAX(0,customer_churn_dataset!L4)) -> 3 | M4: =IF(ISBLANK(customer_churn_dataset!M4),0,customer_churn_dataset!M4) -> 0 | N4: =IF(ISBLANK(customer_churn_dataset!N4),0,MAX(0,customer_churn_dataset!N4)) -> 730.44 | O4: =IF(ISBLANK(customer_churn_dataset!O4),0,customer_churn_dataset!O4) -> 0 | P4: =IF(COUNTIF(customer_churn_dataset!$A$2:$A$1501,customer_churn_dataset!A4)>1,"Duplicate","Unique") -> Unique
A5: =TRIM(customer_churn_dataset!A5) -> CUST101045 | B5: =PROPER(TRIM(customer_churn_dataset!B5)) -> Standard | C5: =PROPER(TRIM(customer_churn_dataset!C5)) -> Month-To-Month | D5: =IF(ISBLANK(customer_churn_dataset!D5),ROUND(MEDIAN(customer_churn_dataset!D$2:D$1501),2),IF(customer_churn_dataset!D5<0,ABS(customer_churn_dataset!D5),customer_churn_dataset!D5)) -> 20.46 | E5: =IF(ISBLANK(customer_churn_dataset!E5),0,MAX(0,customer_churn_dataset!E5)) -> 57 | F5: =IF(ISBLANK(customer_churn_dataset!F5),"",customer_churn_dataset!F5) -> 43837 | G5: =PROPER(TRIM(customer_churn_dataset!G5)) -> Credit Card | H5: =IF(ISBLANK(customer_churn_dataset!H5),0,customer_churn_dataset!H5) -> 0 | I5: =IF(ISBLANK(customer_churn_dataset!I5),ROUND(MEDIAN(customer_churn_dataset!I$2:I$1501),1),MIN(100,MAX(0,customer_churn_dataset!I5))) -> 42.4 | J5: =IF(ISBLANK(customer_churn_dataset!J5),0,MAX(0,customer_churn_dataset!J5)) -> 10 | K5: =IF(ISBLANK(customer_churn_dataset!K5),0,MIN(10,MAX(0,customer_churn_dataset!K5))) -> 3 | L5: =IF(ISBLANK(customer_churn_dataset!L5),0,MAX(0,customer_churn_dataset!L5)) -> 1 | M5: =IF(ISBLANK(customer_churn_dataset!M5),0,customer_churn_dataset!M5) -> 0 | N5: =IF(ISBLANK(customer_churn_dataset!N5),0,MAX(0,customer_churn_dataset!N5)) -> 1166.22 | O5: =IF(ISBLANK(customer_churn_dataset!O5),0,customer_churn_dataset!O5) -> 0 | P5: =IF(COUNTIF(customer_churn_dataset!$A$2:$A$1501,customer_churn_dataset!A5)>1,"Duplicate","Unique") -> Unique
A6: =TRIM(customer_churn_dataset!A6) -> CUST101341 | B6: =PROPER(TRIM(customer_churn_dataset!B6)) -> Standard | C6: =PROPER(TRIM(customer_churn_dataset!C6)) -> Month-To-Month | D6: =IF(ISBLANK(customer_churn_dataset!D6),ROUND(MEDIAN(customer_churn_dataset!D$2:D$1501),2),IF(customer_churn_dataset!D6<0,ABS(customer_churn_dataset!D6),customer_churn_dataset!D6)) -> 20.96 | E6: =IF(ISBLANK(customer_churn_dataset!E6),0,MAX(0,customer_churn_dataset!E6)) -> 9 | F6: =IF(ISBLANK(customer_churn_dataset!F6),"",customer_churn_dataset!F6) -> 43837 | G6: =PROPER(TRIM(customer_churn_dataset!G6)) -> Bank Transfer | H6: =IF(ISBLANK(customer_churn_dataset!H6),0,customer_churn_dataset!H6) -> 1 | I6: =IF(ISBLANK(customer_churn_dataset!I6),ROUND(MEDIAN(customer_churn_dataset!I$2:I$1501),1),MIN(100,MAX(0,customer_churn_dataset!I6))) -> 54.2 | J6: =IF(ISBLANK(customer_churn_dataset!J6),0,MAX(0,customer_churn_dataset!J6)) -> 17 | K6: =IF(ISBLANK(customer_churn_dataset!K6),0,MIN(10,MAX(0,customer_churn_dataset!K6))) -> 6 | L6: =IF(ISBLANK(customer_churn_dataset!L6),0,MAX(0,customer_churn_dataset!L6)) -> 2 | M6: =IF(ISBLANK(customer_churn_dataset!M6),0,customer_churn_dataset!M6) -> 1 | N6: =IF(ISBLANK(customer_churn_dataset!N6),0,MAX(0,customer_churn_dataset!N6)) -> 188.64 | O6: =IF(ISBLANK(customer_churn_dataset!O6),0,customer_churn_dataset!O6) -> 0 | P6: =IF(COUNTIF(customer_churn_dataset!$A$2:$A$1501,customer_churn_dataset!A6)>1,"Duplicate","Unique") -> Unique
A7: =TRIM(customer_churn_dataset!A7) -> CUST101313 | B7: =PROPER(TRIM(customer_churn_dataset!B7)) -> Premium | C7: =PROPER(TRIM(customer_churn_dataset!C7)) -> One Year | D7: =IF(ISBLANK(customer_churn_dataset!D7),ROUND(MEDIAN(customer_churn_dataset!D$2:D$1501),2),IF(customer_churn_dataset!D7<0,ABS(customer_churn_dataset!D7),customer_churn_dataset!D7)) -> 38.61 | E7: =IF(ISBLANK(customer_churn_dataset!E7),0,MAX(0,customer_churn_dataset!E7)) -> 8 | F7: =IF(ISBLANK(customer_churn_dataset!F7),"",customer_churn_dataset!F7) -> 43839 | G7: =PROPER(TRIM(customer_churn_dataset!G7)) -> Credit Card | H7: =IF(ISBLANK(customer_churn_dataset!H7),0,customer_churn_dataset!H7) -> 0 | I7: =IF(ISBLANK(customer_churn_dataset!I7),ROUND(MEDIAN(customer_churn_dataset!I$2:I$1501),1),MIN(100,MAX(0,customer_churn_dataset!I7))) -> 45.7 | J7: =IF(ISBLANK(customer_churn_dataset!J7),0,MAX(0,customer_churn_dataset!J7)) -> 14 | K7: =IF(ISBLANK(customer_churn_dataset!K7),0,MIN(10,MAX(0,customer_churn_dataset!K7))) -> 2 | L7: =IF(ISBLANK(customer_churn_dataset!L7),0,MAX(0,customer_churn_dataset!L7)) -> 1 | M7: =IF(ISBLANK(customer_churn_dataset!M7),0,customer_churn_dataset!M7) -> 1 | N7: =IF(ISBLANK(customer_churn_dataset!N7),0,MAX(0,customer_churn_dataset!N7)) -> 308.88 | O7: =IF(ISBLANK(customer_churn_dataset!O7),0,customer_churn_dataset!O7) -> 1 | P7: =IF(COUNTIF(customer_churn_dataset!$A$2:$A$1501,customer_churn_dataset!A7)>1,"Duplicate","Unique") -> Unique
A8: =TRIM(customer_churn_dataset!A8) -> CUST100592 | B8: =PROPER(TRIM(customer_churn_dataset!B8)) -> Basic | C8: =PROPER(TRIM(customer_churn_dataset!C8)) -> Month-To-Month | D8: =IF(ISBLANK(customer_churn_dataset!D8),ROUND(MEDIAN(customer_churn_dataset!D$2:D$1501),2),IF(customer_churn_dataset!D8<0,ABS(customer_churn_dataset!D8),customer_churn_dataset!D8)) -> 9.34 | E8: =IF(ISBLANK(customer_churn_dataset!E8),0,MAX(0,customer_churn_dataset!E8)) -> 72 | F8: =IF(ISBLANK(customer_churn_dataset!F8),"",customer_churn_dataset!F8) -> 43842 | G8: =PROPER(TRIM(customer_churn_dataset!G8)) -> Bank Transfer | H8: =IF(ISBLANK(customer_churn_dataset!H8),0,customer_churn_dataset!H8) -> 0 | I8: =IF(ISBLANK(customer_churn_dataset!I8),ROUND(MEDIAN(customer_churn_dataset!I$2:I$1501),1),MIN(100,MAX(0,customer_churn_dataset!I8))) -> 72.8 | J8: =IF(ISBLANK(customer_churn_dataset!J8),0,MAX(0,customer_churn_dataset!J8)) -> 25 | K8: =IF(ISBLANK(customer_churn_dataset!K8),0,MIN(10,MAX(0,customer_churn_dataset!K8))) -> 8 | L8: =IF(ISBLANK(customer_churn_dataset!L8),0,MAX(0,customer_churn_dataset!L8)) -> 1 | M8: =IF(ISBLANK(customer_churn_dataset!M8),0,customer_churn_dataset!M8) -> 0 | N8: =IF(ISBLANK(customer_churn_dataset!N8),0,MAX(0,customer_churn_dataset!N8)) -> 672.48 | O8: =IF(ISBLANK(customer_churn_dataset!O8),0,customer_churn_dataset!O8) -> 0 | P8: =IF(COUNTIF(customer_churn_dataset!$A$2:$A$1501,customer_churn_dataset!A8)>1,"Duplicate","Unique") -> Unique
A9: =TRIM(customer_churn_dataset!A9) -> CUST101076 | B9: =PROPER(TRIM(customer_churn_dataset!B9)) -> Basic | C9: =PROPER(TRIM(customer_churn_dataset!C9)) -> Month-To-Month | D9: =IF(ISBLANK(customer_churn_dataset!D9),ROUND(MEDIAN(customer_churn_dataset!D$2:D$1501),2),IF(customer_churn_dataset!D9<0,ABS(customer_churn_dataset!D9),customer_churn_dataset!D9)) -> 10 | E9: =IF(ISBLANK(customer_churn_dataset!E9),0,MAX(0,customer_churn_dataset!E9)) -> 0 | F9: =IF(ISBLANK(customer_churn_dataset!F9),"",customer_churn_dataset!F9) -> 43843 | G9: =PROPER(TRIM(customer_churn_dataset!G9)) -> Credit Card | H9: =IF(ISBLANK(customer_churn_dataset!H9),0,customer_churn_dataset!H9) -> 0 | I9: =IF(ISBLANK(customer_churn_dataset!I9),ROUND(MEDIAN(customer_churn_dataset!I$2:I$1501),1),MIN(100,MAX(0,customer_churn_dataset!I9))) -> 33.9 | J9: =IF(ISBLANK(customer_churn_dataset!J9),0,MAX(0,customer_churn_dataset!J9)) -> 9 | K9: =IF(ISBLANK(customer_churn_dataset!K9),0,MIN(10,MAX(0,customer_churn_dataset!K9))) -> 4 | L9: =IF(ISBLANK(customer_churn_dataset!L9),0,MAX(0,customer_churn_dataset!L9)) -> 1 | M9: =IF(ISBLANK(customer_churn_dataset!M9),0,customer_churn_dataset!M9) -> 0 | N9: =IF(ISBLANK(customer_churn_dataset!N9),0,MAX(0,customer_churn_dataset!N9)) -> 0 | O9: =IF(ISBLANK(customer_churn_dataset!O9),0,customer_churn_dataset!O9) -> 1 | P9: =IF(COUNTIF(customer_churn_dataset!$A$2:$A$1501,customer_churn_dataset!A9)>1,"Duplicate","Unique") -> Unique
A10: =TRIM(customer_churn_dataset!A10) -> CUST101481 | B10: =PROPER(TRIM(customer_churn_dataset!B10)) -> Basic | C10: =PROPER(TRIM(customer_churn_dataset!C10)) -> Month-To-Month | D10: =IF(ISBLANK(customer_churn_dataset!D10),ROUND(MEDIAN(customer_churn_dataset!D$2:D$1501),2),IF(customer_churn_dataset!D10<0,ABS(customer_churn_dataset!D10),customer_churn_dataset!D10)) -> 9.77 | E10: =IF(ISBLANK(customer_churn_dataset!E10),0,MAX(0,customer_churn_dataset!E10)) -> 72 | F10: =IF(ISBLANK(customer_churn_dataset!F10),"",customer_churn_dataset!F10) -> 43843 | G10: =PROPER(TRIM(customer_churn_dataset!G10)) -> Paypal | H10: =IF(ISBLANK(customer_churn_dataset!H10),0,customer_churn_dataset!H10) -> 0 | I10: =IF(ISBLANK(customer_churn_dataset!I10),ROUND(MEDIAN(customer_churn_dataset!I$2:I$1501),1),MIN(100,MAX(0,customer_churn_dataset!I10))) -> 38.9 | J10: =IF(ISBLANK(customer_churn_dataset!J10),0,MAX(0,customer_churn_dataset!J10)) -> 10 | K10: =IF(ISBLANK(customer_churn_dataset!K10),0,MIN(10,MAX(0,customer_churn_dataset!K10))) -> 4 | L10: =IF(ISBLANK(customer_churn_dataset!L10),0,MAX(0,customer_churn_dataset!L10)) -> 1 | M10: =IF(ISBLANK(customer_churn_dataset!M10),0,customer_churn_dataset!M10) -> 1 | N10: =IF(ISBLANK(customer_churn_dataset!N10),0,MAX(0,customer_churn_dataset!N10)) -> 703.44 | O10: =IF(ISBLANK(customer_churn_dataset!O10),0,customer_churn_dataset!O10) -> 0 | P10: =IF(COUNTIF(customer_churn_dataset!$A$2:$A$1501,customer_churn_dataset!A10)>1,"Duplicate","Unique") -> Unique
A11: =TRIM(customer_churn_dataset!A11) -> CUST100688 | B11: =PROPER(TRIM(customer_churn_dataset!B11)) -> Standard | C11: =PROPER(TRIM(customer_churn_dataset!C11)) -> One Year | D11: =IF(ISBLANK(customer_churn_dataset!D11),ROUND(MEDIAN(customer_churn_dataset!D$2:D$1501),2),IF(customer_churn_dataset!D11<0,ABS(customer_churn_dataset!D11),customer_churn_dataset!D11)) -> 20.96 | E11: =IF(ISBLANK(customer_churn_dataset!E11),0,MAX(0,customer_churn_dataset!E11)) -> 39 | F11: =IF(ISBLANK(customer_churn_dataset!F11),"",customer_churn_dataset!F11) -> 43845 | G11: =PROPER(TRIM(customer_churn_dataset!G11)) -> Paypal | H11: =IF(ISBLANK(customer_churn_dataset!H11),0,customer_churn_dataset!H11) -> 1 | I11: =IF(ISBLANK(customer_churn_dataset!I11),ROUND(MEDIAN(customer_churn_dataset!I$2:I$1501),1),MIN(100,MAX(0,customer_churn_dataset!I11))) -> 42.3 | J11: =IF(ISBLANK(customer_churn_dataset!J11),0,MAX(0,customer_churn_dataset!J11)) -> 10 | K11: =IF(ISBLANK(customer_churn_dataset!K11),0,MIN(10,MAX(0,customer_churn_dataset!K11))) -> 5 | L11: =IF(ISBLANK(customer_churn_dataset!L11),0,MAX(0,customer_churn_dataset!L11)) -> 1 | M11: =IF(ISBLANK(customer_churn_dataset!M11),0,customer_churn_dataset!M11) -> 1 | N11: =IF(ISBLANK(customer_churn_dataset!N11),0,MAX(0,customer_churn_dataset!N11)) -> 817.44 | O11: =IF(ISBLANK(customer_churn_dataset!O11),0,customer_churn_dataset!O11) -> 0 | P11: =IF(COUNTIF(customer_churn_dataset!$A$2:$A$1501,customer_churn_dataset!A11)>1,"Duplicate","Unique") -> Unique
A12: =TRIM(customer_churn_dataset!A12) -> CUST100968 | B12: =PROPER(TRIM(customer_churn_dataset!B12)) -> Standard | C12: =PROPER(TRIM(customer_churn_dataset!C12)) -> Month-To-Month | D12: =IF(ISBLANK(customer_churn_dataset!D12),ROUND(MEDIAN(customer_churn_dataset!D$2:D$1501),2),IF(customer_churn_dataset!D12<0,ABS(customer_churn_dataset!D12),customer_churn_dataset!D12)) -> 20.71 | E12: =IF(ISBLANK(customer_churn_dataset!E12),0,MAX(0,customer_churn_dataset!E12)) -> 35 | F12: =IF(ISBLANK(customer_churn_dataset!F12),"",customer_churn_dataset!F12) -> 43845 | G12: =PROPER(TRIM(customer_churn_dataset!G12)) -> Credit Card | H12: =IF(ISBLANK(customer_churn_dataset!H12),0,customer_churn_dataset!H12) -> 0 | I12: =IF(ISBLANK(customer_churn_dataset!I12),ROUND(MEDIAN(customer_churn_dataset!I$2:I$1501),1),MIN(100,MAX(0,customer_churn_dataset!I12))) -> 76.7 | J12: =IF(ISBLANK(customer_churn_dataset!J12),0,MAX(0,customer_churn_dataset!J12)) -> 25 | K12: =IF(ISBLANK(customer_churn_dataset!K12),0,MIN(10,MAX(0,customer_churn_dataset!K12))) -> 6 | L12: =IF(ISBLANK(customer_churn_dataset!L12),0,MAX(0,customer_churn_dataset!L12)) -> 0 | M12: =IF(ISBLANK(customer_churn_dataset!M12),0,customer_churn_dataset!M12) -> 0 | N12: =IF(ISBLANK(customer_churn_dataset!N12),0,MAX(0,customer_churn_dataset!N12)) -> 724.85 | O12: =IF(ISBLANK(customer_churn_dataset!O12),0,customer_churn_dataset!O12) -> 0 | P12: =IF(COUNTIF(customer_churn_dataset!$A$2:$A$1501,customer_churn_dataset!A12)>1,"Duplicate","Unique") -> Unique
A13: =TRIM(customer_churn_dataset!A13) -> CUST101408 | B13: =PROPER(TRIM(customer_churn_dataset!B13)) -> Standard | C13: =PROPER(TRIM(customer_churn_dataset!C13)) -> Month-To-Month | D13: =IF(ISBLANK(customer_churn_dataset!D13),ROUND(MEDIAN(customer_churn_dataset!D$2:D$1501),2),IF(customer_churn_dataset!D13<0,ABS(customer_churn_dataset!D13),customer_churn_dataset!D13)) -> 20.85 | E13: =IF(ISBLANK(customer_churn_dataset!E13),0,MAX(0,customer_churn_dataset!E13)) -> 19 | F13: =IF(ISBLANK(customer_churn_dataset!F13),"",customer_churn_dataset!F13) -> 43845 | G13: =PROPER(TRIM(customer_churn_dataset!G13)) -> Credit Card | H13: =IF(ISBLANK(customer_churn_dataset!H13),0,customer_churn_dataset!H13) -> 1 | I13: =IF(ISBLANK(customer_churn_dataset!I13),ROUND(MEDIAN(customer_churn_dataset!I$2:I$1501),1),MIN(100,MAX(0,customer_churn_dataset!I13))) -> 47.5 | J13: =IF(ISBLANK(customer_churn_dataset!J13),0,MAX(0,customer_churn_dataset!J13)) -> 20 | K13: =IF(ISBLANK(customer_churn_dataset!K13),0,MIN(10,MAX(0,customer_churn_dataset!K13))) -> 6 | L13: =IF(ISBLANK(customer_churn_dataset!L13),0,MAX(0,customer_churn_dataset!L13)) -> 3 | M13: =IF(ISBLANK(customer_churn_dataset!M13),0,customer_churn_dataset!M13) -> 0 | N13: =IF(ISBLANK(customer_churn_dataset!N13),0,MAX(0,customer_churn_dataset!N13)) -> 396.15 | O13: =IF(ISBLANK(customer_churn_dataset!O13),0,customer_churn_dataset!O13) -> 0 | P13: =IF(COUNTIF(customer_churn_dataset!$A$2:$A$1501,customer_churn_dataset!A13)>1,"Duplicate","Unique") -> Unique
... A1501: =TRIM(customer_churn_dataset!A1501) -> CUST100898 | B1501: =PROPER(TRIM(customer_churn_dataset!B1501)) -> Basic | C1501: =PROPER(TRIM(customer_churn_dataset!C1501)) -> One Year | D1501: =IF(ISBLANK(customer_churn_dataset!D1501),ROUND(MEDIAN(customer_churn_dataset!D$2:D$1501),2),IF(customer_churn_dataset!D1501<0,ABS(customer_churn_dataset!D1501),customer_churn_dataset!D1501)) -> 10.25 | E1501: =IF(ISBLANK(customer_churn_dataset!E1501),0,MAX(0,customer_churn_dataset!E1501)) -> 45 | F1501: =IF(ISBLANK(customer_churn_dataset!F1501),"",customer_churn_dataset!F1501) -> 45829 | G1501: =PROPER(TRIM(customer_churn_dataset!G1501)) -> Bank Transfer | H1501: =IF(ISBLANK(customer_churn_dataset!H1501),0,customer_churn_dataset!H1501) -> 1 | I1501: =IF(ISBLANK(customer_churn_dataset!I1501),ROUND(MEDIAN(customer_churn_dataset!I$2:I$1501),1),MIN(100,MAX(0,customer_churn_dataset!I1501))) -> 37.5 | J1501: =IF(ISBLANK(customer_churn_dataset!J1501),0,MAX(0,customer_churn_dataset!J1501)) -> 7 | K1501: =IF(ISBLANK(customer_churn_dataset!K1501),0,MIN(10,MAX(0,customer_churn_dataset!K1501))) -> 3 | L1501: =IF(ISBLANK(customer_churn_dataset!L1501),0,MAX(0,customer_churn_dataset!L1501)) -> 0 | M1501: =IF(ISBLANK(customer_churn_dataset!M1501),0,customer_churn_dataset!M1501) -> 0 | N1501: =IF(ISBLANK(customer_churn_dataset!N1501),0,MAX(0,customer_churn_dataset!N1501)) -> 461.25 | O1501: =IF(ISBLANK(customer_churn_dataset!O1501),0,customer_churn_dataset!O1501) -> 0 | P1501: =IF(COUNTIF(customer_churn_dataset!$A$2:$A$1501,customer_churn_dataset!A1501)>1,"Duplicate","Unique") -> Unique

Sheet Summary
A1: Customer Churn Analysis - Executive Summary
A3: Overall Metrics
A4: Metric | B4: Value
A5: Total Customers | B5: =COUNTA(customer_churn_dataset!$A$2:$A$1501) -> 1500
A6: Churned Customers | B6: =COUNTIF(customer_churn_dataset!$O$2:$O$1501,1) -> 284
A7: Overall Churn Rate | B7: =B6/B5 -> 0.18933333
A9: Data Quality Check
A10: Check | B10: Count
A11: Rows with Complete Data | B11: =COUNTA(customer_churn_dataset!$A$2:$A$1501) -> 1500
A12: Rows with Missing Data | B12: =COUNTIF(customer_churn_dataset!$U$2:$U$1501,"Missing Data") -> 0
A13: % Rows Missing Data | B13: =B12/B11 -> 0
A16: Churn Rate by Plan
A17: Plan | B17: Customers | C17: Churned | D17: Churn Rate
A18: Basic | B18: =COUNTIF(customer_churn_dataset!$B$2:$B$1501,A18) -> 671 | C18: =COUNTIFS(customer_churn_dataset!$B$2:$B$1501,A18,customer_churn_dataset!$O$2:$O$1501,1) -> 137 | D18: =C18/B18 -> 0.20417288
A19: Standard | B19: =COUNTIF(customer_churn_dataset!$B$2:$B$1501,A19) -> 518 | C19: =COUNTIFS(customer_churn_dataset!$B$2:$B$1501,A19,customer_churn_dataset!$O$2:$O$1501,1) -> 86 | D19: =C19/B19 -> 0.16602317
A20: Premium | B20: =COUNTIF(customer_churn_dataset!$B$2:$B$1501,A20) -> 311 | C20: =COUNTIFS(customer_churn_dataset!$B$2:$B$1501,A20,customer_churn_dataset!$O$2:$O$1501,1) -> 61 | D20: =C20/B20 -> 0.19614148
A22: Churn Rate by Contract Type
A23: Contract Type | B23: Customers | C23: Churned | D23: Churn Rate
A24: Month-to-month | B24: =COUNTIF(customer_churn_dataset!$C$2:$C$1501,A24) -> 828 | C24: =COUNTIFS(customer_churn_dataset!$C$2:$C$1501,A24,customer_churn_dataset!$O$2:$O$1501,1) -> 233 | D24: =C24/B24 -> 0.28140097
A25: One year | B25: =COUNTIF(customer_churn_dataset!$C$2:$C$1501,A25) -> 462 | C25: =COUNTIFS(customer_churn_dataset!$C$2:$C$1501,A25,customer_churn_dataset!$O$2:$O$1501,1) -> 37 | D25: =C25/B25 -> 0.08008658
A26: Two year | B26: =COUNTIF(customer_churn_dataset!$C$2:$C$1501,A26) -> 210 | C26: =COUNTIFS(customer_churn_dataset!$C$2:$C$1501,A26,customer_churn_dataset!$O$2:$O$1501,1) -> 14 | D26: =C26/B26 -> 0.066666667
A28: Churn Rate by Tenure
A29: Tenure Bucket | B29: Customers | C29: Churned | D29: Churn Rate
A30: 0-6mo | B30: =COUNTIF(customer_churn_dataset!$S$2:$S$1501,A30) -> 359 | C30: =COUNTIFS(customer_churn_dataset!$S$2:$S$1501,A30,customer_churn_dataset!$O$2:$O$1501,1) -> 83 | D30: =C30/B30 -> 0.23119777
A31: 6-12mo | B31: =COUNTIF(customer_churn_dataset!$S$2:$S$1501,A31) -> 278 | C31: =COUNTIFS(customer_churn_dataset!$S$2:$S$1501,A31,customer_churn_dataset!$O$2:$O$1501,1) -> 69 | D31: =C31/B31 -> 0.24820144
A32: 12-24mo | B32: =COUNTIF(customer_churn_dataset!$S$2:$S$1501,A32) -> 378 | C32: =COUNTIFS(customer_churn_dataset!$S$2:$S$1501,A32,customer_churn_dataset!$O$2:$O$1501,1) -> 64 | D32: =C32/B32 -> 0.16931217
A33: 24mo+ | B33: =COUNTIF(customer_churn_dataset!$S$2:$S$1501,A33) -> 485 | C33: =COUNTIFS(customer_churn_dataset!$S$2:$S$1501,A33,customer_churn_dataset!$O$2:$O$1501,1) -> 68 | D33: =C33/B33 -> 0.14020619
A35: Revenue: Churned vs Retained
A36: Segment | B36: Customers | C36: Total Revenue | D36: Avg Revenue/Customer
A37: Retained | B37: =COUNTIF(customer_churn_dataset!$O$2:$O$1501,0) -> 1216 | C37: =SUMIFS(customer_churn_dataset!$N$2:$N$1501,customer_churn_dataset!$O$2:$O$1501,0) -> 511265.37 | D37: =C37/B37 -> 420.4485
A38: Churned | B38: =COUNTIF(customer_churn_dataset!$O$2:$O$1501,1) -> 284 | C38: =SUMIFS(customer_churn_dataset!$N$2:$N$1501,customer_churn_dataset!$O$2:$O$1501,1) -> 91109.6 | D38: =C38/B38 -> 320.80845
A39: % of Total Revenue Lost to Churn
A41: Usage Patterns by Churn Status
A42: Status | B42: Avg Usage Score | C42: Avg Logins/Month | D42: Avg Features Used
A43: Retained | B43: =IFERROR(AVERAGEIFS(customer_churn_dataset!$I$2:$I$1501,customer_churn_dataset!$O$2:$O$1501,0),"N/A") -> 55.961513 | C43: =IFERROR(AVERAGEIFS(customer_churn_dataset!$J$2:$J$1501,customer_churn_dataset!$O$2:$O$1501,0),"N/A") -> 17.037007 | D43: =IFERROR(AVERAGEIFS(customer_churn_dataset!$K$2:$K$1501,customer_churn_dataset!$O$2:$O$1501,0),"N/A") -> 5.5320724
A44: Churned | B44: =IFERROR(AVERAGEIFS(customer_churn_dataset!$I$2:$I$1501,customer_churn_dataset!$O$2:$O$1501,1),"N/A") -> 47.295775 | C44: =IFERROR(AVERAGEIFS(customer_churn_dataset!$J$2:$J$1501,customer_churn_dataset!$O$2:$O$1501,1),"N/A") -> 14.158451 | D44: =IFERROR(AVERAGEIFS(customer_churn_dataset!$K$2:$K$1501,customer_churn_dataset!$O$2:$O$1501,1),"N/A") -> 4.7676056
A46: Complaints & Churn
A47: Segment | B47: Customers | C47: Churned | D47: Churn Rate
A48: Avg Support Tickets - Retained | B48: =IFERROR(AVERAGEIFS(customer_churn_dataset!$L$2:$L$1501,customer_churn_dataset!$O$2:$O$1501,0),"N/A") -> 1.3215461
A49: Avg Support Tickets - Churned | B49: =IFERROR(AVERAGEIFS(customer_churn_dataset!$L$2:$L$1501,customer_churn_dataset!$O$2:$O$1501,1),"N/A") -> 1.834507
A50: No Unresolved Complaint | B50: =COUNTIF(customer_churn_dataset!$M$2:$M$1501,0) -> 1092 | C50: =COUNTIFS(customer_churn_dataset!$M$2:$M$1501,0,customer_churn_dataset!$O$2:$O$1501,1) -> 170 | D50: =C50/B50 -> 0.15567766
A51: Has Unresolved Complaint | B51: =COUNTIF(customer_churn_dataset!$M$2:$M$1501,1) -> 408 | C51: =COUNTIFS(customer_churn_dataset!$M$2:$M$1501,1,customer_churn_dataset!$O$2:$O$1501,1) -> 114 | D51: =C51/B51 -> 0.27941176
A53: Churn by Autopay & Payment Method
A54: Segment | B54: Customers | C54: Churned | D54: Churn Rate
A55: Autopay Off | B55: =COUNTIF(customer_churn_dataset!$H$2:$H$1501,0) -> 494 | C55: =COUNTIFS(customer_churn_dataset!$H$2:$H$1501,0,customer_churn_dataset!$O$2:$O$1501,1) -> 108 | D55: =C55/B55 -> 0.21862348
A56: Autopay On | B56: =COUNTIF(customer_churn_dataset!$H$2:$H$1501,1) -> 1006 | C56: =COUNTIFS(customer_churn_dataset!$H$2:$H$1501,1,customer_churn_dataset!$O$2:$O$1501,1) -> 176 | D56: =C56/B56 -> 0.1749503
A57: Credit card | B57: =COUNTIF(customer_churn_dataset!$G$2:$G$1501,A57) -> 701 | C57: =COUNTIFS(customer_churn_dataset!$G$2:$G$1501,A57,customer_churn_dataset!$O$2:$O$1501,1) -> 114 | D57: =C57/B57 -> 0.16262482
A58: PayPal | B58: =COUNTIF(customer_churn_dataset!$G$2:$G$1501,A58) -> 380 | C58: =COUNTIFS(customer_churn_dataset!$G$2:$G$1501,A58,customer_churn_dataset!$O$2:$O$1501,1) -> 76 | D58: =C58/B58 -> 0.2
A59: Bank transfer | B59: =COUNTIF(customer_churn_dataset!$G$2:$G$1501,A59) -> 266 | C59: =COUNTIFS(customer_churn_dataset!$G$2:$G$1501,A59,customer_churn_dataset!$O$2:$O$1501,1) -> 60 | D59: =C59/B59 -> 0.22556391
A60: Manual/Invoice | B60: =COUNTIF(customer_churn_dataset!$G$2:$G$1501,A60) -> 153 | C60: =COUNTIFS(customer_churn_dataset!$G$2:$G$1501,A60,customer_churn_dataset!$O$2:$O$1501,1) -> 34 | D60: =C60/B60 -> 0.22222222
A62: High-Risk Segment: Month-to-Month + Low Usage(<40) + Unresolved Complaint
A63: Segment | B63: Customers | C63: Churned | D63: Churn Rate
A64: High-Risk Segment | B64: =COUNTIFS(customer_churn_dataset!$C$2:$C$1501,"Month-to-month",customer_churn_dataset!$I$2:$I$1501,"<40",customer_churn_dataset!$M$2:$M$1501,1) -> 66 | C64: =COUNTIFS(customer_churn_dataset!$C$2:$C$1501,"Month-to-month",customer_churn_dataset!$I$2:$I$1501,"<40",customer_churn_dataset!$M$2:$M$1501,1,customer_churn_dataset!$O$2:$O$1501,1) -> 34 | D64: =C64/B64 -> 0.51515152
A66: Cohort Churn Rate by Signup Year
A67: Signup Year | B67: Customers | C67: Churned | D67: Churn Rate
A68: 2020 | B68: =COUNTIF(customer_churn_dataset!$R$2:$R$1501,A68) -> 266 | C68: =COUNTIFS(customer_churn_dataset!$R$2:$R$1501,A68,customer_churn_dataset!$O$2:$O$1501,1) -> 48 | D68: =C68/B68 -> 0.18045113
A69: 2021 | B69: =COUNTIF(customer_churn_dataset!$R$2:$R$1501,A69) -> 274 | C69: =COUNTIFS(customer_churn_dataset!$R$2:$R$1501,A69,customer_churn_dataset!$O$2:$O$1501,1) -> 70 | D69: =C69/B69 -> 0.25547445
A70: 2022 | B70: =COUNTIF(customer_churn_dataset!$R$2:$R$1501,A70) -> 284 | C70: =COUNTIFS(customer_churn_dataset!$R$2:$R$1501,A70,customer_churn_dataset!$O$2:$O$1501,1) -> 51 | D70: =C70/B70 -> 0.17957746
A71: 2023 | B71: =COUNTIF(customer_churn_dataset!$R$2:$R$1501,A71) -> 300 | C71: =COUNTIFS(customer_churn_dataset!$R$2:$R$1501,A71,customer_churn_dataset!$O$2:$O$1501,1) -> 50 | D71: =C71/B71 -> 0.16666667
A72: 2024 | B72: =COUNTIF(customer_churn_dataset!$R$2:$R$1501,A72) -> 242 | C72: =COUNTIFS(customer_churn_dataset!$R$2:$R$1501,A72,customer_churn_dataset!$O$2:$O$1501,1) -> 46 | D72: =C72/B72 -> 0.19008264
A73: 2025 | B73: =COUNTIF(customer_churn_dataset!$R$2:$R$1501,A73) -> 134 | C73: =COUNTIFS(customer_churn_dataset!$R$2:$R$1501,A73,customer_churn_dataset!$O$2:$O$1501,1) -> 19 | D73: =C73/B73 -> 0.14179104

Sheet Sheet4
A1: Top 50 Active At Risk Customers
A3: Customer_Id | B3: Plan | C3: Contract_Type | D3: Tenure (mo) | E3: Usage_Score | F3: Support_Tickets | G3: Unresolved_complaint | H3: Revenue | I3: Churned | J3: Risk_Score | K3: Risk_Level
A4: =customer_churn_dataset!A1501 -> CUST100898 | B4: =customer_churn_dataset!B1501 -> Basic | C4: =customer_churn_dataset!C1501 -> One year | D4: =INDEX(customer_churn_dataset!$E$2:$E$1501,MATCH($A5,customer_churn_dataset!$A$2:$A$1501,0)) -> 72 | E4: =INDEX(customer_churn_dataset!$I$2:$I$1501,MATCH($A5,customer_churn_dataset!$A$2:$A$1501,0)) -> 38.9 | F4: =INDEX(customer_churn_dataset!$L$2:$L$1501,MATCH($A5,customer_churn_dataset!$A$2:$A$1501,0)) -> 1 | G4: =IF(INDEX(customer_churn_dataset!$M$2:$M$1501,MATCH($A5,customer_churn_dataset!$A$2:$A$1501,0))=1,"Yes","No") -> Yes | H4: =INDEX(customer_churn_dataset!$N$2:$N$1501,MATCH($A5,customer_churn_dataset!$A$2:$A$1501,0)) -> 703.44 | I4: =INDEX(customer_churn_dataset!$O$2:$O$1501,MATCH($A5,customer_churn_dataset!$A$2:$A$1501,0)) -> 0 | J4: =INDEX(customer_churn_dataset!$T$2:$T$1501,MATCH($A5,customer_churn_dataset!$A$2:$A$1501,0)) -> 7 | K4: =INDEX(customer_churn_dataset!$V$2:$V$1501,MATCH($A5,customer_churn_dataset!$A$2:$A$1501,0)) -> High Risk
A5: =customer_churn_dataset!A10 -> CUST101481 | B5: =customer_churn_dataset!B10 -> Basic | C5: =customer_churn_dataset!C10 -> Month-to-month | D5: =INDEX(customer_churn_dataset!$E$2:$E$1501,MATCH($A6,customer_churn_dataset!$A$2:$A$1501,0)) -> 8 | E5: =INDEX(customer_churn_dataset!$I$2:$I$1501,MATCH($A6,customer_churn_dataset!$A$2:$A$1501,0)) -> 45.7 | F5: =INDEX(customer_churn_dataset!$L$2:$L$1501,MATCH($A6,customer_churn_dataset!$A$2:$A$1501,0)) -> 1 | G5: =IF(INDEX(customer_churn_dataset!$M$2:$M$1501,MATCH($A6,customer_churn_dataset!$A$2:$A$1501,0))=1,"Yes","No") -> Yes | H5: =INDEX(customer_churn_dataset!$N$2:$N$1501,MATCH($A6,customer_churn_dataset!$A$2:$A$1501,0)) -> 308.88 | I5: =INDEX(customer_churn_dataset!$O$2:$O$1501,MATCH($A6,customer_churn_dataset!$A$2:$A$1501,0)) -> 1 | J5: =INDEX(customer_churn_dataset!$T$2:$T$1501,MATCH($A6,customer_churn_dataset!$A$2:$A$1501,0)) -> 6 | K5: =INDEX(customer_churn_dataset!$V$2:$V$1501,MATCH($A6,customer_churn_dataset!$A$2:$A$1501,0)) -> High Risk
A6: =customer_churn_dataset!A7 -> CUST101313 | B6: =customer_churn_dataset!B7 -> Premium | C6: =customer_churn_dataset!C7 -> One year | D6: =INDEX(customer_churn_dataset!$E$2:$E$1501,MATCH($A7,customer_churn_dataset!$A$2:$A$1501,0)) -> 19 | E6: =INDEX(customer_churn_dataset!$I$2:$I$1501,MATCH($A7,customer_churn_dataset!$A$2:$A$1501,0)) -> 48.9 | F6: =INDEX(customer_churn_dataset!$L$2:$L$1501,MATCH($A7,customer_churn_dataset!$A$2:$A$1501,0)) -> 0 | G6: =IF(INDEX(customer_churn_dataset!$M$2:$M$1501,MATCH($A7,customer_churn_dataset!$A$2:$A$1501,0))=1,"Yes","No") -> No | H6: =INDEX(customer_churn_dataset!$N$2:$N$1501,MATCH($A7,customer_churn_dataset!$A$2:$A$1501,0)) -> 212.99 | I6: =INDEX(customer_churn_dataset!$O$2:$O$1501,MATCH($A7,customer_churn_dataset!$A$2:$A$1501,0)) -> 0 | J6: =INDEX(customer_churn_dataset!$T$2:$T$1501,MATCH($A7,customer_churn_dataset!$A$2:$A$1501,0)) -> 3 | K6: =INDEX(customer_churn_dataset!$V$2:$V$1501,MATCH($A7,customer_churn_dataset!$A$2:$A$1501,0)) -> Medium Risk
A7: =customer_churn_dataset!A27 -> CUST100360 | B7: =customer_churn_dataset!B27 -> Basic | C7: =customer_churn_dataset!C27 -> Month-to-month | D7: =INDEX(customer_churn_dataset!$E$2:$E$1501,MATCH($A8,customer_churn_dataset!$A$2:$A$1501,0)) -> 57 | E7: =INDEX(customer_churn_dataset!$I$2:$I$1501,MATCH($A8,customer_churn_dataset!$A$2:$A$1501,0)) -> 42.4 | F7: =INDEX(customer_churn_dataset!$L$2:$L$1501,MATCH($A8,customer_churn_dataset!$A$2:$A$1501,0)) -> 1 | G7: =IF(INDEX(customer_churn_dataset!$M$2:$M$1501,MATCH($A8,customer_churn_dataset!$A$2:$A$1501,0))=1,"Yes","No") -> No | H7: =INDEX(customer_churn_dataset!$N$2:$N$1501,MATCH($A8,customer_churn_dataset!$A$2:$A$1501,0)) -> 1166.22 | I7: =INDEX(customer_churn_dataset!$O$2:$O$1501,MATCH($A8,customer_churn_dataset!$A$2:$A$1501,0)) -> 0 | J7: =INDEX(customer_churn_dataset!$T$2:$T$1501,MATCH($A8,customer_churn_dataset!$A$2:$A$1501,0)) -> 3 | K7: =INDEX(customer_churn_dataset!$V$2:$V$1501,MATCH($A8,customer_churn_dataset!$A$2:$A$1501,0)) -> Medium Risk
A8: =customer_churn_dataset!A5 -> CUST101045 | B8: =customer_churn_dataset!B5 -> Standard | C8: =customer_churn_dataset!C5 -> Month-to-month | D8: =INDEX(customer_churn_dataset!$E$2:$E$1501,MATCH($A9,customer_churn_dataset!$A$2:$A$1501,0)) -> 8 | E8: =INDEX(customer_churn_dataset!$I$2:$I$1501,MATCH($A9,customer_churn_dataset!$A$2:$A$1501,0)) -> 27.8 | F8: =INDEX(customer_churn_dataset!$L$2:$L$1501,MATCH($A9,customer_churn_dataset!$A$2:$A$1501,0)) -> 3 | G8: =IF(INDEX(customer_churn_dataset!$M$2:$M$1501,MATCH($A9,customer_churn_dataset!$A$2:$A$1501,0))=1,"Yes","No") -> No | H8: =INDEX(customer_churn_dataset!$N$2:$N$1501,MATCH($A9,customer_churn_dataset!$A$2:$A$1501,0)) -> 99.84 | I8: =INDEX(customer_churn_dataset!$O$2:$O$1501,MATCH($A9,customer_churn_dataset!$A$2:$A$1501,0)) -> 0 | J8: =INDEX(customer_churn_dataset!$T$2:$T$1501,MATCH($A9,customer_churn_dataset!$A$2:$A$1501,0)) -> 4 | K8: =INDEX(customer_churn_dataset!$V$2:$V$1501,MATCH($A9,customer_churn_dataset!$A$2:$A$1501,0)) -> Medium Risk
A9: =customer_churn_dataset!A53 -> CUST100131 | B9: =customer_churn_dataset!B53 -> Basic | C9: =customer_churn_dataset!C53 -> Two year | D9: =INDEX(customer_churn_dataset!$E$2:$E$1501,MATCH($A10,customer_churn_dataset!$A$2:$A$1501,0)) -> 41 | E9: =INDEX(customer_churn_dataset!$I$2:$I$1501,MATCH($A10,customer_churn_dataset!$A$2:$A$1501,0)) -> 52.7 | F9: =INDEX(customer_churn_dataset!$L$2:$L$1501,MATCH($A10,customer_churn_dataset!$A$2:$A$1501,0)) -> 0 | G9: =IF(INDEX(customer_churn_dataset!$M$2:$M$1501,MATCH($A10,customer_churn_dataset!$A$2:$A$1501,0))=1,"Yes","No") -> No | H9: =INDEX(customer_churn_dataset!$N$2:$N$1501,MATCH($A10,customer_churn_dataset!$A$2:$A$1501,0)) -> 450.18 | I9: =INDEX(customer_churn_dataset!$O$2:$O$1501,MATCH($A10,customer_churn_dataset!$A$2:$A$1501,0)) -> 0 | J9: =INDEX(customer_churn_dataset!$T$2:$T$1501,MATCH($A10,customer_churn_dataset!$A$2:$A$1501,0)) -> 3 | K9: =INDEX(customer_churn_dataset!$V$2:$V$1501,MATCH($A10,customer_churn_dataset!$A$2:$A$1501,0)) -> Medium Risk
A10: =customer_churn_dataset!A48 -> CUST100141 | B10: =customer_churn_dataset!B48 -> Basic | C10: =customer_churn_dataset!C48 -> Month-to-month | D10: =INDEX(customer_churn_dataset!$E$2:$E$1501,MATCH($A11,customer_churn_dataset!$A$2:$A$1501,0)) -> 4 | E10: =INDEX(customer_churn_dataset!$I$2:$I$1501,MATCH($A11,customer_churn_dataset!$A$2:$A$1501,0)) -> 54 | F10: =INDEX(customer_churn_dataset!$L$2:$L$1501,MATCH($A11,customer_churn_dataset!$A$2:$A$1501,0)) -> 3 | G10: =IF(INDEX(customer_churn_dataset!$M$2:$M$1501,MATCH($A11,customer_churn_dataset!$A$2:$A$1501,0))=1,"Yes","No") -> No | H10: =INDEX(customer_churn_dataset!$N$2:$N$1501,MATCH($A11,customer_churn_dataset!$A$2:$A$1501,0)) -> 158.88 | I10: =INDEX(customer_churn_dataset!$O$2:$O$1501,MATCH($A11,customer_churn_dataset!$A$2:$A$1501,0)) -> 1 | J10: =INDEX(customer_churn_dataset!$T$2:$T$1501,MATCH($A11,customer_churn_dataset!$A$2:$A$1501,0)) -> 5 | K10: =INDEX(customer_churn_dataset!$V$2:$V$1501,MATCH($A11,customer_churn_dataset!$A$2:$A$1501,0)) -> Medium Risk
A11: =customer_churn_dataset!A31 -> CUST101027 | B11: =customer_churn_dataset!B31 -> Premium | C11: =customer_churn_dataset!C31 -> Month-to-month | D11: =INDEX(customer_churn_dataset!$E$2:$E$1501,MATCH($A12,customer_churn_dataset!$A$2:$A$1501,0)) -> 4 | E11: =INDEX(customer_churn_dataset!$I$2:$I$1501,MATCH($A12,customer_churn_dataset!$A$2:$A$1501,0)) -> 47.5 | F11: =INDEX(customer_churn_dataset!$L$2:$L$1501,MATCH($A12,customer_churn_dataset!$A$2:$A$1501,0)) -> 1 | G11: =IF(INDEX(customer_churn_dataset!$M$2:$M$1501,MATCH($A12,customer_churn_dataset!$A$2:$A$1501,0))=1,"Yes","No") -> Yes | H11: =INDEX(customer_churn_dataset!$N$2:$N$1501,MATCH($A12,customer_churn_dataset!$A$2:$A$1501,0)) -> 77.8 | I11: =INDEX(customer_churn_dataset!$O$2:$O$1501,MATCH($A12,customer_churn_dataset!$A$2:$A$1501,0)) -> 0 | J11: =INDEX(customer_churn_dataset!$T$2:$T$1501,MATCH($A12,customer_churn_dataset!$A$2:$A$1501,0)) -> 7 | K11: =INDEX(customer_churn_dataset!$V$2:$V$1501,MATCH($A12,customer_churn_dataset!$A$2:$A$1501,0)) -> High Risk
A12: =customer_churn_dataset!A62 -> CUST101206 | B12: =customer_churn_dataset!B62 -> Standard | C12: =customer_churn_dataset!C62 -> Month-to-month | D12: =INDEX(customer_churn_dataset!$E$2:$E$1501,MATCH($A13,customer_churn_dataset!$A$2:$A$1501,0)) -> 14 | E12: =INDEX(customer_churn_dataset!$I$2:$I$1501,MATCH($A13,customer_churn_dataset!$A$2:$A$1501,0)) -> 24.1 | F12: =INDEX(customer_churn_dataset!$L$2:$L$1501,MATCH($A13,customer_churn_dataset!$A$2:$A$1501,0)) -> 5 | G12: =IF(INDEX(customer_churn_dataset!$M$2:$M$1501,MATCH($A13,customer_churn_dataset!$A$2:$A$1501,0))=1,"Yes","No") -> No | H12: =INDEX(customer_churn_dataset!$N$2:$N$1501,MATCH($A13,customer_churn_dataset!$A$2:$A$1501,0)) -> 553.42 | I12: =INDEX(customer_churn_dataset!$O$2:$O$1501,MATCH($A13,customer_churn_dataset!$A$2:$A$1501,0)) -> 0 | J12: =INDEX(customer_churn_dataset!$T$2:$T$1501,MATCH($A13,customer_churn_dataset!$A$2:$A$1501,0)) -> 3 | K12: =INDEX(customer_churn_dataset!$V$2:$V$1501,MATCH($A13,customer_churn_dataset!$A$2:$A$1501,0)) -> Medium Risk
A13: =customer_churn_dataset!A73 -> CUST100383 | B13: =customer_churn_dataset!B73 -> Premium | C13: =customer_churn_dataset!C73 -> Two year | D13: =INDEX(customer_churn_dataset!$E$2:$E$1501,MATCH($A14,customer_churn_dataset!$A$2:$A$1501,0)) -> 2 | E13: =INDEX(customer_churn_dataset!$I$2:$I$1501,MATCH($A14,customer_churn_dataset!$A$2:$A$1501,0)) -> 52.8 | F13: =INDEX(customer_churn_dataset!$L$2:$L$1501,MATCH($A14,customer_churn_dataset!$A$2:$A$1501,0)) -> 0 | G13: =IF(INDEX(customer_churn_dataset!$M$2:$M$1501,MATCH($A14,customer_churn_dataset!$A$2:$A$1501,0))=1,"Yes","No") -> No | H13: =INDEX(customer_churn_dataset!$N$2:$N$1501,MATCH($A14,customer_churn_dataset!$A$2:$A$1501,0)) -> 16.94 | I13: =INDEX(customer_churn_dataset!$O$2:$O$1501,MATCH($A14,customer_churn_dataset!$A$2:$A$1501,0)) -> 0 | J13: =INDEX(customer_churn_dataset!$T$2:$T$1501,MATCH($A14,customer_churn_dataset!$A$2:$A$1501,0)) -> 4 | K13: =INDEX(customer_churn_dataset!$V$2:$V$1501,MATCH($A14,customer_churn_dataset!$A$2:$A$1501,0)) -> Medium Risk
A14: =customer_churn_dataset!A79 -> CUST101202 | B14: =customer_churn_dataset!B79 -> Basic | C14: =customer_churn_dataset!C79 -> Month-to-month | D14: =INDEX(customer_churn_dataset!$E$2:$E$1501,MATCH($A15,customer_churn_dataset!$A$2:$A$1501,0)) -> 38 | E14: =INDEX(customer_churn_dataset!$I$2:$I$1501,MATCH($A15,customer_churn_dataset!$A$2:$A$1501,0)) -> 81.6 | F14: =INDEX(customer_churn_dataset!$L$2:$L$1501,MATCH($A15,customer_churn_dataset!$A$2:$A$1501,0)) -> 1 | G14: =IF(INDEX(customer_churn_dataset!$M$2:$M$1501,MATCH($A15,customer_churn_dataset!$A$2:$A$1501,0))=1,"Yes","No") -> Yes | H14: =INDEX(customer_churn_dataset!$N$2:$N$1501,MATCH($A15,customer_churn_dataset!$A$2:$A$1501,0)) -> 1533.68 | I14: =INDEX(customer_churn_dataset!$O$2:$O$1501,MATCH($A15,customer_churn_dataset!$A$2:$A$1501,0)) -> 0 | J14: =INDEX(customer_churn_dataset!$T$2:$T$1501,MATCH($A15,customer_churn_dataset!$A$2:$A$1501,0)) -> 4 | K14: =INDEX(customer_churn_dataset!$V$2:$V$1501,MATCH($A15,customer_churn_dataset!$A$2:$A$1501,0)) -> Medium Risk
A15: =customer_churn_dataset!A84 -> CUST100395 | B15: =customer_churn_dataset!B84 -> Premium | C15: =customer_churn_dataset!C84 -> One year | D15: =INDEX(customer_churn_dataset!$E$2:$E$1501,MATCH($A16,customer_churn_dataset!$A$2:$A$1501,0)) -> 72 | E15: =INDEX(customer_churn_dataset!$I$2:$I$1501,MATCH($A16,customer_churn_dataset!$A$2:$A$1501,0)) -> 50.6 | F15: =INDEX(customer_churn_dataset!$L$2:$L$1501,MATCH($A16,customer_churn_dataset!$A$2:$A$1501,0)) -> 1 | G15: =IF(INDEX(customer_churn_dataset!$M$2:$M$1501,MATCH($A16,customer_churn_dataset!$A$2:$A$1501,0))=1,"Yes","No") -> Yes | H15: =INDEX(customer_churn_dataset!$N$2:$N$1501,MATCH($A16,customer_churn_dataset!$A$2:$A$1501,0)) -> 759.6 | I15: =INDEX(customer_churn_dataset!$O$2:$O$1501,MATCH($A16,customer_churn_dataset!$A$2:$A$1501,0)) -> 0 | J15: =INDEX(customer_churn_dataset!$T$2:$T$1501,MATCH($A16,customer_churn_dataset!$A$2:$A$1501,0)) -> 6 | K15: =INDEX(customer_churn_dataset!$V$2:$V$1501,MATCH($A16,customer_churn_dataset!$A$2:$A$1501,0)) -> High Risk
A16: =customer_churn_dataset!A95 -> CUST100100 | B16: =customer_churn_dataset!B95 -> Basic | C16: =customer_churn_dataset!C95 -> Month-to-month | D16: =INDEX(customer_churn_dataset!$E$2:$E$1501,MATCH($A17,customer_churn_dataset!$A$2:$A$1501,0)) -> 8 | E16: =INDEX(customer_churn_dataset!$I$2:$I$1501,MATCH($A17,customer_churn_dataset!$A$2:$A$1501,0)) -> 24.9 | F16: =INDEX(customer_churn_dataset!$L$2:$L$1501,MATCH($A17,customer_churn_dataset!$A$2:$A$1501,0)) -> 3 | G16: =IF(INDEX(customer_churn_dataset!$M$2:$M$1501,MATCH($A17,customer_churn_dataset!$A$2:$A$1501,0))=1,"Yes","No") -> No | H16: =INDEX(customer_churn_dataset!$N$2:$N$1501,MATCH($A17,customer_churn_dataset!$A$2:$A$1501,0)) -> 74.8 | I16: =INDEX(customer_churn_dataset!$O$2:$O$1501,MATCH($A17,customer_churn_dataset!$A$2:$A$1501,0)) -> 0 | J16: =INDEX(customer_churn_dataset!$T$2:$T$1501,MATCH($A17,customer_churn_dataset!$A$2:$A$1501,0)) -> 5 | K16: =INDEX(customer_churn_dataset!$V$2:$V$1501,MATCH($A17,customer_churn_dataset!$A$2:$A$1501,0)) -> Medium Risk
A17: =customer_churn_dataset!A100 -> CUST100254 | B17: =customer_churn_dataset!B100 -> Basic | C17: =customer_churn_dataset!C100 -> One year | D17: =INDEX(customer_churn_dataset!$E$2:$E$1501,MATCH($A18,customer_churn_dataset!$A$2:$A$1501,0)) -> 27 | E17: =INDEX(customer_churn_dataset!$I$2:$I$1501,MATCH($A18,customer_churn_dataset!$A$2:$A$1501,0)) -> 88.3 | F17: =INDEX(customer_churn_dataset!$L$2:$L$1501,MATCH($A18,customer_churn_dataset!$A$2:$A$1501,0)) -> 0 | G17: =IF(INDEX(customer_churn_dataset!$M$2:$M$1501,MATCH($A18,customer_churn_dataset!$A$2:$A$1501,0))=1,"Yes","No") -> No | H17: =INDEX(customer_churn_dataset!$N$2:$N$1501,MATCH($A18,customer_churn_dataset!$A$2:$A$1501,0)) -> 286.47 | I17: =INDEX(customer_churn_dataset!$O$2:$O$1501,MATCH($A18,customer_churn_dataset!$A$2:$A$1501,0)) -> 0 | J17: =INDEX(customer_churn_dataset!$T$2:$T$1501,MATCH($A18,customer_churn_dataset!$A$2:$A$1501,0)) -> 2 | K17: =INDEX(customer_churn_dataset!$V$2:$V$1501,MATCH($A18,customer_churn_dataset!$A$2:$A$1501,0)) -> Low Risk
A18: =customer_churn_dataset!A107 -> CUST100563 | B18: =customer_churn_dataset!B107 -> Basic | C18: =customer_churn_dataset!C107 -> Month-to-month | D18: =INDEX(customer_churn_dataset!$E$2:$E$1501,MATCH($A19,customer_churn_dataset!$A$2:$A$1501,0)) -> 1 | E18: =INDEX(customer_churn_dataset!$I$2:$I$1501,MATCH($A19,customer_churn_dataset!$A$2:$A$1501,0)) -> 100 | F18: =INDEX(customer_churn_dataset!$L$2:$L$1501,MATCH($A19,customer_churn_dataset!$A$2:$A$1501,0)) -> 1 | G18: =IF(INDEX(customer_churn_dataset!$M$2:$M$1501,MATCH($A19,customer_churn_dataset!$A$2:$A$1501,0))=1,"Yes","No") -> Yes | H18: =INDEX(customer_churn_dataset!$N$2:$N$1501,MATCH($A19,customer_churn_dataset!$A$2:$A$1501,0)) -> 20.17 | I18: =INDEX(customer_churn_dataset!$O$2:$O$1501,MATCH($A19,customer_churn_dataset!$A$2:$A$1501,0)) -> 0 | J18: =INDEX(customer_churn_dataset!$T$2:$T$1501,MATCH($A19,customer_churn_dataset!$A$2:$A$1501,0)) -> 6 | K18: =INDEX(customer_churn_dataset!$V$2:$V$1501,MATCH($A19,customer_churn_dataset!$A$2:$A$1501,0)) -> High Risk
A19: =customer_churn_dataset!A113 -> CUST101241 | B19: =customer_churn_dataset!B113 -> Standard | C19: =customer_churn_dataset!C113 -> Month-to-month | D19: =INDEX(customer_churn_dataset!$E$2:$E$1501,MATCH($A20,customer_churn_dataset!$A$2:$A$1501,0)) -> 3 | E19: =INDEX(customer_churn_dataset!$I$2:$I$1501,MATCH($A20,customer_churn_dataset!$A$2:$A$1501,0)) -> 57 | F19: =INDEX(customer_churn_dataset!$L$2:$L$1501,MATCH($A20,customer_churn_dataset!$A$2:$A$1501,0)) -> 1 | G19: =IF(INDEX(customer_churn_dataset!$M$2:$M$1501,MATCH($A20,customer_churn_dataset!$A$2:$A$1501,0))=1,"Yes","No") -> No | H19: =INDEX(customer_churn_dataset!$N$2:$N$1501,MATCH($A20,customer_churn_dataset!$A$2:$A$1501,0)) -> 56.25 | I19: =INDEX(customer_churn_dataset!$O$2:$O$1501,MATCH($A20,customer_churn_dataset!$A$2:$A$1501,0)) -> 0 | J19: =INDEX(customer_churn_dataset!$T$2:$T$1501,MATCH($A20,customer_churn_dataset!$A$2:$A$1501,0)) -> 2 | K19: =INDEX(customer_churn_dataset!$V$2:$V$1501,MATCH($A20,customer_churn_dataset!$A$2:$A$1501,0)) -> Low Risk
A20: =customer_churn_dataset!A122 -> CUST101303 | B20: =customer_churn_dataset!B122 -> Standard | C20: =customer_churn_dataset!C122 -> One year | D20: =INDEX(customer_churn_dataset!$E$2:$E$1501,MATCH($A21,customer_churn_dataset!$A$2:$A$1501,0)) -> 13 | E20: =INDEX(customer_churn_dataset!$I$2:$I$1501,MATCH($A21,customer_churn_dataset!$A$2:$A$1501,0)) -> 27.7 | F20: =INDEX(customer_churn_dataset!$L$2:$L$1501,MATCH($A21,customer_churn_dataset!$A$2:$A$1501,0)) -> 4 | G20: =IF(INDEX(customer_churn_dataset!$M$2:$M$1501,MATCH($A21,customer_churn_dataset!$A$2:$A$1501,0))=1,"Yes","No") -> No | H20: =INDEX(customer_churn_dataset!$N$2:$N$1501,MATCH($A21,customer_churn_dataset!$A$2:$A$1501,0)) -> 140.27 | I20: =INDEX(customer_churn_dataset!$O$2:$O$1501,MATCH($A21,customer_churn_dataset!$A$2:$A$1501,0)) -> 0 | J20: =INDEX(customer_churn_dataset!$T$2:$T$1501,MATCH($A21,customer_churn_dataset!$A$2:$A$1501,0)) -> 5 | K20: =INDEX(customer_churn_dataset!$V$2:$V$1501,MATCH($A21,customer_churn_dataset!$A$2:$A$1501,0)) -> Medium Risk
A21: =customer_churn_dataset!A140 -> CUST100830 | B21: =customer_churn_dataset!B140 -> Basic | C21: =customer_churn_dataset!C140 -> Month-to-month | D21: =INDEX(customer_churn_dataset!$E$2:$E$1501,MATCH($A22,customer_churn_dataset!$A$2:$A$1501,0)) -> 12 | E21: =INDEX(customer_churn_dataset!$I$2:$I$1501,MATCH($A22,customer_churn_dataset!$A$2:$A$1501,0)) -> 20.5 | F21: =INDEX(customer_churn_dataset!$L$2:$L$1501,MATCH($A22,customer_churn_dataset!$A$2:$A$1501,0)) -> 2 | G21: =IF(INDEX(customer_churn_dataset!$M$2:$M$1501,MATCH($A22,customer_churn_dataset!$A$2:$A$1501,0))=1,"Yes","No") -> Yes | H21: =INDEX(customer_churn_dataset!$N$2:$N$1501,MATCH($A22,customer_churn_dataset!$A$2:$A$1501,0)) -> 117.6 | I21: =INDEX(customer_churn_dataset!$O$2:$O$1501,MATCH($A22,customer_churn_dataset!$A$2:$A$1501,0)) -> 0 | J21: =INDEX(customer_churn_dataset!$T$2:$T$1501,MATCH($A22,customer_churn_dataset!$A$2:$A$1501,0)) -> 7 | K21: =INDEX(customer_churn_dataset!$V$2:$V$1501,MATCH($A22,customer_churn_dataset!$A$2:$A$1501,0)) -> High Risk
A22: =customer_churn_dataset!A146 -> CUST100855 | B22: =customer_churn_dataset!B146 -> Basic | C22: =customer_churn_dataset!C146 -> One year | D22: =INDEX(customer_churn_dataset!$E$2:$E$1501,MATCH($A23,customer_churn_dataset!$A$2:$A$1501,0)) -> 18 | E22: =INDEX(customer_churn_dataset!$I$2:$I$1501,MATCH($A23,customer_churn_dataset!$A$2:$A$1501,0)) -> 26.7 | F22: =INDEX(customer_churn_dataset!$L$2:$L$1501,MATCH($A23,customer_churn_dataset!$A$2:$A$1501,0)) -> 3 | G22: =IF(INDEX(customer_churn_dataset!$M$2:$M$1501,MATCH($A23,customer_churn_dataset!$A$2:$A$1501,0))=1,"Yes","No") -> No | H22: =INDEX(customer_churn_dataset!$N$2:$N$1501,MATCH($A23,customer_churn_dataset!$A$2:$A$1501,0)) -> 155.88 | I22: =INDEX(customer_churn_dataset!$O$2:$O$1501,MATCH($A23,customer_churn_dataset!$A$2:$A$1501,0)) -> 0 | J22: =INDEX(customer_churn_dataset!$T$2:$T$1501,MATCH($A23,customer_churn_dataset!$A$2:$A$1501,0)) -> 4 | K22: =INDEX(customer_churn_dataset!$V$2:$V$1501,MATCH($A23,customer_churn_dataset!$A$2:$A$1501,0)) -> Medium Risk
A23: =customer_churn_dataset!A150 -> CUST100125 | B23: =customer_churn_dataset!B150 -> Basic | C23: =customer_churn_dataset!C150 -> One year | D23: =INDEX(customer_churn_dataset!$E$2:$E$1501,MATCH($A24,customer_churn_dataset!$A$2:$A$1501,0)) -> 14 | E23: =INDEX(customer_churn_dataset!$I$2:$I$1501,MATCH($A24,customer_churn_dataset!$A$2:$A$1501,0)) -> 32.7 | F23: =INDEX(customer_churn_dataset!$L$2:$L$1501,MATCH($A24,customer_churn_dataset!$A$2:$A$1501,0)) -> 1 | G23: =IF(INDEX(customer_churn_dataset!$M$2:$M$1501,MATCH($A24,customer_churn_dataset!$A$2:$A$1501,0))=1,"Yes","No") -> Yes | H23: =INDEX(customer_churn_dataset!$N$2:$N$1501,MATCH($A24,customer_churn_dataset!$A$2:$A$1501,0)) -> 588.14 | I23: =INDEX(customer_churn_dataset!$O$2:$O$1501,MATCH($A24,customer_churn_dataset!$A$2:$A$1501,0)) -> 0 | J23: =INDEX(customer_churn_dataset!$T$2:$T$1501,MATCH($A24,customer_churn_dataset!$A$2:$A$1501,0)) -> 5 | K23: =INDEX(customer_churn_dataset!$V$2:$V$1501,MATCH($A24,customer_churn_dataset!$A$2:$A$1501,0)) -> Medium Risk
A24: =customer_churn_dataset!A154 -> CUST101018 | B24: =customer_churn_dataset!B154 -> Premium | C24: =customer_churn_dataset!C154 -> Two year | D24: =INDEX(customer_churn_dataset!$E$2:$E$1501,MATCH($A25,customer_churn_dataset!$A$2:$A$1501,0)) -> 40 | E24: =INDEX(customer_churn_dataset!$I$2:$I$1501,MATCH($A25,customer_churn_dataset!$A$2:$A$1501,0)) -> 67.3 | F24: =INDEX(customer_churn_dataset!$L$2:$L$1501,MATCH($A25,customer_churn_dataset!$A$2:$A$1501,0)) -> 1 | G24: =IF(INDEX(customer_churn_dataset!$M$2:$M$1501,MATCH($A25,customer_churn_dataset!$A$2:$A$1501,0))=1,"Yes","No") -> No | H24: =INDEX(customer_churn_dataset!$N$2:$N$1501,MATCH($A25,customer_churn_dataset!$A$2:$A$1501,0)) -> 772 | I24: =INDEX(customer_churn_dataset!$O$2:$O$1501,MATCH($A25,customer_churn_dataset!$A$2:$A$1501,0)) -> 0 | J24: =INDEX(customer_churn_dataset!$T$2:$T$1501,MATCH($A25,customer_churn_dataset!$A$2:$A$1501,0)) -> 2 | K24: =INDEX(customer_churn_dataset!$V$2:$V$1501,MATCH($A25,customer_churn_dataset!$A$2:$A$1501,0)) -> Low Risk
A25: =customer_churn_dataset!A169 -> CUST101331 | B25: =customer_churn_dataset!B169 -> Standard | C25: =customer_churn_dataset!C169 -> Month-to-month | D25: =INDEX(customer_churn_dataset!$E$2:$E$1501,MATCH($A26,customer_churn_dataset!$A$2:$A$1501,0)) -> 46 | E25: =INDEX(customer_churn_dataset!$I$2:$I$1501,MATCH($A26,customer_churn_dataset!$A$2:$A$1501,0)) -> 62.9 | F25: =INDEX(customer_churn_dataset!$L$2:$L$1501,MATCH($A26,customer_churn_dataset!$A$2:$A$1501,0)) -> 1 | G25: =IF(INDEX(customer_churn_dataset!$M$2:$M$1501,MATCH($A26,customer_churn_dataset!$A$2:$A$1501,0))=1,"Yes","No") -> No | H25: =INDEX(customer_churn_dataset!$N$2:$N$1501,MATCH($A26,customer_churn_dataset!$A$2:$A$1501,0)) -> 1836.78 | I25: =INDEX(customer_churn_dataset!$O$2:$O$1501,MATCH($A26,customer_churn_dataset!$A$2:$A$1501,0)) -> 0 | J25: =INDEX(customer_churn_dataset!$T$2:$T$1501,MATCH($A26,customer_churn_dataset!$A$2:$A$1501,0)) -> 2 | K25: =INDEX(customer_churn_dataset!$V$2:$V$1501,MATCH($A26,customer_churn_dataset!$A$2:$A$1501,0)) -> Low Risk
A26: =customer_churn_dataset!A184 -> CUST101429 | B26: =customer_churn_dataset!B184 -> Premium | C26: =customer_churn_dataset!C184 -> Month-to-month | D26: =INDEX(customer_churn_dataset!$E$2:$E$1501,MATCH($A27,customer_churn_dataset!$A$2:$A$1501,0)) -> 11 | E26: =INDEX(customer_churn_dataset!$I$2:$I$1501,MATCH($A27,customer_churn_dataset!$A$2:$A$1501,0)) -> 43.1 | F26: =INDEX(customer_churn_dataset!$L$2:$L$1501,MATCH($A27,customer_churn_dataset!$A$2:$A$1501,0)) -> 4 | G26: =IF(INDEX(customer_churn_dataset!$M$2:$M$1501,MATCH($A27,customer_churn_dataset!$A$2:$A$1501,0))=1,"Yes","No") -> No | H26: =INDEX(customer_churn_dataset!$N$2:$N$1501,MATCH($A27,customer_churn_dataset!$A$2:$A$1501,0)) -> 102.74 | I26: =INDEX(customer_churn_dataset!$O$2:$O$1501,MATCH($A27,customer_churn_dataset!$A$2:$A$1501,0)) -> 1 | J26: =INDEX(customer_churn_dataset!$T$2:$T$1501,MATCH($A27,customer_churn_dataset!$A$2:$A$1501,0)) -> 5 | K26: =INDEX(customer_churn_dataset!$V$2:$V$1501,MATCH($A27,customer_churn_dataset!$A$2:$A$1501,0)) -> Medium Risk
A27: =customer_churn_dataset!A186 -> CUST100084 | B27: =customer_churn_dataset!B186 -> Basic | C27: =customer_churn_dataset!C186 -> Month-to-month | D27: =INDEX(customer_churn_dataset!$E$2:$E$1501,MATCH($A28,customer_churn_dataset!$A$2:$A$1501,0)) -> 10 | E27: =INDEX(customer_churn_dataset!$I$2:$I$1501,MATCH($A28,customer_churn_dataset!$A$2:$A$1501,0)) -> 42.2 | F27: =INDEX(customer_churn_dataset!$L$2:$L$1501,MATCH($A28,customer_churn_dataset!$A$2:$A$1501,0)) -> 0 | G27: =IF(INDEX(customer_churn_dataset!$M$2:$M$1501,MATCH($A28,customer_churn_dataset!$A$2:$A$1501,0))=1,"Yes","No") -> No | H27: =INDEX(customer_churn_dataset!$N$2:$N$1501,MATCH($A28,customer_churn_dataset!$A$2:$A$1501,0)) -> 215 | I27: =INDEX(customer_churn_dataset!$O$2:$O$1501,MATCH($A28,customer_churn_dataset!$A$2:$A$1501,0)) -> 0 | J27: =INDEX(customer_churn_dataset!$T$2:$T$1501,MATCH($A28,customer_churn_dataset!$A$2:$A$1501,0)) -> 4 | K27: =INDEX(customer_churn_dataset!$V$2:$V$1501,MATCH($A28,customer_churn_dataset!$A$2:$A$1501,0)) -> Medium Risk
A28: =customer_churn_dataset!A196 -> CUST101091 | B28: =customer_churn_dataset!B196 -> Standard | C28: =customer_churn_dataset!C196 -> Month-to-month | D28: =INDEX(customer_churn_dataset!$E$2:$E$1501,MATCH($A29,customer_churn_dataset!$A$2:$A$1501,0)) -> 27 | E28: =INDEX(customer_churn_dataset!$I$2:$I$1501,MATCH($A29,customer_churn_dataset!$A$2:$A$1501,0)) -> 67.8 | F28: =INDEX(customer_churn_dataset!$L$2:$L$1501,MATCH($A29,customer_churn_dataset!$A$2:$A$1501,0)) -> 3 | G28: =IF(INDEX(customer_churn_dataset!$M$2:$M$1501,MATCH($A29,customer_churn_dataset!$A$2:$A$1501,0))=1,"Yes","No") -> No | H28: =INDEX(customer_churn_dataset!$N$2:$N$1501,MATCH($A29,customer_churn_dataset!$A$2:$A$1501,0)) -> 246.51 | I28: =INDEX(customer_churn_dataset!$O$2:$O$1501,MATCH($A29,customer_churn_dataset!$A$2:$A$1501,0)) -> 0 | J28: =INDEX(customer_churn_dataset!$T$2:$T$1501,MATCH($A29,customer_churn_dataset!$A$2:$A$1501,0)) -> 2 | K28: =INDEX(customer_churn_dataset!$V$2:$V$1501,MATCH($A29,customer_churn_dataset!$A$2:$A$1501,0)) -> Low Risk
A29: =customer_churn_dataset!A207 -> CUST101465 | B29: =customer_churn_dataset!B207 -> Basic | C29: =customer_churn_dataset!C207 -> One year | D29: =INDEX(customer_churn_dataset!$E$2:$E$1501,MATCH($A30,customer_churn_dataset!$A$2:$A$1501,0)) -> 5 | E29: =INDEX(customer_churn_dataset!$I$2:$I$1501,MATCH($A30,customer_churn_dataset!$A$2:$A$1501,0)) -> 56.8 | F29: =INDEX(customer_churn_dataset!$L$2:$L$1501,MATCH($A30,customer_churn_dataset!$A$2:$A$1501,0)) -> 0 | G29: =IF(INDEX(customer_churn_dataset!$M$2:$M$1501,MATCH($A30,customer_churn_dataset!$A$2:$A$1501,0))=1,"Yes","No") -> No | H29: =INDEX(customer_churn_dataset!$N$2:$N$1501,MATCH($A30,customer_churn_dataset!$A$2:$A$1501,0)) -> 47.5 | I29: =INDEX(customer_churn_dataset!$O$2:$O$1501,MATCH($A30,customer_churn_dataset!$A$2:$A$1501,0)) -> 0 | J29: =INDEX(customer_churn_dataset!$T$2:$T$1501,MATCH($A30,customer_churn_dataset!$A$2:$A$1501,0)) -> 3 | K29: =INDEX(customer_churn_dataset!$V$2:$V$1501,MATCH($A30,customer_churn_dataset!$A$2:$A$1501,0)) -> Medium Risk
A30: =customer_churn_dataset!A209 -> CUST101332 | B30: =customer_churn_dataset!B209 -> Basic | C30: =customer_churn_dataset!C209 -> Month-to-month | D30: =INDEX(customer_churn_dataset!$E$2:$E$1501,MATCH($A31,customer_churn_dataset!$A$2:$A$1501,0)) -> 9 | E30: =INDEX(customer_churn_dataset!$I$2:$I$1501,MATCH($A31,customer_churn_dataset!$A$2:$A$1501,0)) -> 72.9 | F30: =INDEX(customer_churn_dataset!$L$2:$L$1501,MATCH($A31,customer_churn_dataset!$A$2:$A$1501,0)) -> 0 | G30: =IF(INDEX(customer_churn_dataset!$M$2:$M$1501,MATCH($A31,customer_churn_dataset!$A$2:$A$1501,0))=1,"Yes","No") -> No | H30: =INDEX(customer_churn_dataset!$N$2:$N$1501,MATCH($A31,customer_churn_dataset!$A$2:$A$1501,0)) -> 189.9 | I30: =INDEX(customer_churn_dataset!$O$2:$O$1501,MATCH($A31,customer_churn_dataset!$A$2:$A$1501,0)) -> 0 | J30: =INDEX(customer_churn_dataset!$T$2:$T$1501,MATCH($A31,customer_churn_dataset!$A$2:$A$1501,0)) -> 2 | K30: =INDEX(customer_churn_dataset!$V$2:$V$1501,MATCH($A31,customer_churn_dataset!$A$2:$A$1501,0)) -> Low Risk
A31: =customer_churn_dataset!A226 -> CUST100550 | B31: =customer_churn_dataset!B226 -> Standard | C31: =customer_churn_dataset!C226 -> One year | D31: =INDEX(customer_churn_dataset!$E$2:$E$1501,MATCH($A32,customer_churn_dataset!$A$2:$A$1501,0)) -> 8 | E31: =INDEX(customer_churn_dataset!$I$2:$I$1501,MATCH($A32,customer_churn_dataset!$A$2:$A$1501,0)) -> 46.3 | F31: =INDEX(customer_churn_dataset!$L$2:$L$1501,MATCH($A32,customer_churn_dataset!$A$2:$A$1501,0)) -> 0 | G31: =IF(INDEX(customer_churn_dataset!$M$2:$M$1501,MATCH($A32,customer_churn_dataset!$A$2:$A$1501,0))=1,"Yes","No") -> No | H31: =INDEX(customer_churn_dataset!$N$2:$N$1501,MATCH($A32,customer_churn_dataset!$A$2:$A$1501,0)) -> 90.64 | I31: =INDEX(customer_churn_dataset!$O$2:$O$1501,MATCH($A32,customer_churn_dataset!$A$2:$A$1501,0)) -> 0 | J31: =INDEX(customer_churn_dataset!$T$2:$T$1501,MATCH($A32,customer_churn_dataset!$A$2:$A$1501,0)) -> 4 | K31: =INDEX(customer_churn_dataset!$V$2:$V$1501,MATCH($A32,customer_churn_dataset!$A$2:$A$1501,0)) -> Medium Risk
A32: =customer_churn_dataset!A229 -> CUST100629 | B32: =customer_churn_dataset!B229 -> Basic | C32: =customer_churn_dataset!C229 -> Month-to-month | D32: =INDEX(customer_churn_dataset!$E$2:$E$1501,MATCH($A33,customer_churn_dataset!$A$2:$A$1501,0)) -> 19 | E32: =INDEX(customer_churn_dataset!$I$2:$I$1501,MATCH($A33,customer_churn_dataset!$A$2:$A$1501,0)) -> 75.7 | F32: =INDEX(customer_churn_dataset!$L$2:$L$1501,MATCH($A33,customer_churn_dataset!$A$2:$A$1501,0)) -> 0 | G32: =IF(INDEX(customer_churn_dataset!$M$2:$M$1501,MATCH($A33,customer_churn_dataset!$A$2:$A$1501,0))=1,"Yes","No") -> No | H32: =INDEX(customer_churn_dataset!$N$2:$N$1501,MATCH($A33,customer_churn_dataset!$A$2:$A$1501,0)) -> 375.06 | I32: =INDEX(customer_churn_dataset!$O$2:$O$1501,MATCH($A33,customer_churn_dataset!$A$2:$A$1501,0)) -> 0 | J32: =INDEX(customer_churn_dataset!$T$2:$T$1501,MATCH($A33,customer_churn_dataset!$A$2:$A$1501,0)) -> 2 | K32: =INDEX(customer_churn_dataset!$V$2:$V$1501,MATCH($A33,customer_churn_dataset!$A$2:$A$1501,0)) -> Low Risk
A33: =customer_churn_dataset!A241 -> CUST100276 | B33: =customer_churn_dataset!B241 -> Standard | C33: =customer_churn_dataset!C241 -> Month-to-month | D33: =INDEX(customer_churn_dataset!$E$2:$E$1501,MATCH($A34,customer_churn_dataset!$A$2:$A$1501,0)) -> 25 | E33: =INDEX(customer_churn_dataset!$I$2:$I$1501,MATCH($A34,customer_churn_dataset!$A$2:$A$1501,0)) -> 35 | F33: =INDEX(customer_churn_dataset!$L$2:$L$1501,MATCH($A34,customer_churn_dataset!$A$2:$A$1501,0)) -> 1 | G33: =IF(INDEX(customer_churn_dataset!$M$2:$M$1501,MATCH($A34,customer_churn_dataset!$A$2:$A$1501,0))=1,"Yes","No") -> Yes | H33: =INDEX(customer_churn_dataset!$N$2:$N$1501,MATCH($A34,customer_churn_dataset!$A$2:$A$1501,0)) -> 510 | I33: =INDEX(customer_churn_dataset!$O$2:$O$1501,MATCH($A34,customer_churn_dataset!$A$2:$A$1501,0)) -> 0 | J33: =INDEX(customer_churn_dataset!$T$2:$T$1501,MATCH($A34,customer_churn_dataset!$A$2:$A$1501,0)) -> 7 | K33: =INDEX(customer_churn_dataset!$V$2:$V$1501,MATCH($A34,customer_churn_dataset!$A$2:$A$1501,0)) -> High Risk
A34: =customer_churn_dataset!A263 -> CUST100544 | B34: =customer_churn_dataset!B263 -> Standard | C34: =customer_churn_dataset!C263 -> Month-to-month | D34: =INDEX(customer_churn_dataset!$E$2:$E$1501,MATCH($A35,customer_churn_dataset!$A$2:$A$1501,0)) -> 37 | E34: =INDEX(customer_churn_dataset!$I$2:$I$1501,MATCH($A35,customer_churn_dataset!$A$2:$A$1501,0)) -> 34.6 | F34: =INDEX(customer_churn_dataset!$L$2:$L$1501,MATCH($A35,customer_churn_dataset!$A$2:$A$1501,0)) -> 1 | G34: =IF(INDEX(customer_churn_dataset!$M$2:$M$1501,MATCH($A35,customer_churn_dataset!$A$2:$A$1501,0))=1,"Yes","No") -> No | H34: =INDEX(customer_churn_dataset!$N$2:$N$1501,MATCH($A35,customer_churn_dataset!$A$2:$A$1501,0)) -> 1594.7 | I34: =INDEX(customer_churn_dataset!$O$2:$O$1501,MATCH($A35,customer_churn_dataset!$A$2:$A$1501,0)) -> 0 | J34: =INDEX(customer_churn_dataset!$T$2:$T$1501,MATCH($A35,customer_churn_dataset!$A$2:$A$1501,0)) -> 4 | K34: =INDEX(customer_churn_dataset!$V$2:$V$1501,MATCH($A35,customer_churn_dataset!$A$2:$A$1501,0)) -> Medium Risk
A35: =customer_churn_dataset!A265 -> CUST101145 | B35: =customer_churn_dataset!B265 -> Premium | C35: =customer_churn_dataset!C265 -> Month-to-month | D35: =INDEX(customer_churn_dataset!$E$2:$E$1501,MATCH($A36,customer_churn_dataset!$A$2:$A$1501,0)) -> 24 | E35: =INDEX(customer_churn_dataset!$I$2:$I$1501,MATCH($A36,customer_churn_dataset!$A$2:$A$1501,0)) -> 13.5 | F35: =INDEX(customer_churn_dataset!$L$2:$L$1501,MATCH($A36,customer_churn_dataset!$A$2:$A$1501,0)) -> 6 | G35: =IF(INDEX(customer_churn_dataset!$M$2:$M$1501,MATCH($A36,customer_churn_dataset!$A$2:$A$1501,0))=1,"Yes","No") -> Yes | H35: =INDEX(customer_churn_dataset!$N$2:$N$1501,MATCH($A36,customer_churn_dataset!$A$2:$A$1501,0)) -> 960 | I35: =INDEX(customer_churn_dataset!$O$2:$O$1501,MATCH($A36,customer_churn_dataset!$A$2:$A$1501,0)) -> 0 | J35: =INDEX(customer_churn_dataset!$T$2:$T$1501,MATCH($A36,customer_churn_dataset!$A$2:$A$1501,0)) -> 8 | K35: =INDEX(customer_churn_dataset!$V$2:$V$1501,MATCH($A36,customer_churn_dataset!$A$2:$A$1501,0)) -> High Risk
A36: =customer_churn_dataset!A270 -> CUST100154 | B36: =customer_churn_dataset!B270 -> Premium | C36: =customer_churn_dataset!C270 -> Month-to-month | D36: =INDEX(customer_churn_dataset!$E$2:$E$1501,MATCH($A37,customer_churn_dataset!$A$2:$A$1501,0)) -> 21 | E36: =INDEX(customer_churn_dataset!$I$2:$I$1501,MATCH($A37,customer_churn_dataset!$A$2:$A$1501,0)) -> 38.1 | F36: =INDEX(customer_churn_dataset!$L$2:$L$1501,MATCH($A37,customer_churn_dataset!$A$2:$A$1501,0)) -> 0 | G36: =IF(INDEX(customer_churn_dataset!$M$2:$M$1501,MATCH($A37,customer_churn_dataset!$A$2:$A$1501,0))=1,"Yes","No") -> No | H36: =INDEX(customer_churn_dataset!$N$2:$N$1501,MATCH($A37,customer_churn_dataset!$A$2:$A$1501,0)) -> 176.4 | I36: =INDEX(customer_churn_dataset!$O$2:$O$1501,MATCH($A37,customer_churn_dataset!$A$2:$A$1501,0)) -> 1 | J36: =INDEX(customer_churn_dataset!$T$2:$T$1501,MATCH($A37,customer_churn_dataset!$A$2:$A$1501,0)) -> 4 | K36: =INDEX(customer_churn_dataset!$V$2:$V$1501,MATCH($A37,customer_churn_dataset!$A$2:$A$1501,0)) -> Medium Risk
A37: =customer_churn_dataset!A281 -> CUST101390 | B37: =customer_churn_dataset!B281 -> Basic | C37: =customer_churn_dataset!C281 -> Month-to-month | D37: =INDEX(customer_churn_dataset!$E$2:$E$1501,MATCH($A38,customer_churn_dataset!$A$2:$A$1501,0)) -> 13 | E37: =INDEX(customer_churn_dataset!$I$2:$I$1501,MATCH($A38,customer_churn_dataset!$A$2:$A$1501,0)) -> 43.1 | F37: =INDEX(customer_churn_dataset!$L$2:$L$1501,MATCH($A38,customer_churn_dataset!$A$2:$A$1501,0)) -> 0 | G37: =IF(INDEX(customer_churn_dataset!$M$2:$M$1501,MATCH($A38,customer_churn_dataset!$A$2:$A$1501,0))=1,"Yes","No") -> No | H37: =INDEX(customer_churn_dataset!$N$2:$N$1501,MATCH($A38,customer_churn_dataset!$A$2:$A$1501,0)) -> 149.63 | I37: =INDEX(customer_churn_dataset!$O$2:$O$1501,MATCH($A38,customer_churn_dataset!$A$2:$A$1501,0)) -> 0 | J37: =INDEX(customer_churn_dataset!$T$2:$T$1501,MATCH($A38,customer_churn_dataset!$A$2:$A$1501,0)) -> 1 | K37: =INDEX(customer_churn_dataset!$V$2:$V$1501,MATCH($A38,customer_churn_dataset!$A$2:$A$1501,0)) -> Low Risk
A38: =customer_churn_dataset!A299 -> CUST101491 | B38: =customer_churn_dataset!B299 -> Basic | C38: =customer_churn_dataset!C299 -> Two year | D38: =INDEX(customer_churn_dataset!$E$2:$E$1501,MATCH($A39,customer_churn_dataset!$A$2:$A$1501,0)) -> 29 | E38: =INDEX(customer_churn_dataset!$I$2:$I$1501,MATCH($A39,customer_churn_dataset!$A$2:$A$1501,0)) -> 49.7 | F38: =INDEX(customer_churn_dataset!$L$2:$L$1501,MATCH($A39,customer_churn_dataset!$A$2:$A$1501,0)) -> 2 | G38: =IF(INDEX(customer_churn_dataset!$M$2:$M$1501,MATCH($A39,customer_churn_dataset!$A$2:$A$1501,0))=1,"Yes","No") -> No | H38: =INDEX(customer_churn_dataset!$N$2:$N$1501,MATCH($A39,customer_churn_dataset!$A$2:$A$1501,0)) -> 263.03 | I38: =INDEX(customer_churn_dataset!$O$2:$O$1501,MATCH($A39,customer_churn_dataset!$A$2:$A$1501,0)) -> 0 | J38: =INDEX(customer_churn_dataset!$T$2:$T$1501,MATCH($A39,customer_churn_dataset!$A$2:$A$1501,0)) -> 3 | K38: =INDEX(customer_churn_dataset!$V$2:$V$1501,MATCH($A39,customer_churn_dataset!$A$2:$A$1501,0)) -> Medium Risk
A39: =customer_churn_dataset!A303 -> CUST101290 | B39: =customer_churn_dataset!B303 -> Basic | C39: =customer_churn_dataset!C303 -> One year | D39: =INDEX(customer_churn_dataset!$E$2:$E$1501,MATCH($A40,customer_churn_dataset!$A$2:$A$1501,0)) -> 18 | E39: =INDEX(customer_churn_dataset!$I$2:$I$1501,MATCH($A40,customer_churn_dataset!$A$2:$A$1501,0)) -> 50.1 | F39: =INDEX(customer_churn_dataset!$L$2:$L$1501,MATCH($A40,customer_churn_dataset!$A$2:$A$1501,0)) -> 1 | G39: =IF(INDEX(customer_churn_dataset!$M$2:$M$1501,MATCH($A40,customer_churn_dataset!$A$2:$A$1501,0))=1,"Yes","No") -> No | H39: =INDEX(customer_churn_dataset!$N$2:$N$1501,MATCH($A40,customer_churn_dataset!$A$2:$A$1501,0)) -> 162.9 | I39: =INDEX(customer_churn_dataset!$O$2:$O$1501,MATCH($A40,customer_churn_dataset!$A$2:$A$1501,0)) -> 1 | J39: =INDEX(customer_churn_dataset!$T$2:$T$1501,MATCH($A40,customer_churn_dataset!$A$2:$A$1501,0)) -> 3 | K39: =INDEX(customer_churn_dataset!$V$2:$V$1501,MATCH($A40,customer_churn_dataset!$A$2:$A$1501,0)) -> Medium Risk
A40: =customer_churn_dataset!A312 -> CUST100166 | B40: =customer_churn_dataset!B312 -> Basic | C40: =customer_churn_dataset!C312 -> Month-to-month | D40: =INDEX(customer_churn_dataset!$E$2:$E$1501,MATCH($A41,customer_churn_dataset!$A$2:$A$1501,0)) -> 38 | E40: =INDEX(customer_churn_dataset!$I$2:$I$1501,MATCH($A41,customer_churn_dataset!$A$2:$A$1501,0)) -> 54.2 | F40: =INDEX(customer_churn_dataset!$L$2:$L$1501,MATCH($A41,customer_churn_dataset!$A$2:$A$1501,0)) -> 0 | G40: =IF(INDEX(customer_churn_dataset!$M$2:$M$1501,MATCH($A41,customer_churn_dataset!$A$2:$A$1501,0))=1,"Yes","No") -> No | H40: =INDEX(customer_churn_dataset!$N$2:$N$1501,MATCH($A41,customer_churn_dataset!$A$2:$A$1501,0)) -> 1460.34 | I40: =INDEX(customer_churn_dataset!$O$2:$O$1501,MATCH($A41,customer_churn_dataset!$A$2:$A$1501,0)) -> 0 | J40: =INDEX(customer_churn_dataset!$T$2:$T$1501,MATCH($A41,customer_churn_dataset!$A$2:$A$1501,0)) -> 2 | K40: =INDEX(customer_churn_dataset!$V$2:$V$1501,MATCH($A41,customer_churn_dataset!$A$2:$A$1501,0)) -> Low Risk
A41: =customer_churn_dataset!A337 -> CUST101083 | B41: =customer_churn_dataset!B337 -> Premium | C41: =customer_churn_dataset!C337 -> One year | D41: =INDEX(customer_churn_dataset!$E$2:$E$1501,MATCH($A42,customer_churn_dataset!$A$2:$A$1501,0)) -> 29 | E41: =INDEX(customer_churn_dataset!$I$2:$I$1501,MATCH($A42,customer_churn_dataset!$A$2:$A$1501,0)) -> 81.2 | F41: =INDEX(customer_churn_dataset!$L$2:$L$1501,MATCH($A42,customer_churn_dataset!$A$2:$A$1501,0)) -> 0 | G41: =IF(INDEX(customer_churn_dataset!$M$2:$M$1501,MATCH($A42,customer_churn_dataset!$A$2:$A$1501,0))=1,"Yes","No") -> No | H41: =INDEX(customer_churn_dataset!$N$2:$N$1501,MATCH($A42,customer_churn_dataset!$A$2:$A$1501,0)) -> 568.4 | I41: =INDEX(customer_churn_dataset!$O$2:$O$1501,MATCH($A42,customer_churn_dataset!$A$2:$A$1501,0)) -> 0 | J41: =INDEX(customer_churn_dataset!$T$2:$T$1501,MATCH($A42,customer_churn_dataset!$A$2:$A$1501,0)) -> 2 | K41: =INDEX(customer_churn_dataset!$V$2:$V$1501,MATCH($A42,customer_churn_dataset!$A$2:$A$1501,0)) -> Low Risk
A42: =customer_churn_dataset!A356 -> CUST100781 | B42: =customer_churn_dataset!B356 -> Standard | C42: =customer_churn_dataset!C356 -> Month-to-month | D42: =INDEX(customer_churn_dataset!$E$2:$E$1501,MATCH($A43,customer_churn_dataset!$A$2:$A$1501,0)) -> 20 | E42: =INDEX(customer_churn_dataset!$I$2:$I$1501,MATCH($A43,customer_churn_dataset!$A$2:$A$1501,0)) -> 37.6 | F42: =INDEX(customer_churn_dataset!$L$2:$L$1501,MATCH($A43,customer_churn_dataset!$A$2:$A$1501,0)) -> 1 | G42: =IF(INDEX(customer_churn_dataset!$M$2:$M$1501,MATCH($A43,customer_churn_dataset!$A$2:$A$1501,0))=1,"Yes","No") -> Yes | H42: =INDEX(customer_churn_dataset!$N$2:$N$1501,MATCH($A43,customer_churn_dataset!$A$2:$A$1501,0)) -> 169.8 | I42: =INDEX(customer_churn_dataset!$O$2:$O$1501,MATCH($A43,customer_churn_dataset!$A$2:$A$1501,0)) -> 0 | J42: =INDEX(customer_churn_dataset!$T$2:$T$1501,MATCH($A43,customer_churn_dataset!$A$2:$A$1501,0)) -> 7 | K42: =INDEX(customer_churn_dataset!$V$2:$V$1501,MATCH($A43,customer_churn_dataset!$A$2:$A$1501,0)) -> High Risk
A43: =customer_churn_dataset!A362 -> CUST100622 | B43: =customer_churn_dataset!B362 -> Basic | C43: =customer_churn_dataset!C362 -> Month-to-month | D43: =INDEX(customer_churn_dataset!$E$2:$E$1501,MATCH($A44,customer_churn_dataset!$A$2:$A$1501,0)) -> 25 | E43: =INDEX(customer_churn_dataset!$I$2:$I$1501,MATCH($A44,customer_churn_dataset!$A$2:$A$1501,0)) -> 45.5 | F43: =INDEX(customer_churn_dataset!$L$2:$L$1501,MATCH($A44,customer_churn_dataset!$A$2:$A$1501,0)) -> 1 | G43: =IF(INDEX(customer_churn_dataset!$M$2:$M$1501,MATCH($A44,customer_churn_dataset!$A$2:$A$1501,0))=1,"Yes","No") -> No | H43: =INDEX(customer_churn_dataset!$N$2:$N$1501,MATCH($A44,customer_churn_dataset!$A$2:$A$1501,0)) -> 285.25 | I43: =INDEX(customer_churn_dataset!$O$2:$O$1501,MATCH($A44,customer_churn_dataset!$A$2:$A$1501,0)) -> 0 | J43: =INDEX(customer_churn_dataset!$T$2:$T$1501,MATCH($A44,customer_churn_dataset!$A$2:$A$1501,0)) -> 2 | K43: =INDEX(customer_churn_dataset!$V$2:$V$1501,MATCH($A44,customer_churn_dataset!$A$2:$A$1501,0)) -> Low Risk
A44: =customer_churn_dataset!A399 -> CUST101129 | B44: =customer_churn_dataset!B399 -> Basic | C44: =customer_churn_dataset!C399 -> One year | D44: =INDEX(customer_churn_dataset!$E$2:$E$1501,MATCH($A45,customer_churn_dataset!$A$2:$A$1501,0)) -> 20 | E44: =INDEX(customer_churn_dataset!$I$2:$I$1501,MATCH($A45,customer_churn_dataset!$A$2:$A$1501,0)) -> 39.7 | F44: =INDEX(customer_churn_dataset!$L$2:$L$1501,MATCH($A45,customer_churn_dataset!$A$2:$A$1501,0)) -> 0 | G44: =IF(INDEX(customer_churn_dataset!$M$2:$M$1501,MATCH($A45,customer_churn_dataset!$A$2:$A$1501,0))=1,"Yes","No") -> No | H44: =INDEX(customer_churn_dataset!$N$2:$N$1501,MATCH($A45,customer_churn_dataset!$A$2:$A$1501,0)) -> 171.4 | I44: =INDEX(customer_churn_dataset!$O$2:$O$1501,MATCH($A45,customer_churn_dataset!$A$2:$A$1501,0)) -> 0 | J44: =INDEX(customer_churn_dataset!$T$2:$T$1501,MATCH($A45,customer_churn_dataset!$A$2:$A$1501,0)) -> 4 | K44: =INDEX(customer_churn_dataset!$V$2:$V$1501,MATCH($A45,customer_churn_dataset!$A$2:$A$1501,0)) -> Medium Risk
A45: =customer_churn_dataset!A404 -> CUST100246 | B45: =customer_churn_dataset!B404 -> Basic | C45: =customer_churn_dataset!C404 -> Month-to-month | D45: =INDEX(customer_churn_dataset!$E$2:$E$1501,MATCH($A46,customer_churn_dataset!$A$2:$A$1501,0)) -> 9 | E45: =INDEX(customer_churn_dataset!$I$2:$I$1501,MATCH($A46,customer_churn_dataset!$A$2:$A$1501,0)) -> 48.5 | F45: =INDEX(customer_churn_dataset!$L$2:$L$1501,MATCH($A46,customer_churn_dataset!$A$2:$A$1501,0)) -> 3 | G45: =IF(INDEX(customer_churn_dataset!$M$2:$M$1501,MATCH($A46,customer_churn_dataset!$A$2:$A$1501,0))=1,"Yes","No") -> Yes | H45: =INDEX(customer_churn_dataset!$N$2:$N$1501,MATCH($A46,customer_churn_dataset!$A$2:$A$1501,0)) -> 87.84 | I45: =INDEX(customer_churn_dataset!$O$2:$O$1501,MATCH($A46,customer_churn_dataset!$A$2:$A$1501,0)) -> 1 | J45: =INDEX(customer_churn_dataset!$T$2:$T$1501,MATCH($A46,customer_churn_dataset!$A$2:$A$1501,0)) -> 8 | K45: =INDEX(customer_churn_dataset!$V$2:$V$1501,MATCH($A46,customer_churn_dataset!$A$2:$A$1501,0)) -> High Risk
A46: =customer_churn_dataset!A419 -> CUST101226 | B46: =customer_churn_dataset!B419 -> Basic | C46: =customer_churn_dataset!C419 -> Month-to-month | D46: =INDEX(customer_churn_dataset!$E$2:$E$1501,MATCH($A47,customer_churn_dataset!$A$2:$A$1501,0)) -> 22 | E46: =INDEX(customer_churn_dataset!$I$2:$I$1501,MATCH($A47,customer_churn_dataset!$A$2:$A$1501,0)) -> 39.2 | F46: =INDEX(customer_churn_dataset!$L$2:$L$1501,MATCH($A47,customer_churn_dataset!$A$2:$A$1501,0)) -> 1 | G46: =IF(INDEX(customer_churn_dataset!$M$2:$M$1501,MATCH($A47,customer_churn_dataset!$A$2:$A$1501,0))=1,"Yes","No") -> No | H46: =INDEX(customer_churn_dataset!$N$2:$N$1501,MATCH($A47,customer_churn_dataset!$A$2:$A$1501,0)) -> 238.7 | I46: =INDEX(customer_churn_dataset!$O$2:$O$1501,MATCH($A47,customer_churn_dataset!$A$2:$A$1501,0)) -> 1 | J46: =INDEX(customer_churn_dataset!$T$2:$T$1501,MATCH($A47,customer_churn_dataset!$A$2:$A$1501,0)) -> 4 | K46: =INDEX(customer_churn_dataset!$V$2:$V$1501,MATCH($A47,customer_churn_dataset!$A$2:$A$1501,0)) -> Medium Risk
A47: =customer_churn_dataset!A426 -> CUST101325 | B47: =customer_churn_dataset!B426 -> Basic | C47: =customer_churn_dataset!C426 -> Month-to-month | D47: =INDEX(customer_churn_dataset!$E$2:$E$1501,MATCH($A48,customer_churn_dataset!$A$2:$A$1501,0)) -> 17 | E47: =INDEX(customer_churn_dataset!$I$2:$I$1501,MATCH($A48,customer_churn_dataset!$A$2:$A$1501,0)) -> 73.6 | F47: =INDEX(customer_churn_dataset!$L$2:$L$1501,MATCH($A48,customer_churn_dataset!$A$2:$A$1501,0)) -> 0 | G47: =IF(INDEX(customer_churn_dataset!$M$2:$M$1501,MATCH($A48,customer_churn_dataset!$A$2:$A$1501,0))=1,"Yes","No") -> No | H47: =INDEX(customer_churn_dataset!$N$2:$N$1501,MATCH($A48,customer_churn_dataset!$A$2:$A$1501,0)) -> 689.01 | I47: =INDEX(customer_churn_dataset!$O$2:$O$1501,MATCH($A48,customer_churn_dataset!$A$2:$A$1501,0)) -> 0 | J47: =INDEX(customer_churn_dataset!$T$2:$T$1501,MATCH($A48,customer_churn_dataset!$A$2:$A$1501,0)) -> 2 | K47: =INDEX(customer_churn_dataset!$V$2:$V$1501,MATCH($A48,customer_churn_dataset!$A$2:$A$1501,0)) -> Low Risk
A48: =customer_churn_dataset!A457 -> CUST100043 | B48: =customer_churn_dataset!B457 -> Premium | C48: =customer_churn_dataset!C457 -> Month-to-month | D48: =INDEX(customer_churn_dataset!$E$2:$E$1501,MATCH($A49,customer_churn_dataset!$A$2:$A$1501,0)) -> 7 | E48: =INDEX(customer_churn_dataset!$I$2:$I$1501,MATCH($A49,customer_churn_dataset!$A$2:$A$1501,0)) -> 9.9 | F48: =INDEX(customer_churn_dataset!$L$2:$L$1501,MATCH($A49,customer_churn_dataset!$A$2:$A$1501,0)) -> 4 | G48: =IF(INDEX(customer_churn_dataset!$M$2:$M$1501,MATCH($A49,customer_churn_dataset!$A$2:$A$1501,0))=1,"Yes","No") -> No | H48: =INDEX(customer_churn_dataset!$N$2:$N$1501,MATCH($A49,customer_churn_dataset!$A$2:$A$1501,0)) -> 277.69 | I48: =INDEX(customer_churn_dataset!$O$2:$O$1501,MATCH($A49,customer_churn_dataset!$A$2:$A$1501,0)) -> 0 | J48: =INDEX(customer_churn_dataset!$T$2:$T$1501,MATCH($A49,customer_churn_dataset!$A$2:$A$1501,0)) -> 6 | K48: =INDEX(customer_churn_dataset!$V$2:$V$1501,MATCH($A49,customer_churn_dataset!$A$2:$A$1501,0)) -> High Risk
A49: =customer_churn_dataset!A474 -> CUST100248 | B49: =customer_churn_dataset!B474 -> Premium | C49: =customer_churn_dataset!C474 -> Month-to-month | D49: =INDEX(customer_churn_dataset!$E$2:$E$1501,MATCH($A50,customer_churn_dataset!$A$2:$A$1501,0)) -> 33 | E49: =INDEX(customer_churn_dataset!$I$2:$I$1501,MATCH($A50,customer_churn_dataset!$A$2:$A$1501,0)) -> 39.8 | F49: =INDEX(customer_churn_dataset!$L$2:$L$1501,MATCH($A50,customer_churn_dataset!$A$2:$A$1501,0)) -> 1 | G49: =IF(INDEX(customer_churn_dataset!$M$2:$M$1501,MATCH($A50,customer_churn_dataset!$A$2:$A$1501,0))=1,"Yes","No") -> No | H49: =INDEX(customer_churn_dataset!$N$2:$N$1501,MATCH($A50,customer_churn_dataset!$A$2:$A$1501,0)) -> 251.79 | I49: =INDEX(customer_churn_dataset!$O$2:$O$1501,MATCH($A50,customer_churn_dataset!$A$2:$A$1501,0)) -> 0 | J49: =INDEX(customer_churn_dataset!$T$2:$T$1501,MATCH($A50,customer_churn_dataset!$A$2:$A$1501,0)) -> 4 | K49: =INDEX(customer_churn_dataset!$V$2:$V$1501,MATCH($A50,customer_churn_dataset!$A$2:$A$1501,0)) -> Medium Risk
A50: =customer_churn_dataset!A480 -> CUST100434 | B50: =customer_churn_dataset!B480 -> Basic | C50: =customer_churn_dataset!C480 -> Month-to-month | D50: =INDEX(customer_churn_dataset!$E$2:$E$1501,MATCH($A51,customer_churn_dataset!$A$2:$A$1501,0)) -> 3 | E50: =INDEX(customer_churn_dataset!$I$2:$I$1501,MATCH($A51,customer_churn_dataset!$A$2:$A$1501,0)) -> 33.1 | F50: =INDEX(customer_churn_dataset!$L$2:$L$1501,MATCH($A51,customer_churn_dataset!$A$2:$A$1501,0)) -> 2 | G50: =IF(INDEX(customer_churn_dataset!$M$2:$M$1501,MATCH($A51,customer_churn_dataset!$A$2:$A$1501,0))=1,"Yes","No") -> No | H50: =INDEX(customer_churn_dataset!$N$2:$N$1501,MATCH($A51,customer_churn_dataset!$A$2:$A$1501,0)) -> 126.84 | I50: =INDEX(customer_churn_dataset!$O$2:$O$1501,MATCH($A51,customer_churn_dataset!$A$2:$A$1501,0)) -> 0 | J50: =INDEX(customer_churn_dataset!$T$2:$T$1501,MATCH($A51,customer_churn_dataset!$A$2:$A$1501,0)) -> 6 | K50: =INDEX(customer_churn_dataset!$V$2:$V$1501,MATCH($A51,customer_churn_dataset!$A$2:$A$1501,0)) -> High Risk
A51: =customer_churn_dataset!A493 -> CUST100001 | B51: =customer_churn_dataset!B493 -> Premium | C51: =customer_churn_dataset!C493 -> Month-to-month | D51: =INDEX(customer_churn_dataset!$E$2:$E$1501,MATCH($A52,customer_churn_dataset!$A$2:$A$1501,0)) -> 4 | E51: =INDEX(customer_churn_dataset!$I$2:$I$1501,MATCH($A52,customer_churn_dataset!$A$2:$A$1501,0)) -> 52.8 | F51: =INDEX(customer_churn_dataset!$L$2:$L$1501,MATCH($A52,customer_churn_dataset!$A$2:$A$1501,0)) -> 2 | G51: =IF(INDEX(customer_churn_dataset!$M$2:$M$1501,MATCH($A52,customer_churn_dataset!$A$2:$A$1501,0))=1,"Yes","No") -> No | H51: =INDEX(customer_churn_dataset!$N$2:$N$1501,MATCH($A52,customer_churn_dataset!$A$2:$A$1501,0)) -> 46 | I51: =INDEX(customer_churn_dataset!$O$2:$O$1501,MATCH($A52,customer_churn_dataset!$A$2:$A$1501,0)) -> 0 | J51: =INDEX(customer_churn_dataset!$T$2:$T$1501,MATCH($A52,customer_churn_dataset!$A$2:$A$1501,0)) -> 3 | K51: =INDEX(customer_churn_dataset!$V$2:$V$1501,MATCH($A52,customer_churn_dataset!$A$2:$A$1501,0)) -> Medium Risk
A52: =customer_churn_dataset!A498 -> CUST100356 | B52: =customer_churn_dataset!B498 -> Basic | C52: =customer_churn_dataset!C498 -> Two year | D52: =INDEX(customer_churn_dataset!$E$2:$E$1501,MATCH($A53,customer_churn_dataset!$A$2:$A$1501,0)) -> 0 | E52: =INDEX(customer_churn_dataset!$I$2:$I$1501,MATCH($A53,customer_churn_dataset!$A$2:$A$1501,0)) -> 73 | F52: =INDEX(customer_churn_dataset!$L$2:$L$1501,MATCH($A53,customer_churn_dataset!$A$2:$A$1501,0)) -> 0 | G52: =IF(INDEX(customer_churn_dataset!$M$2:$M$1501,MATCH($A53,customer_churn_dataset!$A$2:$A$1501,0))=1,"Yes","No") -> No | H52: =INDEX(customer_churn_dataset!$N$2:$N$1501,MATCH($A53,customer_churn_dataset!$A$2:$A$1501,0)) -> 0 | I52: =INDEX(customer_churn_dataset!$O$2:$O$1501,MATCH($A53,customer_churn_dataset!$A$2:$A$1501,0)) -> 0 | J52: =INDEX(customer_churn_dataset!$T$2:$T$1501,MATCH($A53,customer_churn_dataset!$A$2:$A$1501,0)) -> 2 | K52: =INDEX(customer_churn_dataset!$V$2:$V$1501,MATCH($A53,customer_churn_dataset!$A$2:$A$1501,0)) -> Low Risk
A53: =customer_churn_dataset!A506 -> CUST100659 | B53: =customer_churn_dataset!B506 -> Standard | C53: =customer_churn_dataset!C506 -> One year | D53: =INDEX(customer_churn_dataset!$E$2:$E$1501,MATCH($A54,customer_churn_dataset!$A$2:$A$1501,0)) -> 52 | E53: =INDEX(customer_churn_dataset!$I$2:$I$1501,MATCH($A54,customer_churn_dataset!$A$2:$A$1501,0)) -> 34.8 | F53: =INDEX(customer_churn_dataset!$L$2:$L$1501,MATCH($A54,customer_churn_dataset!$A$2:$A$1501,0)) -> 1 | G53: =IF(INDEX(customer_churn_dataset!$M$2:$M$1501,MATCH($A54,customer_churn_dataset!$A$2:$A$1501,0))=1,"Yes","No") -> No | H53: =INDEX(customer_churn_dataset!$N$2:$N$1501,MATCH($A54,customer_churn_dataset!$A$2:$A$1501,0)) -> 491.92 | I53: =INDEX(customer_churn_dataset!$O$2:$O$1501,MATCH($A54,customer_churn_dataset!$A$2:$A$1501,0)) -> 0 | J53: =INDEX(customer_churn_dataset!$T$2:$T$1501,MATCH($A54,customer_churn_dataset!$A$2:$A$1501,0)) -> 4 | K53: =INDEX(customer_churn_dataset!$V$2:$V$1501,MATCH($A54,customer_churn_dataset!$A$2:$A$1501,0)) -> Medium Risk
A54: =customer_churn_dataset!A516 -> CUST100377 | B54: =customer_churn_dataset!B516 -> Basic | C54: =customer_churn_dataset!C516 -> Month-to-month | D54: =INDEX(customer_churn_dataset!$E$2:$E$1501,MATCH($A55,customer_churn_dataset!$A$2:$A$1501,0)) -> 2 | E54: =INDEX(customer_churn_dataset!$I$2:$I$1501,MATCH($A55,customer_churn_dataset!$A$2:$A$1501,0)) -> 54.1 | F54: =INDEX(customer_churn_dataset!$L$2:$L$1501,MATCH($A55,customer_churn_dataset!$A$2:$A$1501,0)) -> 2 | G54: =IF(INDEX(customer_churn_dataset!$M$2:$M$1501,MATCH($A55,customer_churn_dataset!$A$2:$A$1501,0))=1,"Yes","No") -> Yes | H54: =INDEX(customer_churn_dataset!$N$2:$N$1501,MATCH($A55,customer_churn_dataset!$A$2:$A$1501,0)) -> 80.62 | I54: =INDEX(customer_churn_dataset!$O$2:$O$1501,MATCH($A55,customer_churn_dataset!$A$2:$A$1501,0)) -> 1 | J54: =INDEX(customer_churn_dataset!$T$2:$T$1501,MATCH($A55,customer_churn_dataset!$A$2:$A$1501,0)) -> 7 | K54: =INDEX(customer_churn_dataset!$V$2:$V$1501,MATCH($A55,customer_churn_dataset!$A$2:$A$1501,0)) -> High Risk
A55: =customer_churn_dataset!A519 -> CUST100139 | B55: =customer_churn_dataset!B519 -> Premium | C55: =customer_churn_dataset!C519 -> One year | D55: =INDEX(customer_churn_dataset!$E$2:$E$1501,MATCH($A56,customer_churn_dataset!$A$2:$A$1501,0)) -> 36 | E55: =INDEX(customer_churn_dataset!$I$2:$I$1501,MATCH($A56,customer_churn_dataset!$A$2:$A$1501,0)) -> 83.7 | F55: =INDEX(customer_churn_dataset!$L$2:$L$1501,MATCH($A56,customer_churn_dataset!$A$2:$A$1501,0)) -> 1 | G55: =IF(INDEX(customer_churn_dataset!$M$2:$M$1501,MATCH($A56,customer_churn_dataset!$A$2:$A$1501,0))=1,"Yes","No") -> Yes | H55: =INDEX(customer_churn_dataset!$N$2:$N$1501,MATCH($A56,customer_churn_dataset!$A$2:$A$1501,0)) -> 1425.6 | I55: =INDEX(customer_churn_dataset!$O$2:$O$1501,MATCH($A56,customer_churn_dataset!$A$2:$A$1501,0)) -> 0 | J55: =INDEX(customer_churn_dataset!$T$2:$T$1501,MATCH($A56,customer_churn_dataset!$A$2:$A$1501,0)) -> 4 | K55: =INDEX(customer_churn_dataset!$V$2:$V$1501,MATCH($A56,customer_churn_dataset!$A$2:$A$1501,0)) -> Medium Risk
A56: =customer_churn_dataset!A521 -> CUST100512 | B56: =customer_churn_dataset!B521 -> Premium | C56: =customer_churn_dataset!C521 -> One year | D56: =INDEX(customer_churn_dataset!$E$2:$E$1501,MATCH($A57,customer_churn_dataset!$A$2:$A$1501,0)) -> 14 | E56: =INDEX(customer_churn_dataset!$I$2:$I$1501,MATCH($A57,customer_churn_dataset!$A$2:$A$1501,0)) -> 52.7 | F56: =INDEX(customer_churn_dataset!$L$2:$L$1501,MATCH($A57,customer_churn_dataset!$A$2:$A$1501,0)) -> 1 | G56: =IF(INDEX(customer_churn_dataset!$M$2:$M$1501,MATCH($A57,customer_churn_dataset!$A$2:$A$1501,0))=1,"Yes","No") -> No | H56: =INDEX(customer_churn_dataset!$N$2:$N$1501,MATCH($A57,customer_churn_dataset!$A$2:$A$1501,0)) -> 147.56 | I56: =INDEX(customer_churn_dataset!$O$2:$O$1501,MATCH($A57,customer_churn_dataset!$A$2:$A$1501,0)) -> 1 | J56: =INDEX(customer_churn_dataset!$T$2:$T$1501,MATCH($A57,customer_churn_dataset!$A$2:$A$1501,0)) -> 3 | K56: =INDEX(customer_churn_dataset!$V$2:$V$1501,MATCH($A57,customer_churn_dataset!$A$2:$A$1501,0)) -> Medium Risk
A57: =customer_churn_dataset!A524 -> CUST100965 | B57: =customer_churn_dataset!B524 -> Basic | C57: =customer_churn_dataset!C524 -> Month-to-month | D57: =INDEX(customer_churn_dataset!$E$2:$E$1501,MATCH($A58,customer_churn_dataset!$A$2:$A$1501,0)) -> 8 | E57: =INDEX(customer_churn_dataset!$I$2:$I$1501,MATCH($A58,customer_churn_dataset!$A$2:$A$1501,0)) -> 65.1 | F57: =INDEX(customer_churn_dataset!$L$2:$L$1501,MATCH($A58,customer_churn_dataset!$A$2:$A$1501,0)) -> 3 | G57: =IF(INDEX(customer_churn_dataset!$M$2:$M$1501,MATCH($A58,customer_churn_dataset!$A$2:$A$1501,0))=1,"Yes","No") -> No | H57: =INDEX(customer_churn_dataset!$N$2:$N$1501,MATCH($A58,customer_churn_dataset!$A$2:$A$1501,0)) -> 169.52 | I57: =INDEX(customer_churn_dataset!$O$2:$O$1501,MATCH($A58,customer_churn_dataset!$A$2:$A$1501,0)) -> 1 | J57: =INDEX(customer_churn_dataset!$T$2:$T$1501,MATCH($A58,customer_churn_dataset!$A$2:$A$1501,0)) -> 4 | K57: =INDEX(customer_churn_dataset!$V$2:$V$1501,MATCH($A58,customer_churn_dataset!$A$2:$A$1501,0)) -> Medium Risk
A58: =customer_churn_dataset!A532 -> CUST100238 | B58: =customer_churn_dataset!B532 -> Standard | C58: =customer_churn_dataset!C532 -> Month-to-month | D58: =INDEX(customer_churn_dataset!$E$2:$E$1501,MATCH($A59,customer_churn_dataset!$A$2:$A$1501,0)) -> 2 | E58: =INDEX(customer_churn_dataset!$I$2:$I$1501,MATCH($A59,customer_churn_dataset!$A$2:$A$1501,0)) -> 46.7 | F58: =INDEX(customer_churn_dataset!$L$2:$L$1501,MATCH($A59,customer_churn_dataset!$A$2:$A$1501,0)) -> 3 | G58: =IF(INDEX(customer_churn_dataset!$M$2:$M$1501,MATCH($A59,customer_churn_dataset!$A$2:$A$1501,0))=1,"Yes","No") -> No | H58: =INDEX(customer_churn_dataset!$N$2:$N$1501,MATCH($A59,customer_churn_dataset!$A$2:$A$1501,0)) -> 39.7 | I58: =INDEX(customer_churn_dataset!$O$2:$O$1501,MATCH($A59,customer_churn_dataset!$A$2:$A$1501,0)) -> 0 | J58: =INDEX(customer_churn_dataset!$T$2:$T$1501,MATCH($A59,customer_churn_dataset!$A$2:$A$1501,0)) -> 5 | K58: =INDEX(customer_churn_dataset!$V$2:$V$1501,MATCH($A59,customer_churn_dataset!$A$2:$A$1501,0)) -> Medium Risk
A59: =customer_churn_dataset!A537 -> CUST100841 | B59: =customer_churn_dataset!B537 -> Standard | C59: =customer_churn_dataset!C537 -> Month-to-month | D59: =INDEX(customer_churn_dataset!$E$2:$E$1501,MATCH($A60,customer_churn_dataset!$A$2:$A$1501,0)) -> 34 | E59: =INDEX(customer_churn_dataset!$I$2:$I$1501,MATCH($A60,customer_churn_dataset!$A$2:$A$1501,0)) -> 38.9 | F59: =INDEX(customer_churn_dataset!$L$2:$L$1501,MATCH($A60,customer_churn_dataset!$A$2:$A$1501,0)) -> 2 | G59: =IF(INDEX(customer_churn_dataset!$M$2:$M$1501,MATCH($A60,customer_churn_dataset!$A$2:$A$1501,0))=1,"Yes","No") -> No | H59: =INDEX(customer_churn_dataset!$N$2:$N$1501,MATCH($A60,customer_churn_dataset!$A$2:$A$1501,0)) -> 387.6 | I59: =INDEX(customer_churn_dataset!$O$2:$O$1501,MATCH($A60,customer_churn_dataset!$A$2:$A$1501,0)) -> 0 | J59: =INDEX(customer_churn_dataset!$T$2:$T$1501,MATCH($A60,customer_churn_dataset!$A$2:$A$1501,0)) -> 3 | K59: =INDEX(customer_churn_dataset!$V$2:$V$1501,MATCH($A60,customer_churn_dataset!$A$2:$A$1501,0)) -> Medium Risk
A60: =customer_churn_dataset!A548 -> CUST100667 | B60: =customer_churn_dataset!B548 -> Basic | C60: =customer_churn_dataset!C548 -> Two year | D60: =INDEX(customer_churn_dataset!$E$2:$E$1501,MATCH($A61,customer_churn_dataset!$A$2:$A$1501,0)) -> 3 | E60: =INDEX(customer_churn_dataset!$I$2:$I$1501,MATCH($A61,customer_churn_dataset!$A$2:$A$1501,0)) -> 30.8 | F60: =INDEX(customer_churn_dataset!$L$2:$L$1501,MATCH($A61,customer_churn_dataset!$A$2:$A$1501,0)) -> 0 | G60: =IF(INDEX(customer_churn_dataset!$M$2:$M$1501,MATCH($A61,customer_churn_dataset!$A$2:$A$1501,0))=1,"Yes","No") -> No | H60: =INDEX(customer_churn_dataset!$N$2:$N$1501,MATCH($A61,customer_churn_dataset!$A$2:$A$1501,0)) -> 56.31 | I60: =INDEX(customer_churn_dataset!$O$2:$O$1501,MATCH($A61,customer_churn_dataset!$A$2:$A$1501,0)) -> 1 | J60: =INDEX(customer_churn_dataset!$T$2:$T$1501,MATCH($A61,customer_churn_dataset!$A$2:$A$1501,0)) -> 5 | K60: =INDEX(customer_churn_dataset!$V$2:$V$1501,MATCH($A61,customer_churn_dataset!$A$2:$A$1501,0)) -> Medium Risk
A61: =customer_churn_dataset!A552 -> CUST100301 | B61: =customer_churn_dataset!B552 -> Standard | C61: =customer_churn_dataset!C552 -> Month-to-month | D61: =INDEX(customer_churn_dataset!$E$2:$E$1501,MATCH($A62,customer_churn_dataset!$A$2:$A$1501,0)) -> 13 | E61: =INDEX(customer_churn_dataset!$I$2:$I$1501,MATCH($A62,customer_churn_dataset!$A$2:$A$1501,0)) -> 59 | F61: =INDEX(customer_churn_dataset!$L$2:$L$1501,MATCH($A62,customer_churn_dataset!$A$2:$A$1501,0)) -> 2 | G61: =IF(INDEX(customer_churn_dataset!$M$2:$M$1501,MATCH($A62,customer_churn_dataset!$A$2:$A$1501,0))=1,"Yes","No") -> No | H61: =INDEX(customer_churn_dataset!$N$2:$N$1501,MATCH($A62,customer_churn_dataset!$A$2:$A$1501,0)) -> 126.62 | I61: =INDEX(customer_churn_dataset!$O$2:$O$1501,MATCH($A62,customer_churn_dataset!$A$2:$A$1501,0)) -> 0 | J61: =INDEX(customer_churn_dataset!$T$2:$T$1501,MATCH($A62,customer_churn_dataset!$A$2:$A$1501,0)) -> 2 | K61: =INDEX(customer_churn_dataset!$V$2:$V$1501,MATCH($A62,customer_churn_dataset!$A$2:$A$1501,0)) -> Low Risk
A62: =customer_churn_dataset!A572 -> CUST100449 | B62: =customer_churn_dataset!B572 -> Basic | C62: =customer_churn_dataset!C572 -> One year | D62: =INDEX(customer_churn_dataset!$E$2:$E$1501,MATCH($A63,customer_churn_dataset!$A$2:$A$1501,0)) -> 4 | E62: =INDEX(customer_churn_dataset!$I$2:$I$1501,MATCH($A63,customer_churn_dataset!$A$2:$A$1501,0)) -> 65.1 | F62: =INDEX(customer_churn_dataset!$L$2:$L$1501,MATCH($A63,customer_churn_dataset!$A$2:$A$1501,0)) -> 2 | G62: =IF(INDEX(customer_churn_dataset!$M$2:$M$1501,MATCH($A63,customer_churn_dataset!$A$2:$A$1501,0))=1,"Yes","No") -> No | H62: =INDEX(customer_churn_dataset!$N$2:$N$1501,MATCH($A63,customer_churn_dataset!$A$2:$A$1501,0)) -> 72 | I62: =INDEX(customer_churn_dataset!$O$2:$O$1501,MATCH($A63,customer_churn_dataset!$A$2:$A$1501,0)) -> 0 | J62: =INDEX(customer_churn_dataset!$T$2:$T$1501,MATCH($A63,customer_churn_dataset!$A$2:$A$1501,0)) -> 3 | K62: =INDEX(customer_churn_dataset!$V$2:$V$1501,MATCH($A63,customer_churn_dataset!$A$2:$A$1501,0)) -> Medium Risk
A63: =customer_churn_dataset!A580 -> CUST100092 | B63: =customer_churn_dataset!B580 -> Standard | C63: =customer_churn_dataset!C580 -> One year | D63: =INDEX(customer_churn_dataset!$E$2:$E$1501,MATCH($A64,customer_churn_dataset!$A$2:$A$1501,0)) -> 39 | E63: =INDEX(customer_churn_dataset!$I$2:$I$1501,MATCH($A64,customer_churn_dataset!$A$2:$A$1501,0)) -> 55.4 | F63: =INDEX(customer_churn_dataset!$L$2:$L$1501,MATCH($A64,customer_churn_dataset!$A$2:$A$1501,0)) -> 0 | G63: =IF(INDEX(customer_churn_dataset!$M$2:$M$1501,MATCH($A64,customer_churn_dataset!$A$2:$A$1501,0))=1,"Yes","No") -> No | H63: =INDEX(customer_churn_dataset!$N$2:$N$1501,MATCH($A64,customer_churn_dataset!$A$2:$A$1501,0)) -> 379.08 | I63: =INDEX(customer_churn_dataset!$O$2:$O$1501,MATCH($A64,customer_churn_dataset!$A$2:$A$1501,0)) -> 0 | J63: =INDEX(customer_churn_dataset!$T$2:$T$1501,MATCH($A64,customer_churn_dataset!$A$2:$A$1501,0)) -> 2 | K63: =INDEX(customer_churn_dataset!$V$2:$V$1501,MATCH($A64,customer_churn_dataset!$A$2:$A$1501,0)) -> Low Risk
A64: =customer_churn_dataset!A588 -> CUST100654 | B64: =customer_churn_dataset!B588 -> Basic | C64: =customer_churn_dataset!C588 -> Month-to-month | D64: =INDEX(customer_churn_dataset!$E$2:$E$1501,MATCH($A65,customer_churn_dataset!$A$2:$A$1501,0)) -> 44 | E64: =INDEX(customer_churn_dataset!$I$2:$I$1501,MATCH($A65,customer_churn_dataset!$A$2:$A$1501,0)) -> 66 | F64: =INDEX(customer_churn_dataset!$L$2:$L$1501,MATCH($A65,customer_churn_dataset!$A$2:$A$1501,0)) -> 3 | G64: =IF(INDEX(customer_churn_dataset!$M$2:$M$1501,MATCH($A65,customer_churn_dataset!$A$2:$A$1501,0))=1,"Yes","No") -> No | H64: =INDEX(customer_churn_dataset!$N$2:$N$1501,MATCH($A65,customer_churn_dataset!$A$2:$A$1501,0)) -> 389.4 | I64: =INDEX(customer_churn_dataset!$O$2:$O$1501,MATCH($A65,customer_churn_dataset!$A$2:$A$1501,0)) -> 0 | J64: =INDEX(customer_churn_dataset!$T$2:$T$1501,MATCH($A65,customer_churn_dataset!$A$2:$A$1501,0)) -> 3 | K64: =INDEX(customer_churn_dataset!$V$2:$V$1501,MATCH($A65,customer_churn_dataset!$A$2:$A$1501,0)) -> Medium Risk
A65: =customer_churn_dataset!A592 -> CUST100676 | B65: =customer_churn_dataset!B592 -> Basic | C65: =customer_churn_dataset!C592 -> Month-to-month | D65: =INDEX(customer_churn_dataset!$E$2:$E$1501,MATCH($A66,customer_churn_dataset!$A$2:$A$1501,0)) -> 72 | E65: =INDEX(customer_churn_dataset!$I$2:$I$1501,MATCH($A66,customer_churn_dataset!$A$2:$A$1501,0)) -> 19.4 | F65: =INDEX(customer_churn_dataset!$L$2:$L$1501,MATCH($A66,customer_churn_dataset!$A$2:$A$1501,0)) -> 2 | G65: =IF(INDEX(customer_churn_dataset!$M$2:$M$1501,MATCH($A66,customer_churn_dataset!$A$2:$A$1501,0))=1,"Yes","No") -> No | H65: =INDEX(customer_churn_dataset!$N$2:$N$1501,MATCH($A66,customer_churn_dataset!$A$2:$A$1501,0)) -> 1559.52 | I65: =INDEX(customer_churn_dataset!$O$2:$O$1501,MATCH($A66,customer_churn_dataset!$A$2:$A$1501,0)) -> 0 | J65: =INDEX(customer_churn_dataset!$T$2:$T$1501,MATCH($A66,customer_churn_dataset!$A$2:$A$1501,0)) -> 5 | K65: =INDEX(customer_churn_dataset!$V$2:$V$1501,MATCH($A66,customer_churn_dataset!$A$2:$A$1501,0)) -> Medium Risk
A66: =customer_churn_dataset!A595 -> CUST101244 | B66: =customer_churn_dataset!B595 -> Standard | C66: =customer_churn_dataset!C595 -> Month-to-month | D66: =INDEX(customer_churn_dataset!$E$2:$E$1501,MATCH($A67,customer_churn_dataset!$A$2:$A$1501,0)) -> 6 | E66: =INDEX(customer_churn_dataset!$I$2:$I$1501,MATCH($A67,customer_churn_dataset!$A$2:$A$1501,0)) -> 46.3 | F66: =INDEX(customer_churn_dataset!$L$2:$L$1501,MATCH($A67,customer_churn_dataset!$A$2:$A$1501,0)) -> 2 | G66: =IF(INDEX(customer_churn_dataset!$M$2:$M$1501,MATCH($A67,customer_churn_dataset!$A$2:$A$1501,0))=1,"Yes","No") -> Yes | H66: =INDEX(customer_churn_dataset!$N$2:$N$1501,MATCH($A67,customer_churn_dataset!$A$2:$A$1501,0)) -> 239.94 | I66: =INDEX(customer_churn_dataset!$O$2:$O$1501,MATCH($A67,customer_churn_dataset!$A$2:$A$1501,0)) -> 0 | J66: =INDEX(customer_churn_dataset!$T$2:$T$1501,MATCH($A67,customer_churn_dataset!$A$2:$A$1501,0)) -> 6 | K66: =INDEX(customer_churn_dataset!$V$2:$V$1501,MATCH($A67,customer_churn_dataset!$A$2:$A$1501,0)) -> High Risk
A67: =customer_churn_dataset!A602 -> CUST100920 | B67: =customer_churn_dataset!B602 -> Premium | C67: =customer_churn_dataset!C602 -> Two year | D67: =INDEX(customer_churn_dataset!$E$2:$E$1501,MATCH($A68,customer_churn_dataset!$A$2:$A$1501,0)) -> 22 | E67: =INDEX(customer_churn_dataset!$I$2:$I$1501,MATCH($A68,customer_churn_dataset!$A$2:$A$1501,0)) -> 33.3 | F67: =INDEX(customer_churn_dataset!$L$2:$L$1501,MATCH($A68,customer_churn_dataset!$A$2:$A$1501,0)) -> 0 | G67: =IF(INDEX(customer_churn_dataset!$M$2:$M$1501,MATCH($A68,customer_churn_dataset!$A$2:$A$1501,0))=1,"Yes","No") -> No | H67: =INDEX(customer_churn_dataset!$N$2:$N$1501,MATCH($A68,customer_churn_dataset!$A$2:$A$1501,0)) -> 890.12 | I67: =INDEX(customer_churn_dataset!$O$2:$O$1501,MATCH($A68,customer_churn_dataset!$A$2:$A$1501,0)) -> 0 | J67: =INDEX(customer_churn_dataset!$T$2:$T$1501,MATCH($A68,customer_churn_dataset!$A$2:$A$1501,0)) -> 4 | K67: =INDEX(customer_churn_dataset!$V$2:$V$1501,MATCH($A68,customer_churn_dataset!$A$2:$A$1501,0)) -> Medium Risk
A68: =customer_churn_dataset!A604 -> CUST101370 | B68: =customer_churn_dataset!B604 -> Premium | C68: =customer_churn_dataset!C604 -> Month-to-month | D68: =INDEX(customer_churn_dataset!$E$2:$E$1501,MATCH($A69,customer_churn_dataset!$A$2:$A$1501,0)) -> 12 | E68: =INDEX(customer_churn_dataset!$I$2:$I$1501,MATCH($A69,customer_churn_dataset!$A$2:$A$1501,0)) -> 71.9 | F68: =INDEX(customer_churn_dataset!$L$2:$L$1501,MATCH($A69,customer_churn_dataset!$A$2:$A$1501,0)) -> 7 | G68: =IF(INDEX(customer_churn_dataset!$M$2:$M$1501,MATCH($A69,customer_churn_dataset!$A$2:$A$1501,0))=1,"Yes","No") -> No | H68: =INDEX(customer_churn_dataset!$N$2:$N$1501,MATCH($A69,customer_churn_dataset!$A$2:$A$1501,0)) -> 223.44 | I68: =INDEX(customer_churn_dataset!$O$2:$O$1501,MATCH($A69,customer_churn_dataset!$A$2:$A$1501,0)) -> 1 | J68: =INDEX(customer_churn_dataset!$T$2:$T$1501,MATCH($A69,customer_churn_dataset!$A$2:$A$1501,0)) -> 3 | K68: =INDEX(customer_churn_dataset!$V$2:$V$1501,MATCH($A69,customer_churn_dataset!$A$2:$A$1501,0)) -> Medium Risk
A69: =customer_churn_dataset!A608 -> CUST100188 | B69: =customer_churn_dataset!B608 -> Standard | C69: =customer_churn_dataset!C608 -> Month-to-month | D69: =INDEX(customer_churn_dataset!$E$2:$E$1501,MATCH($A70,customer_churn_dataset!$A$2:$A$1501,0)) -> 8 | E69: =INDEX(customer_churn_dataset!$I$2:$I$1501,MATCH($A70,customer_churn_dataset!$A$2:$A$1501,0)) -> 52.5 | F69: =INDEX(customer_churn_dataset!$L$2:$L$1501,MATCH($A70,customer_churn_dataset!$A$2:$A$1501,0)) -> 1 | G69: =IF(INDEX(customer_churn_dataset!$M$2:$M$1501,MATCH($A70,customer_churn_dataset!$A$2:$A$1501,0))=1,"Yes","No") -> Yes | H69: =INDEX(customer_churn_dataset!$N$2:$N$1501,MATCH($A70,customer_churn_dataset!$A$2:$A$1501,0)) -> 153.2 | I69: =INDEX(customer_churn_dataset!$O$2:$O$1501,MATCH($A70,customer_churn_dataset!$A$2:$A$1501,0)) -> 0 | J69: =INDEX(customer_churn_dataset!$T$2:$T$1501,MATCH($A70,customer_churn_dataset!$A$2:$A$1501,0)) -> 7 | K69: =INDEX(customer_churn_dataset!$V$2:$V$1501,MATCH($A70,customer_churn_dataset!$A$2:$A$1501,0)) -> High Risk
A70: =customer_churn_dataset!A611 -> CUST100605 | B70: =customer_churn_dataset!B611 -> Standard | C70: =customer_churn_dataset!C611 -> Month-to-month | D70: =INDEX(customer_churn_dataset!$E$2:$E$1501,MATCH($A71,customer_churn_dataset!$A$2:$A$1501,0)) -> 12 | E70: =INDEX(customer_churn_dataset!$I$2:$I$1501,MATCH($A71,customer_churn_dataset!$A$2:$A$1501,0)) -> 46.7 | F70: =INDEX(customer_churn_dataset!$L$2:$L$1501,MATCH($A71,customer_churn_dataset!$A$2:$A$1501,0)) -> 2 | G70: =IF(INDEX(customer_churn_dataset!$M$2:$M$1501,MATCH($A71,customer_churn_dataset!$A$2:$A$1501,0))=1,"Yes","No") -> Yes | H70: =INDEX(customer_churn_dataset!$N$2:$N$1501,MATCH($A71,customer_churn_dataset!$A$2:$A$1501,0)) -> 467.88 | I70: =INDEX(customer_churn_dataset!$O$2:$O$1501,MATCH($A71,customer_churn_dataset!$A$2:$A$1501,0)) -> 1 | J70: =INDEX(customer_churn_dataset!$T$2:$T$1501,MATCH($A71,customer_churn_dataset!$A$2:$A$1501,0)) -> 7 | K70: =INDEX(customer_churn_dataset!$V$2:$V$1501,MATCH($A71,customer_churn_dataset!$A$2:$A$1501,0)) -> High Risk
A71: =customer_churn_dataset!A615 -> CUST100506 | B71: =customer_churn_dataset!B615 -> Premium | C71: =customer_churn_dataset!C615 -> Month-to-month | D71: =INDEX(customer_churn_dataset!$E$2:$E$1501,MATCH($A72,customer_churn_dataset!$A$2:$A$1501,0)) -> 13 | E71: =INDEX(customer_churn_dataset!$I$2:$I$1501,MATCH($A72,customer_churn_dataset!$A$2:$A$1501,0)) -> 69.3 | F71: =INDEX(customer_churn_dataset!$L$2:$L$1501,MATCH($A72,customer_churn_dataset!$A$2:$A$1501,0)) -> 1 | G71: =IF(INDEX(customer_churn_dataset!$M$2:$M$1501,MATCH($A72,customer_churn_dataset!$A$2:$A$1501,0))=1,"Yes","No") -> Yes | H71: =INDEX(customer_churn_dataset!$N$2:$N$1501,MATCH($A72,customer_churn_dataset!$A$2:$A$1501,0)) -> 258.83 | I71: =INDEX(customer_churn_dataset!$O$2:$O$1501,MATCH($A72,customer_churn_dataset!$A$2:$A$1501,0)) -> 0 | J71: =INDEX(customer_churn_dataset!$T$2:$T$1501,MATCH($A72,customer_churn_dataset!$A$2:$A$1501,0)) -> 4 | K71: =INDEX(customer_churn_dataset!$V$2:$V$1501,MATCH($A72,customer_churn_dataset!$A$2:$A$1501,0)) -> Medium Risk
A72: =customer_churn_dataset!A619 -> CUST100482 | B72: =customer_churn_dataset!B619 -> Standard | C72: =customer_churn_dataset!C619 -> One year | D72: =INDEX(customer_churn_dataset!$E$2:$E$1501,MATCH($A73,customer_churn_dataset!$A$2:$A$1501,0)) -> 6 | E72: =INDEX(customer_churn_dataset!$I$2:$I$1501,MATCH($A73,customer_churn_dataset!$A$2:$A$1501,0)) -> 57.1 | F72: =INDEX(customer_churn_dataset!$L$2:$L$1501,MATCH($A73,customer_churn_dataset!$A$2:$A$1501,0)) -> 1 | G72: =IF(INDEX(customer_churn_dataset!$M$2:$M$1501,MATCH($A73,customer_churn_dataset!$A$2:$A$1501,0))=1,"Yes","No") -> Yes | H72: =INDEX(customer_churn_dataset!$N$2:$N$1501,MATCH($A73,customer_churn_dataset!$A$2:$A$1501,0)) -> 62.28 | I72: =INDEX(customer_churn_dataset!$O$2:$O$1501,MATCH($A73,customer_churn_dataset!$A$2:$A$1501,0)) -> 0 | J72: =INDEX(customer_churn_dataset!$T$2:$T$1501,MATCH($A73,customer_churn_dataset!$A$2:$A$1501,0)) -> 5 | K72: =INDEX(customer_churn_dataset!$V$2:$V$1501,MATCH($A73,customer_churn_dataset!$A$2:$A$1501,0)) -> Medium Risk
A73: =customer_churn_dataset!A627 -> CUST100902 | B73: =customer_churn_dataset!B627 -> Basic | C73: =customer_churn_dataset!C627 -> One year | D73: =INDEX(customer_churn_dataset!$E$2:$E$1501,MATCH($A74,customer_churn_dataset!$A$2:$A$1501,0)) -> 35 | E73: =INDEX(customer_churn_dataset!$I$2:$I$1501,MATCH($A74,customer_churn_dataset!$A$2:$A$1501,0)) -> 42.7 | F73: =INDEX(customer_churn_dataset!$L$2:$L$1501,MATCH($A74,customer_churn_dataset!$A$2:$A$1501,0)) -> 3 | G73: =IF(INDEX(customer_churn_dataset!$M$2:$M$1501,MATCH($A74,customer_churn_dataset!$A$2:$A$1501,0))=1,"Yes","No") -> No | H73: =INDEX(customer_churn_dataset!$N$2:$N$1501,MATCH($A74,customer_churn_dataset!$A$2:$A$1501,0)) -> 363.3 | I73: =INDEX(customer_churn_dataset!$O$2:$O$1501,MATCH($A74,customer_churn_dataset!$A$2:$A$1501,0)) -> 0 | J73: =INDEX(customer_churn_dataset!$T$2:$T$1501,MATCH($A74,customer_churn_dataset!$A$2:$A$1501,0)) -> 2 | K73: =INDEX(customer_churn_dataset!$V$2:$V$1501,MATCH($A74,customer_churn_dataset!$A$2:$A$1501,0)) -> Low Risk
A74: =customer_churn_dataset!A636 -> CUST101258 | B74: =customer_churn_dataset!B636 -> Basic | C74: =customer_churn_dataset!C636 -> Two year | D74: =INDEX(customer_churn_dataset!$E$2:$E$1501,MATCH($A75,customer_churn_dataset!$A$2:$A$1501,0)) -> 16 | E74: =INDEX(customer_churn_dataset!$I$2:$I$1501,MATCH($A75,customer_churn_dataset!$A$2:$A$1501,0)) -> 25 | F74: =INDEX(customer_churn_dataset!$L$2:$L$1501,MATCH($A75,customer_churn_dataset!$A$2:$A$1501,0)) -> 5 | G74: =IF(INDEX(customer_churn_dataset!$M$2:$M$1501,MATCH($A75,customer_churn_dataset!$A$2:$A$1501,0))=1,"Yes","No") -> Yes | H74: =INDEX(customer_churn_dataset!$N$2:$N$1501,MATCH($A75,customer_churn_dataset!$A$2:$A$1501,0)) -> 316.8 | I74: =INDEX(customer_churn_dataset!$O$2:$O$1501,MATCH($A75,customer_churn_dataset!$A$2:$A$1501,0)) -> 1 | J74: =INDEX(customer_churn_dataset!$T$2:$T$1501,MATCH($A75,customer_churn_dataset!$A$2:$A$1501,0)) -> 8 | K74: =INDEX(customer_churn_dataset!$V$2:$V$1501,MATCH($A75,customer_churn_dataset!$A$2:$A$1501,0)) -> High Risk
A75: =customer_churn_dataset!A646 -> CUST100159 | B75: =customer_churn_dataset!B646 -> Standard | C75: =customer_churn_dataset!C646 -> Month-to-month | D75: =INDEX(customer_churn_dataset!$E$2:$E$1501,MATCH($A76,customer_churn_dataset!$A$2:$A$1501,0)) -> 44 | E75: =INDEX(customer_churn_dataset!$I$2:$I$1501,MATCH($A76,customer_churn_dataset!$A$2:$A$1501,0)) -> 37 | F75: =INDEX(customer_churn_dataset!$L$2:$L$1501,MATCH($A76,customer_churn_dataset!$A$2:$A$1501,0)) -> 1 | G75: =IF(INDEX(customer_churn_dataset!$M$2:$M$1501,MATCH($A76,customer_churn_dataset!$A$2:$A$1501,0))=1,"Yes","No") -> Yes | H75: =INDEX(customer_churn_dataset!$N$2:$N$1501,MATCH($A76,customer_churn_dataset!$A$2:$A$1501,0)) -> 1726.12 | I75: =INDEX(customer_churn_dataset!$O$2:$O$1501,MATCH($A76,customer_churn_dataset!$A$2:$A$1501,0)) -> 0 | J75: =INDEX(customer_churn_dataset!$T$2:$T$1501,MATCH($A76,customer_churn_dataset!$A$2:$A$1501,0)) -> 7 | K75: =INDEX(customer_churn_dataset!$V$2:$V$1501,MATCH($A76,customer_churn_dataset!$A$2:$A$1501,0)) -> High Risk
A76: =customer_churn_dataset!A650 -> CUST100245 | B76: =customer_churn_dataset!B650 -> Premium | C76: =customer_churn_dataset!C650 -> Month-to-month | D76: =INDEX(customer_churn_dataset!$E$2:$E$1501,MATCH($A77,customer_churn_dataset!$A$2:$A$1501,0)) -> 14 | E76: =INDEX(customer_churn_dataset!$I$2:$I$1501,MATCH($A77,customer_churn_dataset!$A$2:$A$1501,0)) -> 51.5 | F76: =INDEX(customer_churn_dataset!$L$2:$L$1501,MATCH($A77,customer_churn_dataset!$A$2:$A$1501,0)) -> 1 | G76: =IF(INDEX(customer_churn_dataset!$M$2:$M$1501,MATCH($A77,customer_churn_dataset!$A$2:$A$1501,0))=1,"Yes","No") -> Yes | H76: =INDEX(customer_churn_dataset!$N$2:$N$1501,MATCH($A77,customer_churn_dataset!$A$2:$A$1501,0)) -> 144.34 | I76: =INDEX(customer_churn_dataset!$O$2:$O$1501,MATCH($A77,customer_churn_dataset!$A$2:$A$1501,0)) -> 0 | J76: =INDEX(customer_churn_dataset!$T$2:$T$1501,MATCH($A77,customer_churn_dataset!$A$2:$A$1501,0)) -> 6 | K76: =INDEX(customer_churn_dataset!$V$2:$V$1501,MATCH($A77,customer_churn_dataset!$A$2:$A$1501,0)) -> High Risk
A77: =customer_churn_dataset!A666 -> CUST100628 | B77: =customer_churn_dataset!B666 -> Basic | C77: =customer_churn_dataset!C666 -> Month-to-month | D77: =INDEX(customer_churn_dataset!$E$2:$E$1501,MATCH($A78,customer_churn_dataset!$A$2:$A$1501,0)) -> 54 | E77: =INDEX(customer_churn_dataset!$I$2:$I$1501,MATCH($A78,customer_churn_dataset!$A$2:$A$1501,0)) -> 75.1 | F77: =INDEX(customer_churn_dataset!$L$2:$L$1501,MATCH($A78,customer_churn_dataset!$A$2:$A$1501,0)) -> 2 | G77: =IF(INDEX(customer_churn_dataset!$M$2:$M$1501,MATCH($A78,customer_churn_dataset!$A$2:$A$1501,0))=1,"Yes","No") -> No | H77: =INDEX(customer_churn_dataset!$N$2:$N$1501,MATCH($A78,customer_churn_dataset!$A$2:$A$1501,0)) -> 633.96 | I77: =INDEX(customer_churn_dataset!$O$2:$O$1501,MATCH($A78,customer_churn_dataset!$A$2:$A$1501,0)) -> 1 | J77: =INDEX(customer_churn_dataset!$T$2:$T$1501,MATCH($A78,customer_churn_dataset!$A$2:$A$1501,0)) -> 2 | K77: =INDEX(customer_churn_dataset!$V$2:$V$1501,MATCH($A78,customer_churn_dataset!$A$2:$A$1501,0)) -> Low Risk
A78: =customer_churn_dataset!A700 -> CUST100049 | B78: =customer_churn_dataset!B700 -> Basic | C78: =customer_churn_dataset!C700 -> One year | D78: =INDEX(customer_churn_dataset!$E$2:$E$1501,MATCH($A79,customer_churn_dataset!$A$2:$A$1501,0)) -> 20 | E78: =INDEX(customer_churn_dataset!$I$2:$I$1501,MATCH($A79,customer_churn_dataset!$A$2:$A$1501,0)) -> 65.4 | F78: =INDEX(customer_churn_dataset!$L$2:$L$1501,MATCH($A79,customer_churn_dataset!$A$2:$A$1501,0)) -> 1 | G78: =IF(INDEX(customer_churn_dataset!$M$2:$M$1501,MATCH($A79,customer_churn_dataset!$A$2:$A$1501,0))=1,"Yes","No") -> No | H78: =INDEX(customer_churn_dataset!$N$2:$N$1501,MATCH($A79,customer_churn_dataset!$A$2:$A$1501,0)) -> 406.6 | I78: =INDEX(customer_churn_dataset!$O$2:$O$1501,MATCH($A79,customer_churn_dataset!$A$2:$A$1501,0)) -> 0 | J78: =INDEX(customer_churn_dataset!$T$2:$T$1501,MATCH($A79,customer_churn_dataset!$A$2:$A$1501,0)) -> 1 | K78: =INDEX(customer_churn_dataset!$V$2:$V$1501,MATCH($A79,customer_churn_dataset!$A$2:$A$1501,0)) -> Low Risk
A79: =customer_churn_dataset!A713 -> CUST100494 | B79: =customer_churn_dataset!B713 -> Standard | C79: =customer_churn_dataset!C713 -> One year | D79: =INDEX(customer_churn_dataset!$E$2:$E$1501,MATCH($A80,customer_churn_dataset!$A$2:$A$1501,0)) -> 72 | E79: =INDEX(customer_churn_dataset!$I$2:$I$1501,MATCH($A80,customer_churn_dataset!$A$2:$A$1501,0)) -> 33.9 | F79: =INDEX(customer_churn_dataset!$L$2:$L$1501,MATCH($A80,customer_churn_dataset!$A$2:$A$1501,0)) -> 1 | G79: =IF(INDEX(customer_churn_dataset!$M$2:$M$1501,MATCH($A80,customer_churn_dataset!$A$2:$A$1501,0))=1,"Yes","No") -> No | H79: =INDEX(customer_churn_dataset!$N$2:$N$1501,MATCH($A80,customer_churn_dataset!$A$2:$A$1501,0)) -> 719.28 | I79: =INDEX(customer_churn_dataset!$O$2:$O$1501,MATCH($A80,customer_churn_dataset!$A$2:$A$1501,0)) -> 0 | J79: =INDEX(customer_churn_dataset!$T$2:$T$1501,MATCH($A80,customer_churn_dataset!$A$2:$A$1501,0)) -> 4 | K79: =INDEX(customer_churn_dataset!$V$2:$V$1501,MATCH($A80,customer_churn_dataset!$A$2:$A$1501,0)) -> Medium Risk
A80: =customer_churn_dataset!A738 -> CUST101397 | B80: =customer_churn_dataset!B738 -> Basic | C80: =customer_churn_dataset!C738 -> Month-to-month | D80: =INDEX(customer_churn_dataset!$E$2:$E$1501,MATCH($A81,customer_churn_dataset!$A$2:$A$1501,0)) -> 34 | E80: =INDEX(customer_churn_dataset!$I$2:$I$1501,MATCH($A81,customer_churn_dataset!$A$2:$A$1501,0)) -> 81.2 | F80: =INDEX(customer_churn_dataset!$L$2:$L$1501,MATCH($A81,customer_churn_dataset!$A$2:$A$1501,0)) -> 2 | G80: =IF(INDEX(customer_churn_dataset!$M$2:$M$1501,MATCH($A81,customer_churn_dataset!$A$2:$A$1501,0))=1,"Yes","No") -> No | H80: =INDEX(customer_churn_dataset!$N$2:$N$1501,MATCH($A81,customer_churn_dataset!$A$2:$A$1501,0)) -> 388.96 | I80: =INDEX(customer_churn_dataset!$O$2:$O$1501,MATCH($A81,customer_churn_dataset!$A$2:$A$1501,0)) -> 0 | J80: =INDEX(customer_churn_dataset!$T$2:$T$1501,MATCH($A81,customer_churn_dataset!$A$2:$A$1501,0)) -> 3 | K80: =INDEX(customer_churn_dataset!$V$2:$V$1501,MATCH($A81,customer_churn_dataset!$A$2:$A$1501,0)) -> Medium Risk
A81: =customer_churn_dataset!A743 -> CUST100929 | B81: =customer_churn_dataset!B743 -> Basic | C81: =customer_churn_dataset!C743 -> Month-to-month | D81: =INDEX(customer_churn_dataset!$E$2:$E$1501,MATCH($A82,customer_churn_dataset!$A$2:$A$1501,0)) -> 2 | E81: =INDEX(customer_churn_dataset!$I$2:$I$1501,MATCH($A82,customer_churn_dataset!$A$2:$A$1501,0)) -> 73.6 | F81: =INDEX(customer_churn_dataset!$L$2:$L$1501,MATCH($A82,customer_churn_dataset!$A$2:$A$1501,0)) -> 2 | G81: =IF(INDEX(customer_churn_dataset!$M$2:$M$1501,MATCH($A82,customer_churn_dataset!$A$2:$A$1501,0))=1,"Yes","No") -> No | H81: =INDEX(customer_churn_dataset!$N$2:$N$1501,MATCH($A82,customer_churn_dataset!$A$2:$A$1501,0)) -> 81.38 | I81: =INDEX(customer_churn_dataset!$O$2:$O$1501,MATCH($A82,customer_churn_dataset!$A$2:$A$1501,0)) -> 0 | J81: =INDEX(customer_churn_dataset!$T$2:$T$1501,MATCH($A82,customer_churn_dataset!$A$2:$A$1501,0)) -> 4 | K81: =INDEX(customer_churn_dataset!$V$2:$V$1501,MATCH($A82,customer_churn_dataset!$A$2:$A$1501,0)) -> Medium Risk
